Workbook

Sheet TablasInformes (1)
B1: SparklingCo
A2: 0 | B2: Valor de la compania
C3: Total Compania | E3: Variacion
C4: 2028 | D4: 2027 | E4: Diferencia | F4: %
B5: GlobalBiz | C5: 5406 | D5: 5315 | E5: 91 | F5: 0.017
B6: FreshMarket | C6: 5463 | D6: 5279 | E6: 184 | F6: 0.035
B7: SparklingCo | C7: 5104 | D7: 4815 | E7: 289 | F7: 0.06
B8: QualityMax | C8: 5344 | D8: 5079 | E8: 265 | F8: 0.052
B9: Drink2Go | C9: 4697 | D9: 5314 | E9: -617 | F9: -0.116
B10: Media | C10: 5203 | D10: 5161 | E10: 42 | F10: 0.008
A12: Comparativa Valor Compania. 1
A13: 1 | B13: 2023 | C13: 2024 | D13: 2025 | E13: 2026 | F13: 2027 | G13: 2028
A14: GlobalBiz | B14: 4118.8 | C14: 4491.6 | D14: 4646 | E14: 5061 | F14: 5315.5 | G14: 5406.1
A15: FreshMarket | B15: 4118.8 | C15: 4392.1 | D15: 4736.3 | E15: 5139.4 | F15: 5279 | G15: 5462.8
A16: SparklingCo | B16: 4118.8 | C16: 3910.9 | D16: 3825.2 | E16: 4384.7 | F16: 4815.2 | G16: 5103.8
A17: QualityMax | B17: 4118.8 | C17: 4073.1 | D17: 4470.4 | E17: 4796.8 | F17: 5079.4 | G17: 5344.4
A18: Drink2Go | B18: 4118.8 | C18: 4538 | D18: 5089.3 | E18: 5223.1 | F18: 5314.2 | G18: 4696.8
A21: Analisis valor compania.
A22: Ponderacion media parametros.
A23: 2 | B23: 2023 | C23: 2024 | D23: 2025 | E23: 2026 | F23: 2027 | G23: 2028
B24: Ponderacion Media | C24: Ponderacion Media | D24: Ponderacion Media | E24: Ponderacion Media | F24: Ponderacion Media | G24: Ponderacion Media
A25: Resultados Economicos | B25: 1925 | C25: 2056 | D25: 2301 | E25: 2587 | F25: 2779 | G25: 2769
A26: Patrimonio - Solvencia | B26: 272 | C26: 245 | D26: 247 | E26: 275 | F26: 278 | G26: 278
A27: Participacion de Mercado | B27: 458 | C27: 462 | D27: 467 | E27: 470 | F27: 478 | G27: 482
A28: Valor de Marca | B28: 408 | C28: 444 | D28: 435 | E28: 443 | F28: 441 | G28: 462
A29: Valor de Producto | B29: 495 | C29: 500 | D29: 504 | E29: 513 | F29: 521 | G29: 527
A30: Cobertura de Distribucion | B30: 296 | C30: 295 | D30: 296 | E30: 295 | F30: 298 | G30: 300
A31: Tecnologia Industrial | B31: 264 | C31: 280 | D31: 304 | E31: 337 | F31: 365 | G31: 386
A34: Variacion Valor Compañia
B35: Primer año | C35: Diferencia 1 | D35: Diferencia 2 | E35: Diferencia 3 | F35: Diferencia 4 | G35: Diferencia 5 | H35: Ano actual
A36: GlobalBiz | B36: 4119 | C36: 373 | D36: 154 | E36: 415 | F36: 254 | G36: 91 | H36: 5406
A37: FreshMarket | B37: 4119 | C37: 273 | D37: 344 | E37: 403 | F37: 140 | G37: 184 | H37: 5463
A38: SparklingCo | B38: 4119 | C38: -208 | D38: -86 | E38: 559 | F38: 431 | G38: 289 | H38: 5104
A39: QualityMax | B39: 4119 | C39: -46 | D39: 397 | E39: 326 | F39: 283 | G39: 265 | H39: 5344
A40: Drink2Go | B40: 4119 | C40: 419 | D40: 551 | E40: 134 | F40: 91 | G40: -617 | H40: 4697
A42: Analisis valor compania. Comparativa.
A43: 3 | B43: GlobalBiz | C43: FreshMarket | D43: SparklingCo | E43: QualityMax | F43: Drink2Go
A44: Resultados Economicos | B44: 3021 | C44: 3056 | D44: 2626 | E44: 2984 | F44: 2156
A45: Patrimonio - Solvencia | B45: 229 | C45: 229 | D45: 358 | E45: 309 | F45: 263
A46: Participacion de Mercado | B46: 501 | C46: 467 | D46: 472 | E46: 477 | F46: 491
A47: Valor de Marca | B47: 448 | C47: 525 | D47: 405 | E47: 405 | F47: 525
A48: Valor de Producto | B48: 539 | C48: 529 | D48: 520 | E48: 520 | F48: 529
A49: Capacidad - Cobertura | B49: 273 | C49: 305 | D49: 327 | E49: 254 | F49: 337
A50: Desarrollo Tecno - Eficiencia Prod | B50: 395 | C50: 352 | D50: 395 | E50: 395 | F50: 395
A51: No Decision | B51: 100 | C51: 100 | D51: 100 | E51: 100 | F51: 100
A52: Valor Compania | B52: 5406 | C52: 5463 | D52: 5104 | E52: 5344 | F52: 4697
A55: Valores del Escenario
A56: 4 | C56: Periodo Actual | D56: T+1 | E56: T+2
A57: Indice de Precios al Consumo | B57: Espana | C57: 30 | D57: 26 | E57: 24
B58: Portugal | C58: 25 | D58: 23 | E58: 21
B59: Francia | C59: 26 | D59: 19 | E59: 20
B60: Italia | C60: 27 | D60: 22 | E60: 24
B61: Centro Europa | C61: 11 | D61: 12 | E61: 18
B62: Polonia | C62: 26 | D62: 19 | E62: 16
B63: Mexico | C63: 41 | D63: 32 | E63: 35
A64: Producto Interior Bruto | B64: Espana | C64: 27 | D64: 23 | E64: 21
B65: Portugal | C65: 27 | D65: 22 | E65: 18
B66: Francia | C66: 22 | D66: 16 | E66: 21
B67: Italia | C67: 24 | D67: 19 | E67: 23
B68: Centro Europa | C68: 9 | D68: 15 | E68: 22
B69: Polonia | C69: 31 | D69: 23 | E69: 18
B70: Mexico | C70: 28 | D70: 21 | E70: 23
A71: Tipo de Interes | B71: Espana | C71: 24 | D71: 0 | E71: 0
B72: Marruecos | C72: 36 | D72: 0 | E72: 0
B73: Mexico | C73: 52 | D73: 0 | E73: 0
B74: China | C74: 55 | D74: 0 | E74: 0
A77: 5 | B77: Indicadores Clave de la Compania Drink2Go
C78: Ano 0 | D78: Ano -1 | E78: Diferencia | F78: Variacion
B79: Unidades Vendidas | C79: 10555331 | D79: 10146898 | E79: 408433 | F79: 0.4
B80: Participacion de Mercado | C80: 1.68 | D80: 1.65 | E80: 0 | F80: 0.18
B81: Ingresos | C81: 21517990 | D81: 19829118 | E81: 1688872 | F81: 0.85
B82: Resultado Bruto | C82: -188802 | D82: 2403283 | E82: -2592084 | F82: -10.79
B83: Ratio Resultado Bruto sobre Ingresos- | C83: -0.09 | D83: 1.21 | E83: -130 | F83: -10.73
B84: Resultado Neto | C84: -1479023 | D84: 1244268 | E84: -2723291 | F84: -21.89
B85: Rentabilidad sobre Patrimonio Neto - | C85: -0.78 | D85: 0.45 | E85: -123 | F85: -27.35
B86: Rendimiento del Activo | C86: -0.07 | D86: 0.83 | E86: -89 | F86: -10.79
B87: Total Pasivo sobre Patrimonio | C87: 0.05 | D87: 0.04 | E87: 1 | F87: 3.25
B88: Capacidad Fabricacion Total - Litro o Kilo | C88: 10785200 | D88: 10511000 | E88: 274200 | F88: 0.26
B89: Tasa Ocupacion Fabricas - | C89: 9.9 | D89: 9.77 | E89: 13 | F89: 0.13
B90: Unidades Inventario sobre Ventas - | C90: 1.2 | D90: 1.11 | E90: 8 | F90: 0.76
... B94: Cobertura Distribucion - escala 1 a 100- | C94: 4.11 | D94: 4.12 | E94: 0 | F94: -0.02
A97: Indicadores Clave de la Compania.
A98: 6 | B98: GlobalBiz | C98: FreshMarket | D98: SparklingCo | E98: QualityMax | F98: Drink2Go
A99: Unidades Vendidas | B99: 13710419 | C99: 14426726 | D99: 13502462 | E99: 10643463 | F99: 10555331
A100: Cuota de Mercado | B100: 2.18 | C100: 2.3 | D100: 2.15 | E100: 1.69 | F100: 1.68
A101: Ingresos | B101: 27027948 | C101: 23052926 | D101: 20193200 | E101: 20913542 | F101: 21517990
A102: Resultado Bruto | B102: 8648527 | C102: 6561048 | D102: 5140601 | E102: 7171972 | F102: -188802
A103: Ratio Beneficio Bruto sobre Ingresos- | B103: 3.2 | C103: 2.85 | D103: 2.55 | E103: 3.43 | F103: -0.09
A104: Resultado Neto | B104: 6991802 | C104: 4827083 | D104: 3309868 | E104: 6033841 | F104: -1479023
A105: Rentabilidad sobre Patrimonio Neto - | B105: 1.7 | C105: 1.19 | D105: 1.26 | E105: 1.49 | F105: -0.78
A106: Rendimiento del Activo | B106: 1.91 | C106: 1.46 | D106: 1.43 | E106: 1.87 | F106: -0.07
A107: Total Pasivo sobre Patrimonio | B107: 5 | C107: 5 | D107: 8 | E107: 3 | F107: 5
A108: Capacidad Fabricacion Total | B108: 13481500 | C108: 16177800 | D108: 13481500 | E108: 10785200 | F108: 10785200
A109: Tasa Ocupacion Fabricas - | B109: 10 | C109: 8.97 | D109: 10 | E109: 9.91 | F109: 9.9
A110: Unidades Inventario sobre Ventas - | B110: 0.71 | C110: 0.8 | D110: 0.71 | E110: 0.79 | F110: 1.2
... A114: Cobertura Distribucion - escala 1 a 100- | B114: 2.59 | C114: 3.17 | D114: 3.78 | E114: 1.92 | F114: 4.11
A117: Indicadores Clave de la Compania Drink2Go
A118: 7 | B118: 2023 | C118: 2024 | D118: 2025 | E118: 2026 | F118: 2027 | G118: 2028
A120: Unidades Vendidas | B120: 6641121 | C120: 6841045 | D120: 8078565 | E120: 8686200 | F120: 10146898 | G120: 10555331 | H120: **** | J120: mercado y finanzas
A121: Participacion de Mercado | B121: 0.2 | C121: 0.187 | D121: 0.17 | E121: 0.155 | F121: 0.165 | G121: 0.168
...

Sheet 1
A1: 0
A2: Valor de la compania
B3: Total Compania | D3: Variacion
B4: Año T | C4: Año T-1 | D4: Diferencia | E4: % Variacion
A5: GlobalBiz | B5: =+'TablasInformes (1)'!C5 -> 5406 | C5: =+'TablasInformes (1)'!D5 -> 5315 | D5: =+'TablasInformes (1)'!E5 -> 91 | E5: =+'TablasInformes (1)'!F5 -> 0.017
A6: FreshMarket | B6: =+'TablasInformes (1)'!C6 -> 5463 | C6: =+'TablasInformes (1)'!D6 -> 5279 | D6: =+'TablasInformes (1)'!E6 -> 184 | E6: =+'TablasInformes (1)'!F6 -> 0.035
A7: SparklingCo | B7: =+'TablasInformes (1)'!C7 -> 5104 | C7: =+'TablasInformes (1)'!D7 -> 4815 | D7: =+'TablasInformes (1)'!E7 -> 289 | E7: =+'TablasInformes (1)'!F7 -> 0.06
A8: QualityMax | B8: =+'TablasInformes (1)'!C8 -> 5344 | C8: =+'TablasInformes (1)'!D8 -> 5079 | D8: =+'TablasInformes (1)'!E8 -> 265 | E8: =+'TablasInformes (1)'!F8 -> 0.052
A9: Drink2Go | B9: =+'TablasInformes (1)'!C9 -> 4697 | C9: =+'TablasInformes (1)'!D9 -> 5314 | D9: =+'TablasInformes (1)'!E9 -> -617 | E9: =+'TablasInformes (1)'!F9 -> -0.116
A10: Media | B10: =+'TablasInformes (1)'!C10 -> 5203 | C10: =+'TablasInformes (1)'!D10 -> 5161 | D10: =+'TablasInformes (1)'!E10 -> 42 | E10: =+'TablasInformes (1)'!F10 -> 0.008
A25: 1
A26: Comparativa Valor Compania.
B27: =+'TablasInformes (1)'!B13 -> 2023 | C27: =+'TablasInformes (1)'!C13 -> 2024 | D27: =+'TablasInformes (1)'!D13 -> 2025 | E27: =+'TablasInformes (1)'!E13 -> 2026 | F27: =+'TablasInformes (1)'!F13 -> 2027 | G27: =+'TablasInformes (1)'!G13 -> 2028
A28: =+'TablasInformes (1)'!A14 -> GlobalBiz | B28: =+'TablasInformes (1)'!B14 -> 4118.8 | C28: =+'TablasInformes (1)'!C14 -> 4491.6 | D28: =+'TablasInformes (1)'!D14 -> 4646 | E28: =+'TablasInformes (1)'!E14 -> 5061 | F28: =+'TablasInformes (1)'!F14 -> 5315.5 | G28: =+'TablasInformes (1)'!G14 -> 5406.1
A29: =+'TablasInformes (1)'!A15 -> FreshMarket | B29: =+'TablasInformes (1)'!B15 -> 4118.8 | C29: =+'TablasInformes (1)'!C15 -> 4392.1 | D29: =+'TablasInformes (1)'!D15 -> 4736.3 | E29: =+'TablasInformes (1)'!E15 -> 5139.4 | F29: =+'TablasInformes (1)'!F15 -> 5279 | G29: =+'TablasInformes (1)'!G15 -> 5462.8
A30: =+'TablasInformes (1)'!A16 -> SparklingCo | B30: =+'TablasInformes (1)'!B16 -> 4118.8 | C30: =+'TablasInformes (1)'!C16 -> 3910.9 | D30: =+'TablasInformes (1)'!D16 -> 3825.2 | E30: =+'TablasInformes (1)'!E16 -> 4384.7 | F30: =+'TablasInformes (1)'!F16 -> 4815.2 | G30: =+'TablasInformes (1)'!G16 -> 5103.8
A31: =+'TablasInformes (1)'!A17 -> QualityMax | B31: =+'TablasInformes (1)'!B17 -> 4118.8 | C31: =+'TablasInformes (1)'!C17 -> 4073.1 | D31: =+'TablasInformes (1)'!D17 -> 4470.4 | E31: =+'TablasInformes (1)'!E17 -> 4796.8 | F31: =+'TablasInformes (1)'!F17 -> 5079.4 | G31: =+'TablasInformes (1)'!G17 -> 5344.4
B32: =+'TablasInformes (1)'!B18 -> 4118.8 | C32: =+'TablasInformes (1)'!C18 -> 4538 | D32: =+'TablasInformes (1)'!D18 -> 5089.3 | E32: =+'TablasInformes (1)'!E18 -> 5223.1 | F32: =+'TablasInformes (1)'!F18 -> 5314.2 | G32: =+'TablasInformes (1)'!G18 -> 4696.8
C33: =+B32*1.07 -> 4407.116 | D33: =+C32*1.07 -> 4855.66 | E33: =+D32*1.07 -> 5445.551 | F33: =+E32*1.07 -> 5588.717 | G33: =+F32*1.07 -> 5686.194
B34: =+'TablasInformes (1)'!A18 -> Drink2Go | C34: =(C32-B32)/B32 -> 0.10177722 | D34: =(D32-C32)/C32 -> 0.12148524 | E34: =(E32-D32)/D32 -> 0.026290453 | F34: =(F32-E32)/E32 -> 0.017441749 | G34: =(G32-F32)/F32 -> -0.11617929
E35: =SUM(C34:G34)/5 -> 0.030163072
B38: GlobalBiz | C38: FreshMarket | D38: SparklingCo | E38: QualityMax | F38: Drink2Go
A39: =+B27 -> 2023 | B39: =+B28 -> 4118.8 | C39: =+B29 -> 4118.8 | D39: =+B30 -> 4118.8 | E39: =+B31 -> 4118.8 | F39: =+B32 -> 4118.8
A40: =+C27 -> 2024 | B40: =+C28 -> 4491.6 | C40: =+C29 -> 4392.1 | D40: =+C30 -> 3910.9 | E40: =+C31 -> 4073.1 | F40: =+C32 -> 4538
A41: =+D27 -> 2025 | B41: =+D28 -> 4646 | C41: =+D29 -> 4736.3 | D41: =+D30 -> 3825.2 | E41: =+D31 -> 4470.4 | F41: =+D32 -> 5089.3
A42: =+E27 -> 2026 | B42: =+E28 -> 5061 | C42: =+E29 -> 5139.4 | D42: =+E30 -> 4384.7 | E42: =+E31 -> 4796.8 | F42: =+E32 -> 5223.1
A43: =+F27 -> 2027 | B43: =+F28 -> 5315.5 | C43: =+F29 -> 5279 | D43: =+F30 -> 4815.2 | E43: =+F31 -> 5079.4 | F43: =+F32 -> 5314.2
A44: =+G27 -> 2028 | B44: =+G28 -> 5406.1 | C44: =+G29 -> 5462.8 | D44: =+G30 -> 5103.8 | E44: =+G31 -> 5344.4 | F44: =+G32 -> 4696.8
B47: =+B38 -> GlobalBiz
A48: =+A39 -> 2023 | B48: =+B39 -> 4118.8
A49: =+A40 -> 2024 | B49: =+B40 -> 4491.6
A50: =+A41 -> 2025 | B50: =+B41 -> 4646
A51: =+A42 -> 2026 | B51: =+B42 -> 5061
A52: =+A43 -> 2027 | B52: =+B43 -> 5315.5
A53: =+A44 -> 2028 | B53: =+B44 -> 5406.1
B62: FreshMarket
A63: =+A48 -> 2023 | B63: =+C39 -> 4118.8
A64: =+A49 -> 2024 | B64: =+C40 -> 4392.1
A65: =+A50 -> 2025 | B65: =+C41 -> 4736.3
A66: =+A51 -> 2026 | B66: =+C42 -> 5139.4
A67: =+A52 -> 2027 | B67: =+C43 -> 5279
A68: =+A53 -> 2028 | B68: =+C44 -> 5462.8
B72: SparklingCo
A73: =+A63 -> 2023 | B73: =+D39 -> 4118.8
A74: =+A64 -> 2024 | B74: =+D40 -> 3910.9
A75: =+A65 -> 2025 | B75: =+D41 -> 3825.2
A76: =+A66 -> 2026 | B76: =+D42 -> 4384.7
A77: =+A67 -> 2027 | B77: =+D43 -> 4815.2
A78: =+A68 -> 2028 | B78: =+D44 -> 5103.8
B82: QualityMax
A83: =+A73 -> 2023 | B83: =+E39 -> 4118.8
A84: =+A74 -> 2024 | B84: =+E40 -> 4073.1
A85: =+A75 -> 2025 | B85: =+E41 -> 4470.4
A86: =+A76 -> 2026 | B86: =+E42 -> 4796.8
A87: =+A77 -> 2027 | B87: =+E43 -> 5079.4
A88: =+A78 -> 2028 | B88: =+E44 -> 5344.4
B93: Drink2Go
A94: =+A83 -> 2023 | B94: =+F39 -> 4118.8
A95: =+A84 -> 2024 | B95: =+F40 -> 4538
A96: =+A85 -> 2025 | B96: =+F41 -> 5089.3
A97: =+A86 -> 2026 | B97: =+F42 -> 5223.1
A98: =+A87 -> 2027 | B98: =+F43 -> 5314.2
A99: =+A88 -> 2028 | B99: =+F44 -> 4696.8

Sheet 2
A1: 2
A2: Analisis valor compania.
A3: Ponderacion Media de los parametros.
B4: =+'TablasInformes (1)'!B23 -> 2023 | C4: =+'TablasInformes (1)'!C23 -> 2024 | D4: =+'TablasInformes (1)'!D23 -> 2025 | E4: =+'TablasInformes (1)'!E23 -> 2026 | F4: =+'TablasInformes (1)'!F23 -> 2027 | G4: =+'TablasInformes (1)'!G23 -> 2028 | H4: COMPORTAMIENTO GRÁFICO
B5: =+'TablasInformes (1)'!B24 -> Ponderacion Media | C5: =+'TablasInformes (1)'!C24 -> Ponderacion Media | D5: =+'TablasInformes (1)'!D24 -> Ponderacion Media | E5: =+'TablasInformes (1)'!E24 -> Ponderacion Media | F5: =+'TablasInformes (1)'!F24 -> Ponderacion Media | G5: =+'TablasInformes (1)'!G24 -> Ponderacion Media
A6: Resultados Economicos | B6: =+'TablasInformes (1)'!B25 -> 1925 | C6: =+'TablasInformes (1)'!C25 -> 2056 | D6: =+'TablasInformes (1)'!D25 -> 2301 | E6: =+'TablasInformes (1)'!E25 -> 2587 | F6: =+'TablasInformes (1)'!F25 -> 2779 | G6: =+'TablasInformes (1)'!G25 -> 2769
A7: Patrimonio - Solvencia | B7: =+'TablasInformes (1)'!B26 -> 272 | C7: =+'TablasInformes (1)'!C26 -> 245 | D7: =+'TablasInformes (1)'!D26 -> 247 | E7: =+'TablasInformes (1)'!E26 -> 275 | F7: =+'TablasInformes (1)'!F26 -> 278 | G7: =+'TablasInformes (1)'!G26 -> 278
A8: Participacion de Mercado | B8: =+'TablasInformes (1)'!B27 -> 458 | C8: =+'TablasInformes (1)'!C27 -> 462 | D8: =+'TablasInformes (1)'!D27 -> 467 | E8: =+'TablasInformes (1)'!E27 -> 470 | F8: =+'TablasInformes (1)'!F27 -> 478 | G8: =+'TablasInformes (1)'!G27 -> 482
A9: Valor de Marca | B9: =+'TablasInformes (1)'!B28 -> 408 | C9: =+'TablasInformes (1)'!C28 -> 444 | D9: =+'TablasInformes (1)'!D28 -> 435 | E9: =+'TablasInformes (1)'!E28 -> 443 | F9: =+'TablasInformes (1)'!F28 -> 441 | G9: =+'TablasInformes (1)'!G28 -> 462
A10: Valor de Producto | B10: =+'TablasInformes (1)'!B29 -> 495 | C10: =+'TablasInformes (1)'!C29 -> 500 | D10: =+'TablasInformes (1)'!D29 -> 504 | E10: =+'TablasInformes (1)'!E29 -> 513 | F10: =+'TablasInformes (1)'!F29 -> 521 | G10: =+'TablasInformes (1)'!G29 -> 527
A11: Cobertura de Distribucion | B11: =+'TablasInformes (1)'!B30 -> 296 | C11: =+'TablasInformes (1)'!C30 -> 295 | D11: =+'TablasInformes (1)'!D30 -> 296 | E11: =+'TablasInformes (1)'!E30 -> 295 | F11: =+'TablasInformes (1)'!F30 -> 298 | G11: =+'TablasInformes (1)'!G30 -> 300
A12: Tecnologia Industrial | B12: =+'TablasInformes (1)'!B31 -> 264 | C12: =+'TablasInformes (1)'!C31 -> 280 | D12: =+'TablasInformes (1)'!D31 -> 304 | E12: =+'TablasInformes (1)'!E31 -> 337 | F12: =+'TablasInformes (1)'!F31 -> 365 | G12: =+'TablasInformes (1)'!G31 -> 386
A15: Ge | B15: Resultados Economicos
A16: =+B4 -> 2023 | B16: =+B6 -> 1925 | D16: 0.076425596
A17: =+C4 -> 2024 | B17: =+C6 -> 2056 | C17: =(B17-B16)/B16 -> 0.068051948 | D17: 0.076425596
A18: =+D4 -> 2025 | B18: =+D6 -> 2301 | C18: =(B18-B17)/B17 -> 0.11916342 | D18: 0.076425596
A19: =+E4 -> 2026 | B19: =+E6 -> 2587 | C19: =(B19-B18)/B18 -> 0.12429379 | D19: 0.076425596
A20: =+F4 -> 2027 | B20: =+F6 -> 2779 | C20: =(B20-B19)/B19 -> 0.07421724 | D20: 0.076425596
A21: =+G4 -> 2028 | B21: =+G6 -> 2769 | C21: =(B21-B20)/B20 -> -0.0035984167 | D21: 0.076425596
C22: =AVERAGE(C17:C21) -> 0.076425596
B24: =+A7 -> Patrimonio - Solvencia
A25: =+A16 -> 2023 | B25: =+B7 -> 272
A26: =+A17 -> 2024 | B26: =+C7 -> 245
A27: =+A18 -> 2025 | B27: =+D7 -> 247
A28: =+A19 -> 2026 | B28: =+E7 -> 275
A29: =+A20 -> 2027 | B29: =+F7 -> 278
A30: =+A21 -> 2028 | B30: =+G7 -> 278
B33: =+A8 -> Participacion de Mercado
A34: =+A25 -> 2023 | B34: =+B8 -> 458
A35: =+A26 -> 2024 | B35: =+C8 -> 462
A36: =+A27 -> 2025 | B36: =+D8 -> 467
A37: =+A28 -> 2026 | B37: =+E8 -> 470
A38: =+A29 -> 2027 | B38: =+F8 -> 478
A39: =+A30 -> 2028 | B39: =+G8 -> 482
B42: =+A9 -> Valor de Marca
A43: =+A34 -> 2023 | B43: =+B9 -> 408
A44: =+A35 -> 2024 | B44: =+C9 -> 444
A45: =+A36 -> 2025 | B45: =+D9 -> 435
A46: =+A37 -> 2026 | B46: =+E9 -> 443
A47: =+A38 -> 2027 | B47: =+F9 -> 441
A48: =+A39 -> 2028 | B48: =+G9 -> 462
B51: =+A10 -> Valor de Producto
A52: =+A43 -> 2023 | B52: =+B10 -> 495
A53: =+A44 -> 2024 | B53: =+C10 -> 500
A54: =+A45 -> 2025 | B54: =+D10 -> 504
A55: =+A46 -> 2026 | B55: =+E10 -> 513
A56: =+A47 -> 2027 | B56: =+F10 -> 521
A57: =+A48 -> 2028 | B57: =+G10 -> 527
B61: =+A11 -> Cobertura de Distribucion
A62: =+A52 -> 2023 | B62: =+B11 -> 296
A63: =+A53 -> 2024 | B63: =+C11 -> 295
A64: =+A54 -> 2025 | B64: =+D11 -> 296
A65: =+A55 -> 2026 | B65: =+E11 -> 295
A66: =+A56 -> 2027 | B66: =+F11 -> 298
A67: =+A57 -> 2028 | B67: =+G11 -> 300
B70: Tecnologia Industrial
A71: =+A62 -> 2023 | B71: =+B12 -> 264
A72: =+A63 -> 2024 | B72: =+C12 -> 280
A73: =+A64 -> 2025 | B73: =+D12 -> 304
A74: =+A65 -> 2026 | B74: =+E12 -> 337
A75: =+A66 -> 2027 | B75: =+F12 -> 365
A76: =+A67 -> 2028 | B76: =+G12 -> 386

Sheet 3
A1: 3
A2: Analisis valor compania. Comparativa.
B3: =+'TablasInformes (1)'!B43 -> GlobalBiz | C3: =+'TablasInformes (1)'!C43 -> FreshMarket | D3: =+'TablasInformes (1)'!D43 -> SparklingCo | E3: =+'TablasInformes (1)'!E43 -> QualityMax | F3: =+'TablasInformes (1)'!F43 -> Drink2Go | M3: =+A4 -> Resultados Economicos
A4: Resultados Economicos | B4: =+'TablasInformes (1)'!B44 -> 3021 | C4: =+'TablasInformes (1)'!C44 -> 3056 | D4: =+'TablasInformes (1)'!D44 -> 2626 | E4: =+'TablasInformes (1)'!E44 -> 2984 | F4: =+'TablasInformes (1)'!F44 -> 2156 | L4: =+B3 -> GlobalBiz | M4: =+B4 -> 3021
A5: Patrimonio - Solvencia | B5: =+'TablasInformes (1)'!B45 -> 229 | C5: =+'TablasInformes (1)'!C45 -> 229 | D5: =+'TablasInformes (1)'!D45 -> 358 | E5: =+'TablasInformes (1)'!E45 -> 309 | F5: =+'TablasInformes (1)'!F45 -> 263 | L5: =+C3 -> FreshMarket | M5: =+C4 -> 3056
A6: Participacion de Mercado | B6: =+'TablasInformes (1)'!B46 -> 501 | C6: =+'TablasInformes (1)'!C46 -> 467 | D6: =+'TablasInformes (1)'!D46 -> 472 | E6: =+'TablasInformes (1)'!E46 -> 477 | F6: =+'TablasInformes (1)'!F46 -> 491 | L6: =+D3 -> SparklingCo | M6: =+D4 -> 2626
A7: Valor de Marca | B7: =+'TablasInformes (1)'!B47 -> 448 | C7: =+'TablasInformes (1)'!C47 -> 525 | D7: =+'TablasInformes (1)'!D47 -> 405 | E7: =+'TablasInformes (1)'!E47 -> 405 | F7: =+'TablasInformes (1)'!F47 -> 525 | L7: =+E3 -> QualityMax | M7: =+E4 -> 2984
A8: Valor de Producto | B8: =+'TablasInformes (1)'!B48 -> 539 | C8: =+'TablasInformes (1)'!C48 -> 529 | D8: =+'TablasInformes (1)'!D48 -> 520 | E8: =+'TablasInformes (1)'!E48 -> 520 | F8: =+'TablasInformes (1)'!F48 -> 529 | L8: =+F3 -> Drink2Go | M8: =+F4 -> 2156
A9: Capacidad - Cobertura | B9: =+'TablasInformes (1)'!B49 -> 273 | C9: =+'TablasInformes (1)'!C49 -> 305 | D9: =+'TablasInformes (1)'!D49 -> 327 | E9: =+'TablasInformes (1)'!E49 -> 254 | F9: =+'TablasInformes (1)'!F49 -> 337
A10: Desarrollo Tecno - Eficiencia Prod | B10: =+'TablasInformes (1)'!B50 -> 395 | C10: =+'TablasInformes (1)'!C50 -> 352 | D10: =+'TablasInformes (1)'!D50 -> 395 | E10: =+'TablasInformes (1)'!E50 -> 395 | F10: =+'TablasInformes (1)'!F50 -> 395
A11: No Decision | B11: =+'TablasInformes (1)'!B51 -> 100 | C11: =+'TablasInformes (1)'!C51 -> 100 | D11: =+'TablasInformes (1)'!D51 -> 100 | E11: =+'TablasInformes (1)'!E51 -> 100 | F11: =+'TablasInformes (1)'!F51 -> 100
A12: Valor Compania | B12: =+'TablasInformes (1)'!B52 -> 5406 | C12: =+'TablasInformes (1)'!C52 -> 5463 | D12: =+'TablasInformes (1)'!D52 -> 5104 | E12: =+'TablasInformes (1)'!E52 -> 5344 | F12: =+'TablasInformes (1)'!F52 -> 4697
B15: GlobalBiz
A16: Resultados Economicos | B16: =+B4 -> 3021 | M16: =+A5 -> Patrimonio - Solvencia
A17: Patrimonio - Solvencia | B17: =+B5 -> 229 | L17: =+B3 -> GlobalBiz | M17: =+B5 -> 229
A18: Participacion de Mercado | B18: =+B6 -> 501 | L18: =+C3 -> FreshMarket | M18: =+C5 -> 229
A19: Valor de Marca | B19: =+B7 -> 448 | L19: =+D3 -> SparklingCo | M19: =+D5 -> 358
A20: Valor de Producto | B20: =+B8 -> 539 | L20: =+E3 -> QualityMax | M20: =+E5 -> 309
A21: Capacidad - Cobertura | B21: =+B9 -> 273 | L21: =+F3 -> Drink2Go | M21: =+F5 -> 263
A22: Desarrollo Tecno - Eficiencia Prod | B22: =+B10 -> 395
A23: No Decision | B23: =+B11 -> 100
A24: Valor Compania | B24: =+B12 -> 5406
B27: FreshMarket
A28: Resultados Economicos | B28: =+C4 -> 3056
A29: Patrimonio - Solvencia | B29: =+C5 -> 229
A30: Participacion de Mercado | B30: =+C6 -> 467 | M30: =+A6 -> Participacion de Mercado
A31: Valor de Marca | B31: =+C7 -> 525 | L31: GlobalBiz | M31: =+B6 -> 501
A32: Valor de Producto | B32: =+C8 -> 529 | L32: FreshMarket | M32: =+C6 -> 467
A33: Capacidad - Cobertura | B33: =+C9 -> 305 | L33: SparklingCo | M33: =+D6 -> 472
A34: Desarrollo Tecno - Eficiencia Prod | B34: =+C10 -> 352 | L34: QualityMax | M34: =+E6 -> 477
A35: No Decision | B35: =+C11 -> 100 | L35: Drink2Go | M35: =+F6 -> 491
A36: Valor Compania | B36: =+C12 -> 5463
B39: SparklingCo
A40: Resultados Economicos | B40: 2626
A41: Patrimonio - Solvencia | B41: 358
A42: Participacion de Mercado | B42: 472
A43: Valor de Marca | B43: 405
A44: Valor de Producto | B44: 520 | M44: =+A7 -> Valor de Marca
A45: Capacidad - Cobertura | B45: 327 | L45: GlobalBiz | M45: =+B7 -> 448
A46: Desarrollo Tecno - Eficiencia Prod | B46: 395 | L46: FreshMarket | M46: =+C7 -> 525
A47: No Decision | B47: 100 | L47: SparklingCo | M47: =+D7 -> 405
A48: Valor Compania | B48: 5104 | L48: QualityMax | M48: =+E7 -> 405
L49: Drink2Go | M49: =+F7 -> 525
B51: QualityMax
A52: Resultados Economicos | B52: 2984
A53: Patrimonio - Solvencia | B53: 309
A54: Participacion de Mercado | B54: 477
A55: Valor de Marca | B55: 405 | M55: =+A8 -> Valor de Producto
A56: Valor de Producto | B56: 520 | L56: GlobalBiz | M56: =+B8 -> 539
A57: Capacidad - Cobertura | B57: 254 | L57: FreshMarket | M57: =+C8 -> 529
A58: Desarrollo Tecno - Eficiencia Prod | B58: 395 | L58: SparklingCo | M58: =+D8 -> 520
A59: No Decision | B59: 100 | L59: QualityMax | M59: =+E8 -> 520
A60: Valor Compania | B60: 5344 | L60: Drink2Go | M60: =+F8 -> 529
B63: Drink2Go
A64: Resultados Economicos | B64: 2156
A65: Patrimonio - Solvencia | B65: 263
A66: Participacion de Mercado | B66: 491
A67: Valor de Marca | B67: 525 | M67: =+A9 -> Capacidad - Cobertura
A68: Valor de Producto | B68: 529 | L68: GlobalBiz | M68: =+B9 -> 273
A69: Capacidad - Cobertura | B69: 337 | L69: FreshMarket | M69: =+C9 -> 305
A70: Desarrollo Tecno - Eficiencia Prod | B70: 395 | L70: SparklingCo | M70: =+D9 -> 327
A71: No Decision | B71: 100 | L71: QualityMax | M71: =+E9 -> 254
A72: Valor Compania | B72: 4697 | L72: Drink2Go | M72: =+F9 -> 337
M79: =+A10 -> Desarrollo Tecno - Eficiencia Prod
L80: GlobalBiz | M80: =+B10 -> 395
L81: FreshMarket | M81: =+C10 -> 352
L82: SparklingCo | M82: =+D10 -> 395
L83: QualityMax | M83: =+E10 -> 395
L84: Drink2Go | M84: =+F10 -> 395
M91: =+A11 -> No Decision
L92: GlobalBiz | M92: =+B11 -> 100
L93: FreshMarket | M93: =+C11 -> 100
L94: SparklingCo | M94: =+D11 -> 100
L95: QualityMax | M95: =+E11 -> 100
L96: Drink2Go | M96: =+F11 -> 100
M103: =+A12 -> Valor Compania
L104: GlobalBiz | M104: =+B12 -> 5406
L105: FreshMarket | M105: =+C12 -> 5463
L106: SparklingCo | M106: =+D12 -> 5104
L107: QualityMax | M107: =+E12 -> 5344
L108: Drink2Go | M108: =+F12 -> 4697

Sheet 4
A1: 4
A2: Valores del Escenario
C3: Periodo Actual | D3: T+1 | E3: T+2
A4: Indice de Precios al Consumo | B4: España | C4: =+'TablasInformes (1)'!C57 -> 30 | D4: =+'TablasInformes (1)'!D57 -> 26 | E4: =+'TablasInformes (1)'!E57 -> 24
B5: Portugal | C5: =+'TablasInformes (1)'!C58 -> 25 | D5: =+'TablasInformes (1)'!D58 -> 23 | E5: =+'TablasInformes (1)'!E58 -> 21
B6: Francia | C6: =+'TablasInformes (1)'!C59 -> 26 | D6: =+'TablasInformes (1)'!D59 -> 19 | E6: =+'TablasInformes (1)'!E59 -> 20
B7: Italia | C7: =+'TablasInformes (1)'!C60 -> 27 | D7: =+'TablasInformes (1)'!D60 -> 22 | E7: =+'TablasInformes (1)'!E60 -> 24
B8: Centro Europa | C8: =+'TablasInformes (1)'!C61 -> 11 | D8: =+'TablasInformes (1)'!D61 -> 12 | E8: =+'TablasInformes (1)'!E61 -> 18
B9: Polonia | C9: =+'TablasInformes (1)'!C62 -> 26 | D9: =+'TablasInformes (1)'!D62 -> 19 | E9: =+'TablasInformes (1)'!E62 -> 16
B10: Mexico | C10: =+'TablasInformes (1)'!C63 -> 41 | D10: =+'TablasInformes (1)'!D63 -> 32 | E10: =+'TablasInformes (1)'!E63 -> 35
C16: Periodo Actual | D16: T+1 | E16: T+2
A17: Producto Interior Bruto | B17: España | C17: =+'TablasInformes (1)'!C64 -> 27 | D17: =+'TablasInformes (1)'!D64 -> 23 | E17: =+'TablasInformes (1)'!E64 -> 21
B18: Portugal | C18: =+'TablasInformes (1)'!C65 -> 27 | D18: =+'TablasInformes (1)'!D65 -> 22 | E18: =+'TablasInformes (1)'!E65 -> 18
B19: Francia | C19: =+'TablasInformes (1)'!C66 -> 22 | D19: =+'TablasInformes (1)'!D66 -> 16 | E19: =+'TablasInformes (1)'!E66 -> 21
B20: Italia | C20: =+'TablasInformes (1)'!C67 -> 24 | D20: =+'TablasInformes (1)'!D67 -> 19 | E20: =+'TablasInformes (1)'!E67 -> 23
B21: Centro Europa | C21: =+'TablasInformes (1)'!C68 -> 9 | D21: =+'TablasInformes (1)'!D68 -> 15 | E21: =+'TablasInformes (1)'!E68 -> 22
B22: Polonia | C22: =+'TablasInformes (1)'!C69 -> 31 | D22: =+'TablasInformes (1)'!D69 -> 23 | E22: =+'TablasInformes (1)'!E69 -> 18
B23: Mexico | C23: =+'TablasInformes (1)'!C70 -> 28 | D23: =+'TablasInformes (1)'!D70 -> 21 | E23: =+'TablasInformes (1)'!E70 -> 23
C32: Periodo Actual | D32: T+1 | E32: T+2
A33: Tipo de Interes | B33: España | C33: =+'TablasInformes (1)'!C71 -> 24 | D33: =+'TablasInformes (1)'!D71 -> 0 | E33: =+'TablasInformes (1)'!E71 -> 0
B34: Marruecos | C34: =+'TablasInformes (1)'!C72 -> 36 | D34: =+'TablasInformes (1)'!D72 -> 0 | E34: =+'TablasInformes (1)'!E72 -> 0
B35: Mexico | C35: =+'TablasInformes (1)'!C73 -> 52 | D35: =+'TablasInformes (1)'!D73 -> 0 | E35: =+'TablasInformes (1)'!E73 -> 0
B36: China | C36: =+'TablasInformes (1)'!C74 -> 55 | D36: =+'TablasInformes (1)'!D74 -> 0 | E36: =+'TablasInformes (1)'!E74 -> 0

Sheet 5
A1: 5
A2: Indicadores Clave de la Compania Drink2Go
B3: Ano 0 | C3: Ano -1 | D3: Diferencia | E3: Variacion
A4: Unidades Vendidas | B4: =+'TablasInformes (1)'!C79 -> 10555331 | C4: =+'TablasInformes (1)'!D79 -> 10146898 | D4: =+'TablasInformes (1)'!E79 -> 408433 | E4: =+'TablasInformes (1)'!F79 -> 0.4
A5: Participacion de Mercado | B5: =+'TablasInformes (1)'!C80 -> 1.68 | C5: =+'TablasInformes (1)'!D80 -> 1.65 | D5: =+'TablasInformes (1)'!E80 -> 0 | E5: =+'TablasInformes (1)'!F80 -> 0.18
A6: Ingresos | B6: =+'TablasInformes (1)'!C81 -> 21517990 | C6: =+'TablasInformes (1)'!D81 -> 19829118 | D6: =+'TablasInformes (1)'!E81 -> 1688872 | E6: =+'TablasInformes (1)'!F81 -> 0.85
A7: Resultado Bruto | B7: =+'TablasInformes (1)'!C82 -> -188802 | C7: =+'TablasInformes (1)'!D82 -> 2403283 | D7: =+'TablasInformes (1)'!E82 -> -2592084 | E7: =+'TablasInformes (1)'!F82 -> -10.79
A8: Ratio Resultado Bruto sobre Ingresos- | B8: =+'TablasInformes (1)'!C83 -> -0.09 | C8: =+'TablasInformes (1)'!D83 -> 1.21 | D8: =+'TablasInformes (1)'!E83 -> -130 | E8: =+'TablasInformes (1)'!F83 -> -10.73
A9: Resultado Neto | B9: =+'TablasInformes (1)'!C84 -> -1479023 | C9: =+'TablasInformes (1)'!D84 -> 1244268 | D9: =+'TablasInformes (1)'!E84 -> -2723291 | E9: =+'TablasInformes (1)'!F84 -> -21.89
A10: Rentabilidad sobre Patrimonio Neto - | B10: =+'TablasInformes (1)'!C85 -> -0.78 | C10: =+'TablasInformes (1)'!D85 -> 0.45 | D10: =+'TablasInformes (1)'!E85 -> -123 | E10: =+'TablasInformes (1)'!F85 -> -27.35
A11: Rendimiento del Activo | B11: =+'TablasInformes (1)'!C86 -> -0.07 | C11: =+'TablasInformes (1)'!D86 -> 0.83 | D11: =+'TablasInformes (1)'!E86 -> -89 | E11: =+'TablasInformes (1)'!F86 -> -10.79
A12: Total Pasivo sobre Patrimonio | B12: =+'TablasInformes (1)'!C87 -> 0.05 | C12: =+'TablasInformes (1)'!D87 -> 0.04 | D12: =+'TablasInformes (1)'!E87 -> 1 | E12: =+'TablasInformes (1)'!F87 -> 3.25
A13: Capacidad Fabricacion Total - Litro o Kilo | B13: =+'TablasInformes (1)'!C88 -> 10785200 | C13: =+'TablasInformes (1)'!D88 -> 10511000 | D13: =+'TablasInformes (1)'!E88 -> 274200 | E13: =+'TablasInformes (1)'!F88 -> 0.26
A14: Tasa Ocupacion Fabricas - | B14: =+'TablasInformes (1)'!C89 -> 9.9 | C14: =+'TablasInformes (1)'!D89 -> 9.77 | D14: =+'TablasInformes (1)'!E89 -> 13 | E14: =+'TablasInformes (1)'!F89 -> 0.13
A15: Unidades Inventario sobre Ventas - | B15: =+'TablasInformes (1)'!C90 -> 1.2 | C15: =+'TablasInformes (1)'!D90 -> 1.11 | D15: =+'TablasInformes (1)'!E90 -> 8 | E15: =+'TablasInformes (1)'!F90 -> 0.76
... A19: Cobertura Distribucion - escala 1 a 100- | B19: =+'TablasInformes (1)'!C94 -> 4.11 | C19: =+'TablasInformes (1)'!D94 -> 4.12 | D19: =+'TablasInformes (1)'!E94 -> 0 | E19: =+'TablasInformes (1)'!F94 -> -0.02

Sheet 6
A1: 6
A2: Indicadores Clave de la Compania.
B3: GlobalBiz | C3: FreshMarket | D3: SparklingCo | E3: QualityMax | F3: Drink2Go
A4: Unidades Vendidas | B4: =+'TablasInformes (1)'!B99 -> 13710419 | C4: =+'TablasInformes (1)'!C99 -> 14426726 | D4: =+'TablasInformes (1)'!D99 -> 13502462 | E4: =+'TablasInformes (1)'!E99 -> 10643463 | F4: =+'TablasInformes (1)'!F99 -> 10555331
A5: Cuota de Mercado | B5: =+'TablasInformes (1)'!B100 -> 2.18 | C5: =+'TablasInformes (1)'!C100 -> 2.3 | D5: =+'TablasInformes (1)'!D100 -> 2.15 | E5: =+'TablasInformes (1)'!E100 -> 1.69 | F5: =+'TablasInformes (1)'!F100 -> 1.68
A6: Ingresos | B6: =+'TablasInformes (1)'!B101 -> 27027948 | C6: =+'TablasInformes (1)'!C101 -> 23052926 | D6: =+'TablasInformes (1)'!D101 -> 20193200 | E6: =+'TablasInformes (1)'!E101 -> 20913542 | F6: =+'TablasInformes (1)'!F101 -> 21517990
A7: Resultado Bruto | B7: =+'TablasInformes (1)'!B102 -> 8648527 | C7: =+'TablasInformes (1)'!C102 -> 6561048 | D7: =+'TablasInformes (1)'!D102 -> 5140601 | E7: =+'TablasInformes (1)'!E102 -> 7171972 | F7: =+'TablasInformes (1)'!F102 -> -188802
A8: Ratio Beneficio Bruto sobre Ingresos- | B8: =+'TablasInformes (1)'!B103 -> 3.2 | C8: =+'TablasInformes (1)'!C103 -> 2.85 | D8: =+'TablasInformes (1)'!D103 -> 2.55 | E8: =+'TablasInformes (1)'!E103 -> 3.43 | F8: =+'TablasInformes (1)'!F103 -> -0.09
A9: Resultado Neto | B9: =+'TablasInformes (1)'!B104 -> 6991802 | C9: =+'TablasInformes (1)'!C104 -> 4827083 | D9: =+'TablasInformes (1)'!D104 -> 3309868 | E9: =+'TablasInformes (1)'!E104 -> 6033841 | F9: =+'TablasInformes (1)'!F104 -> -1479023
A10: Rentabilidad sobre Patrimonio Neto - | B10: =+'TablasInformes (1)'!B105 -> 1.7 | C10: =+'TablasInformes (1)'!C105 -> 1.19 | D10: =+'TablasInformes (1)'!D105 -> 1.26 | E10: =+'TablasInformes (1)'!E105 -> 1.49 | F10: =+'TablasInformes (1)'!F105 -> -0.78
A11: Rendimiento del Activo | B11: =+'TablasInformes (1)'!B106 -> 1.91 | C11: =+'TablasInformes (1)'!C106 -> 1.46 | D11: =+'TablasInformes (1)'!D106 -> 1.43 | E11: =+'TablasInformes (1)'!E106 -> 1.87 | F11: =+'TablasInformes (1)'!F106 -> -0.07
A12: Total Pasivo sobre Patrimonio | B12: =+'TablasInformes (1)'!B107 -> 5 | C12: =+'TablasInformes (1)'!C107 -> 5 | D12: =+'TablasInformes (1)'!D107 -> 8 | E12: =+'TablasInformes (1)'!E107 -> 3 | F12: =+'TablasInformes (1)'!F107 -> 5
A13: Capacidad Fabricacion Total | B13: =+'TablasInformes (1)'!B108 -> 13481500 | C13: =+'TablasInformes (1)'!C108 -> 16177800 | D13: =+'TablasInformes (1)'!D108 -> 13481500 | E13: =+'TablasInformes (1)'!E108 -> 10785200 | F13: =+'TablasInformes (1)'!F108 -> 10785200
A14: Tasa Ocupacion Fabricas - | B14: =+'TablasInformes (1)'!B109 -> 10 | C14: =+'TablasInformes (1)'!C109 -> 8.97 | D14: =+'TablasInformes (1)'!D109 -> 10 | E14: =+'TablasInformes (1)'!E109 -> 9.91 | F14: =+'TablasInformes (1)'!F109 -> 9.9
A15: Unidades Inventario sobre Ventas - | B15: 0.071 | C15: 0.08 | D15: 0.071 | E15: 0.079 | F15: 0.12 | G15: =B15/10 -> 0.0071 | H15: =C15/10 -> 0.008 | I15: =D15/10 -> 0.0071 | J15: =E15/10 -> 0.0079 | K15: =F15/10 -> 0.012
A16: Valor de Marca - escala 1 a 100- | B16: =+'TablasInformes (1)'!B111 -> 40 | C16: =+'TablasInformes (1)'!C111 -> 49 | D16: =+'TablasInformes (1)'!D111 -> 28 | E16: =+'TablasInformes (1)'!E111 -> 28 | F16: =+'TablasInformes (1)'!F111 -> 49
A17: Valor de Producto - escala 1 a 10- | B17: =+'TablasInformes (1)'!B112 -> 81 | C17: =+'TablasInformes (1)'!C112 -> 79 | D17: =+'TablasInformes (1)'!D112 -> 78 | E17: =+'TablasInformes (1)'!E112 -> 79 | F17: =+'TablasInformes (1)'!F112 -> 79
A18: Tecnologia Industrial - escala 1 a 10- | B18: =+'TablasInformes (1)'!B113 -> 9 | C18: =+'TablasInformes (1)'!C113 -> 9 | D18: =+'TablasInformes (1)'!D113 -> 9 | E18: =+'TablasInformes (1)'!E113 -> 9 | F18: =+'TablasInformes (1)'!F113 -> 9
A19: Cobertura Distribucion - escala 1 a 100- | B19: =+'TablasInformes (1)'!B114 -> 2.59 | C19: =+'TablasInformes (1)'!C114 -> 3.17 | D19: =+'TablasInformes (1)'!D114 -> 3.78 | E19: =+'TablasInformes (1)'!E114 -> 1.92 | F19: =+'TablasInformes (1)'!F114 -> 4.11

Sheet 7
A1: 7
A2: Indicadores Clave de la Compania Drink2Go
B3: =+'TablasInformes (1)'!B118 -> 2023 | C3: =+'TablasInformes (1)'!C118 -> 2024 | D3: =+'TablasInformes (1)'!D118 -> 2025 | E3: =+'TablasInformes (1)'!E118 -> 2026 | F3: =+'TablasInformes (1)'!F118 -> 2027 | G3: =+'TablasInformes (1)'!G118 -> 2028
A4: Unidades Vendidas | B4: =+'TablasInformes (1)'!B120 -> 6641121 | C4: =+'TablasInformes (1)'!C120 -> 6841045 | D4: =+'TablasInformes (1)'!D120 -> 8078565 | E4: =+'TablasInformes (1)'!E120 -> 8686200 | F4: =+'TablasInformes (1)'!F120 -> 10146898 | G4: =+'TablasInformes (1)'!G120 -> 10555331 | J4: mercado y finanzas
A5: Participacion de Mercado | B5: =+'TablasInformes (1)'!B121 -> 0.2 | C5: =+'TablasInformes (1)'!C121 -> 0.187 | D5: =+'TablasInformes (1)'!D121 -> 0.17 | E5: =+'TablasInformes (1)'!E121 -> 0.155 | F5: =+'TablasInformes (1)'!F121 -> 0.165 | G5: =+'TablasInformes (1)'!G121 -> 0.168
A6: Ingresos | B6: =+'TablasInformes (1)'!B122 -> 7976033 | C6: =+'TablasInformes (1)'!C122 -> 10787901 | D6: =+'TablasInformes (1)'!D122 -> 16607629 | E6: =+'TablasInformes (1)'!E122 -> 19958018 | F6: =+'TablasInformes (1)'!F122 -> 19829118 | G6: =+'TablasInformes (1)'!G122 -> 21517990
A7: Resultado Bruto | B7: =+'TablasInformes (1)'!B123 -> 847700 | C7: =+'TablasInformes (1)'!C123 -> 3100303 | D7: =+'TablasInformes (1)'!D123 -> 3422755 | E7: =+'TablasInformes (1)'!E123 -> 4903309 | F7: =+'TablasInformes (1)'!F123 -> 2403283 | G7: =+'TablasInformes (1)'!G123 -> -188802
A8: Ratio Beneficio Bruto sobre Ingresos- | B8: =+'TablasInformes (1)'!B124 -> 1.06 | C8: =+'TablasInformes (1)'!C124 -> 2.87 | D8: =+'TablasInformes (1)'!D124 -> 2.06 | E8: =+'TablasInformes (1)'!E124 -> 2.46 | F8: =+'TablasInformes (1)'!F124 -> 1.21 | G8: =+'TablasInformes (1)'!G124 -> -0.09 | J8: naranja | K8: financiera
A9: Resultado Neto | B9: =+'TablasInformes (1)'!B125 -> 184751 | C9: =+'TablasInformes (1)'!C125 -> 2217466 | D9: =+'TablasInformes (1)'!D125 -> 2182566 | E9: =+'TablasInformes (1)'!E125 -> 3699908 | F9: =+'TablasInformes (1)'!F125 -> 1244268 | G9: =+'TablasInformes (1)'!G125 -> -1479023 | J9: rojo | K9: mercado
A10: Rentabilidad sobre Patrimonio Neto - | B10: =+'TablasInformes (1)'!B126 -> 0.01 | C10: =+'TablasInformes (1)'!C126 -> 0.1 | D10: =+'TablasInformes (1)'!D126 -> 0.095 | E10: =+'TablasInformes (1)'!E126 -> 0.136 | F10: =+'TablasInformes (1)'!F126 -> 0.045 | G10: =+'TablasInformes (1)'!G126 -> -0.078 | J10: verde | K10: produccioon
A11: Rendimiento del Activo | B11: =+'TablasInformes (1)'!B127 -> 0.045 | C11: =+'TablasInformes (1)'!C127 -> 0.126 | D11: =+'TablasInformes (1)'!D127 -> 0.119 | E11: =+'TablasInformes (1)'!E127 -> 0.162 | F11: =+'TablasInformes (1)'!F127 -> 0.083 | G11: =+'TablasInformes (1)'!G127 -> -0.007
A12: Total Pasivo sobre Patrimonio | B12: =+'TablasInformes (1)'!B128 -> 3 | C12: =+'TablasInformes (1)'!C128 -> 5 | D12: =+'TablasInformes (1)'!D128 -> 7 | E12: =+'TablasInformes (1)'!E128 -> 5 | F12: =+'TablasInformes (1)'!F128 -> 4 | G12: =+'TablasInformes (1)'!G128 -> 5
A13: Capacidad Fabricacion Total | B13: =+'TablasInformes (1)'!B129 -> 7334850 | C13: =+'TablasInformes (1)'!C129 -> 7471950 | D13: =+'TablasInformes (1)'!D129 -> 10145400 | E13: =+'TablasInformes (1)'!E129 -> 10328200 | F13: =+'TablasInformes (1)'!F129 -> 10511000 | G13: =+'TablasInformes (1)'!G129 -> 10785200 | I13: =(G13-B13)/B13 -> 0.47040498
A14: Tasa Ocupacion Fabricas - | B14: =+'TablasInformes (1)'!B130 -> 0.887 | C14: =+'TablasInformes (1)'!C130 -> 0.963 | D14: =+'TablasInformes (1)'!D130 -> 0.821 | E14: =+'TablasInformes (1)'!E130 -> 0.866 | F14: =+'TablasInformes (1)'!F130 -> 0.977 | G14: =+'TablasInformes (1)'!G130 -> 0.99
A15: Unidades Inventario sobre Ventas - | B15: =+'TablasInformes (1)'!B131 -> 0.022 | C15: =+'TablasInformes (1)'!C131 -> 0.073 | D15: =+'TablasInformes (1)'!D131 -> 0.093 | E15: =+'TablasInformes (1)'!E131 -> 0.116 | F15: =+'TablasInformes (1)'!F131 -> 0.111 | G15: =+'TablasInformes (1)'!G131 -> 0.12
A16: Valor de Marca - escala 1 a 100- | B16: =+'TablasInformes (1)'!B132 -> 35 | C16: =+'TablasInformes (1)'!C132 -> 28 | D16: =+'TablasInformes (1)'!D132 -> 49 | E16: =+'TablasInformes (1)'!E132 -> 36 | F16: =+'TablasInformes (1)'!F132 -> 30 | G16: =+'TablasInformes (1)'!G132 -> 49
A17: Valor de Producto - escala 1 a 10- | B17: =+'TablasInformes (1)'!B133 -> 7.4 | C17: =+'TablasInformes (1)'!C133 -> 7.4 | D17: =+'TablasInformes (1)'!D133 -> 7.6 | E17: =+'TablasInformes (1)'!E133 -> 7.8 | F17: =+'TablasInformes (1)'!F133 -> 7.9 | G17: =+'TablasInformes (1)'!G133 -> 7.9
A18: Tecnologia Industrial - escala 1 a 10- | B18: =+'TablasInformes (1)'!B134 -> 4 | C18: =+'TablasInformes (1)'!C134 -> 5 | D18: =+'TablasInformes (1)'!D134 -> 6 | E18: =+'TablasInformes (1)'!E134 -> 7 | F18: =+'TablasInformes (1)'!F134 -> 8 | G18: =+'TablasInformes (1)'!G134 -> 9
A19: º | B19: =+'TablasInformes (1)'!B135 -> 0.439 | C19: =+'TablasInformes (1)'!C135 -> 0.408 | D19: =+'TablasInformes (1)'!D135 -> 0.397 | E19: =+'TablasInformes (1)'!E135 -> 0.409 | F19: =+'TablasInformes (1)'!F135 -> 0.412 | G19: =+'TablasInformes (1)'!G135 -> 0.411
B21: =B15/10 -> 0.0022 | C21: =C15/10 -> 0.0073 | D21: =D15/10 -> 0.0093 | E21: =E15/10 -> 0.0116 | F21: =F15/10 -> 0.0111 | G21: =G15/10 -> 0.012
B70: 2023 | C70: 2024 | D70: 2025 | E70: 2026 | F70: 2027 | G70: 2028
A71: Unidades Vendidas | B71: 6641121 | C71: 6841045 | D71: 8078565 | E71: 8686200 | F71: 10146898 | G71: 10555331
A72: Porcentaje de Crecimiento | C72: =(C71-B71)/C71 -> 0.02922419 | D72: =(D71-C71)/D71 -> 0.15318562 | E72: =(E71-D71)/E71 -> 0.069954065 | F72: =(F71-E71)/F71 -> 0.14395513 | G72: =(G71-F71)/G71 -> 0.038694476
A75: Valor de Marca - escala 1 a 100- | B75: 35 | C75: 28 | D75: 49 | E75: 36 | F75: 30 | G75: 49
C76: =(C75-B75)/C75 -> -0.25 | D76: =(D75-C75)/D75 -> 0.42857143 | E76: =(E75-D75)/E75 -> -0.36111111 | F76: =(F75-E75)/F75 -> -0.2 | G76: =(G75-B75)/G75 -> 0.28571429

Sheet 8
A1: 8
A2: Nivel de precios por compania Drink2Go
C3: =+'TablasInformes (1)'!C139 -> 2023 | D3: =+'TablasInformes (1)'!D139 -> 2024 | E3: =+'TablasInformes (1)'!E139 -> 2025 | F3: =+'TablasInformes (1)'!F139 -> 2026 | G3: =+'TablasInformes (1)'!G139 -> 2027 | H3: =+'TablasInformes (1)'!H139 -> 2028
A4: Espana | B4: Refrescos | C4: =+'TablasInformes (1)'!C141 -> 12 | D4: =+'TablasInformes (1)'!D141 -> 16 | E4: =+'TablasInformes (1)'!E141 -> 20 | F4: =+'TablasInformes (1)'!F141 -> 20 | G4: =+'TablasInformes (1)'!G141 -> 20 | H4: =+'TablasInformes (1)'!H141 -> 25
B5: Isotonicas | C5: =+'TablasInformes (1)'!C142 -> 18 | D5: =+'TablasInformes (1)'!D142 -> 24 | E5: =+'TablasInformes (1)'!E142 -> 28 | F5: =+'TablasInformes (1)'!F142 -> 28 | G5: =+'TablasInformes (1)'!G142 -> 28 | H5: =+'TablasInformes (1)'!H142 -> 28
B6: Zumos | C6: =+'TablasInformes (1)'!C143 -> 22 | D6: =+'TablasInformes (1)'!D143 -> 30 | E6: =+'TablasInformes (1)'!E143 -> 35 | F6: =+'TablasInformes (1)'!F143 -> 35 | G6: =+'TablasInformes (1)'!G143 -> 30 | H6: =+'TablasInformes (1)'!H143 -> 29
A7: Portugal | B7: Refrescos | C7: =+'TablasInformes (1)'!C144 -> 11 | D7: =+'TablasInformes (1)'!D144 -> 16 | E7: =+'TablasInformes (1)'!E144 -> 20 | F7: =+'TablasInformes (1)'!F144 -> 20 | G7: =+'TablasInformes (1)'!G144 -> 20 | H7: =+'TablasInformes (1)'!H144 -> 24
B8: Isotonicas | C8: =+'TablasInformes (1)'!C145 -> 17 | D8: =+'TablasInformes (1)'!D145 -> 23 | E8: =+'TablasInformes (1)'!E145 -> 28 | F8: =+'TablasInformes (1)'!F145 -> 28 | G8: =+'TablasInformes (1)'!G145 -> 28 | H8: =+'TablasInformes (1)'!H145 -> 28
B9: Zumos | C9: =+'TablasInformes (1)'!C146 -> 23 | D9: =+'TablasInformes (1)'!D146 -> 31 | E9: =+'TablasInformes (1)'!E146 -> 36 | F9: =+'TablasInformes (1)'!F146 -> 36 | G9: =+'TablasInformes (1)'!G146 -> 3 | H9: =+'TablasInformes (1)'!H146 -> 29
A10: Francia | B10: Refrescos | C10: =+'TablasInformes (1)'!C147 -> 13 | D10: =+'TablasInformes (1)'!D147 -> 18 | E10: =+'TablasInformes (1)'!E147 -> 25 | F10: =+'TablasInformes (1)'!F147 -> 25 | G10: =+'TablasInformes (1)'!G147 -> 23 | H10: =+'TablasInformes (1)'!H147 -> 27
B11: Isotonicas | C11: =+'TablasInformes (1)'!C148 -> 19 | D11: =+'TablasInformes (1)'!D148 -> 26 | E11: =+'TablasInformes (1)'!E148 -> 30 | F11: =+'TablasInformes (1)'!F148 -> 30 | G11: =+'TablasInformes (1)'!G148 -> 28 | H11: =+'TablasInformes (1)'!H148 -> 28
B12: Zumos | C12: =+'TablasInformes (1)'!C149 -> 25 | D12: =+'TablasInformes (1)'!D149 -> 34 | E12: =+'TablasInformes (1)'!E149 -> 38 | F12: =+'TablasInformes (1)'!F149 -> 38 | G12: =+'TablasInformes (1)'!G149 -> 32 | H12: =+'TablasInformes (1)'!H149 -> 3
A13: Italia | B13: Refrescos | C13: =+'TablasInformes (1)'!C150 -> 0 | D13: =+'TablasInformes (1)'!D150 -> 16 | E13: =+'TablasInformes (1)'!E150 -> 24 | F13: =+'TablasInformes (1)'!F150 -> 3 | G13: =+'TablasInformes (1)'!G150 -> 24 | H13: =+'TablasInformes (1)'!H150 -> 28
B14: Isotonicas | C14: =+'TablasInformes (1)'!C151 -> 0 | D14: =+'TablasInformes (1)'!D151 -> 24 | E14: =+'TablasInformes (1)'!E151 -> 36 | F14: =+'TablasInformes (1)'!F151 -> 40 | G14: =+'TablasInformes (1)'!G151 -> 30 | H14: =+'TablasInformes (1)'!H151 -> 31
B15: Zumos | C15: =+'TablasInformes (1)'!C152 -> 0 | D15: =+'TablasInformes (1)'!D152 -> 30 | E15: =+'TablasInformes (1)'!E152 -> 45 | F15: =+'TablasInformes (1)'!F152 -> 56 | G15: =+'TablasInformes (1)'!G152 -> 34 | H15: =+'TablasInformes (1)'!H152 -> 34
A16: Centro Europa | B16: Refrescos | C16: =+'TablasInformes (1)'!C153 -> 0 | D16: =+'TablasInformes (1)'!D153 -> 0 | E16: =+'TablasInformes (1)'!E153 -> 0 | F16: =+'TablasInformes (1)'!F153 -> 0 | G16: =+'TablasInformes (1)'!G153 -> 28 | H16: =+'TablasInformes (1)'!H153 -> 28
B17: Isotonicas | C17: =+'TablasInformes (1)'!C154 -> 0 | D17: =+'TablasInformes (1)'!D154 -> 0 | E17: =+'TablasInformes (1)'!E154 -> 0 | F17: =+'TablasInformes (1)'!F154 -> 0 | G17: =+'TablasInformes (1)'!G154 -> 34 | H17: =+'TablasInformes (1)'!H154 -> 32
B18: Zumos | C18: =+'TablasInformes (1)'!C155 -> 0 | D18: =+'TablasInformes (1)'!D155 -> 0 | E18: =+'TablasInformes (1)'!E155 -> 0 | F18: =+'TablasInformes (1)'!F155 -> 0 | G18: =+'TablasInformes (1)'!G155 -> 35 | H18: =+'TablasInformes (1)'!H155 -> 32
A19: Polonia | B19: Refrescos | C19: =+'TablasInformes (1)'!C156 -> 0 | D19: =+'TablasInformes (1)'!D156 -> 0 | E19: =+'TablasInformes (1)'!E156 -> 0 | F19: =+'TablasInformes (1)'!F156 -> 24 | G19: =+'TablasInformes (1)'!G156 -> 26 | H19: =+'TablasInformes (1)'!H156 -> 27
B20: Isotonicas | C20: =+'TablasInformes (1)'!C157 -> 0 | D20: =+'TablasInformes (1)'!D157 -> 0 | E20: =+'TablasInformes (1)'!E157 -> 0 | F20: =+'TablasInformes (1)'!F157 -> 28 | G20: =+'TablasInformes (1)'!G157 -> 32 | H20: =+'TablasInformes (1)'!H157 -> 32
B21: Zumos | C21: =+'TablasInformes (1)'!C158 -> 0 | D21: =+'TablasInformes (1)'!D158 -> 0 | E21: =+'TablasInformes (1)'!E158 -> 0 | F21: =+'TablasInformes (1)'!F158 -> 35 | G21: =+'TablasInformes (1)'!G158 -> 38 | H21: =+'TablasInformes (1)'!H158 -> 35
A22: Mexico | B22: Refrescos | C22: =+'TablasInformes (1)'!C159 -> 0 | D22: =+'TablasInformes (1)'!D159 -> 0 | E22: =+'TablasInformes (1)'!E159 -> 24 | F22: =+'TablasInformes (1)'!F159 -> 3 | G22: =+'TablasInformes (1)'!G159 -> 3 | H22: =+'TablasInformes (1)'!H159 -> 32
B23: Isotonicas | C23: =+'TablasInformes (1)'!C160 -> 0 | D23: =+'TablasInformes (1)'!D160 -> 0 | E23: =+'TablasInformes (1)'!E160 -> 36 | F23: =+'TablasInformes (1)'!F160 -> 4 | G23: =+'TablasInformes (1)'!G160 -> 29 | H23: =+'TablasInformes (1)'!H160 -> 33
B24: Zumos | C24: =+'TablasInformes (1)'!C161 -> 0 | D24: =+'TablasInformes (1)'!D161 -> 0 | E24: =+'TablasInformes (1)'!E161 -> 45 | F24: =+'TablasInformes (1)'!F161 -> 5 | G24: =+'TablasInformes (1)'!G161 -> 5 | H24: =+'TablasInformes (1)'!H161 -> 38

Sheet 9
A1: 9
A2: Nivel de precios por compania.
C3: GlobalBiz | D3: FreshMarket | E3: SparklingCo | F3: QualityMax | G3: Drink2Go
A4: Espana | B4: Refrescos | C4: =+'TablasInformes (1)'!C166 -> 19 | D4: =+'TablasInformes (1)'!D166 -> 17 | E4: =+'TablasInformes (1)'!E166 -> 17 | F4: =+'TablasInformes (1)'!F166 -> 20 | G4: =+'TablasInformes (1)'!G166 -> 25
B5: Isotonicas | C5: =+'TablasInformes (1)'!C167 -> 28 | D5: =+'TablasInformes (1)'!D167 -> 26 | E5: =+'TablasInformes (1)'!E167 -> 24 | F5: =+'TablasInformes (1)'!F167 -> 27 | G5: =+'TablasInformes (1)'!G167 -> 28
B6: Zumos | C6: =+'TablasInformes (1)'!C168 -> 31 | D6: =+'TablasInformes (1)'!D168 -> 3 | E6: =+'TablasInformes (1)'!E168 -> 27 | F6: =+'TablasInformes (1)'!F168 -> 32 | G6: =+'TablasInformes (1)'!G168 -> 29
A7: Portugal | B7: Refrescos | C7: =+'TablasInformes (1)'!C169 -> 19 | D7: =+'TablasInformes (1)'!D169 -> 17 | E7: =+'TablasInformes (1)'!E169 -> 17 | F7: =+'TablasInformes (1)'!F169 -> 19 | G7: =+'TablasInformes (1)'!G169 -> 24
B8: Isotonicas | C8: =+'TablasInformes (1)'!C170 -> 26 | D8: =+'TablasInformes (1)'!D170 -> 25 | E8: =+'TablasInformes (1)'!E170 -> 23 | F8: =+'TablasInformes (1)'!F170 -> 27 | G8: =+'TablasInformes (1)'!G170 -> 28
B9: Zumos | C9: =+'TablasInformes (1)'!C171 -> 31 | D9: =+'TablasInformes (1)'!D171 -> 3 | E9: =+'TablasInformes (1)'!E171 -> 27 | F9: =+'TablasInformes (1)'!F171 -> 34 | G9: =+'TablasInformes (1)'!G171 -> 29
A10: Francia | B10: Refrescos | C10: =+'TablasInformes (1)'!C172 -> 20 | D10: =+'TablasInformes (1)'!D172 -> 20 | E10: =+'TablasInformes (1)'!E172 -> 18 | F10: =+'TablasInformes (1)'!F172 -> 21 | G10: =+'TablasInformes (1)'!G172 -> 27
B11: Isotonicas | C11: =+'TablasInformes (1)'!C173 -> 28 | D11: =+'TablasInformes (1)'!D173 -> 29 | E11: =+'TablasInformes (1)'!E173 -> 27 | F11: =+'TablasInformes (1)'!F173 -> 28 | G11: =+'TablasInformes (1)'!G173 -> 28
B12: Zumos | C12: =+'TablasInformes (1)'!C174 -> 32 | D12: =+'TablasInformes (1)'!D174 -> 35 | E12: =+'TablasInformes (1)'!E174 -> 32 | F12: =+'TablasInformes (1)'!F174 -> 33 | G12: =+'TablasInformes (1)'!G174 -> 3
A13: Italia | B13: Refrescos | C13: =+'TablasInformes (1)'!C175 -> 22 | D13: =+'TablasInformes (1)'!D175 -> 17 | E13: =+'TablasInformes (1)'!E175 -> 17 | F13: =+'TablasInformes (1)'!F175 -> 22 | G13: =+'TablasInformes (1)'!G175 -> 28
B14: Isotonicas | C14: =+'TablasInformes (1)'!C176 -> 29 | D14: =+'TablasInformes (1)'!D176 -> 26 | E14: =+'TablasInformes (1)'!E176 -> 24 | F14: =+'TablasInformes (1)'!F176 -> 27 | G14: =+'TablasInformes (1)'!G176 -> 31
B15: Zumos | C15: =+'TablasInformes (1)'!C177 -> 36 | D15: =+'TablasInformes (1)'!D177 -> 3 | E15: =+'TablasInformes (1)'!E177 -> 27 | F15: =+'TablasInformes (1)'!F177 -> 32 | G15: =+'TablasInformes (1)'!G177 -> 34
A16: Centro Europa | B16: Refrescos | C16: =+'TablasInformes (1)'!C178 -> 23 | D16: =+'TablasInformes (1)'!D178 -> 17 | E16: =+'TablasInformes (1)'!E178 -> 16 | F16: =+'TablasInformes (1)'!F178 -> 25 | G16: =+'TablasInformes (1)'!G178 -> 28
B17: Isotonicas | C17: =+'TablasInformes (1)'!C179 -> 3 | D17: =+'TablasInformes (1)'!D179 -> 26 | E17: =+'TablasInformes (1)'!E179 -> 24 | F17: =+'TablasInformes (1)'!F179 -> 30 | G17: =+'TablasInformes (1)'!G179 -> 32
B18: Zumos | C18: =+'TablasInformes (1)'!C180 -> 35 | D18: =+'TablasInformes (1)'!D180 -> 3 | E18: =+'TablasInformes (1)'!E180 -> 27 | F18: =+'TablasInformes (1)'!F180 -> 35 | G18: =+'TablasInformes (1)'!G180 -> 32
A19: Polonia | B19: Refrescos | C19: =+'TablasInformes (1)'!C181 -> 22 | D19: =+'TablasInformes (1)'!D181 -> 18 | E19: =+'TablasInformes (1)'!E181 -> 16 | F19: =+'TablasInformes (1)'!F181 -> 25 | G19: =+'TablasInformes (1)'!G181 -> 27
B20: Isotonicas | C20: =+'TablasInformes (1)'!C182 -> 31 | D20: =+'TablasInformes (1)'!D182 -> 27 | E20: =+'TablasInformes (1)'!E182 -> 25 | F20: =+'TablasInformes (1)'!F182 -> 30 | G20: =+'TablasInformes (1)'!G182 -> 32
B21: Zumos | C21: =+'TablasInformes (1)'!C183 -> 36 | D21: =+'TablasInformes (1)'!D183 -> 33 | E21: =+'TablasInformes (1)'!E183 -> 3 | F21: =+'TablasInformes (1)'!F183 -> 35 | G21: =+'TablasInformes (1)'!G183 -> 35
A22: Mexico | B22: Refrescos | C22: =+'TablasInformes (1)'!C184 -> 23 | D22: =+'TablasInformes (1)'!D184 -> 17 | E22: =+'TablasInformes (1)'!E184 -> 16 | F22: =+'TablasInformes (1)'!F184 -> 23 | G22: =+'TablasInformes (1)'!G184 -> 32
B23: Isotonicas | C23: =+'TablasInformes (1)'!C185 -> 31 | D23: =+'TablasInformes (1)'!D185 -> 26 | E23: =+'TablasInformes (1)'!E185 -> 24 | F23: =+'TablasInformes (1)'!F185 -> 28 | G23: =+'TablasInformes (1)'!G185 -> 33
B24: Zumos | C24: =+'TablasInformes (1)'!C186 -> 36 | D24: =+'TablasInformes (1)'!D186 -> 30 | E24: =+'TablasInformes (1)'!E186 -> 27 | F24: =+'TablasInformes (1)'!F186 -> 33 | G24: =+'TablasInformes (1)'!G186 -> 38

Sheet 10
A1: 10
A2: Valor de producto - Escala 1 a 10. Drink2Go
B3: =+'TablasInformes (1)'!B190 -> 2023 | C3: =+'TablasInformes (1)'!C190 -> 2024 | D3: =+'TablasInformes (1)'!D190 -> 2025 | E3: =+'TablasInformes (1)'!E190 -> 2026 | F3: =+'TablasInformes (1)'!F190 -> 2027 | G3: =+'TablasInformes (1)'!G190 -> 2028
A4: Refrescos | B4: =+'TablasInformes (1)'!B192 -> 8.3 | C4: =+'TablasInformes (1)'!C192 -> 8.3 | D4: =+'TablasInformes (1)'!D192 -> 8.3 | E4: =+'TablasInformes (1)'!E192 -> 8.3 | F4: =+'TablasInformes (1)'!F192 -> 8.3 | G4: =+'TablasInformes (1)'!G192 -> 8.3
A5: Isotonicas | B5: =+'TablasInformes (1)'!B193 -> 6.5 | C5: =+'TablasInformes (1)'!C193 -> 6.3 | D5: =+'TablasInformes (1)'!D193 -> 6.5 | E5: =+'TablasInformes (1)'!E193 -> 6.8 | F5: =+'TablasInformes (1)'!F193 -> 7.1 | G5: =+'TablasInformes (1)'!G193 -> 7.1
A6: Zumos | B6: =+'TablasInformes (1)'!B194 -> 7.4 | C6: =+'TablasInformes (1)'!C194 -> 7.7 | D6: =+'TablasInformes (1)'!D194 -> 8 | E6: =+'TablasInformes (1)'!E194 -> 8.3 | F6: =+'TablasInformes (1)'!F194 -> 8.4 | G6: =+'TablasInformes (1)'!G194 -> 8.4

Sheet 11
A1: 11
A2: Gama de producto por compania. Drink2Go | I2: TOTAL
C3: =+'TablasInformes (1)'!C198 -> 2023 | D3: =+'TablasInformes (1)'!D198 -> 2024 | E3: =+'TablasInformes (1)'!E198 -> 2025 | F3: =+'TablasInformes (1)'!F198 -> 2026 | G3: =+'TablasInformes (1)'!G198 -> 2027 | H3: =+'TablasInformes (1)'!H198 -> 2028
A4: Espana | B4: Refrescos | C4: =+'TablasInformes (1)'!C200 -> 6 | D4: =+'TablasInformes (1)'!D200 -> 8 | E4: =+'TablasInformes (1)'!E200 -> 9 | F4: =+'TablasInformes (1)'!F200 -> 10 | G4: =+'TablasInformes (1)'!G200 -> 10 | H4: =+'TablasInformes (1)'!H200 -> 11
B5: Isotonicas | C5: =+'TablasInformes (1)'!C201 -> 2 | D5: =+'TablasInformes (1)'!D201 -> 3 | E5: =+'TablasInformes (1)'!E201 -> 4 | F5: =+'TablasInformes (1)'!F201 -> 5 | G5: =+'TablasInformes (1)'!G201 -> 5 | H5: =+'TablasInformes (1)'!H201 -> 6
B6: Zumos | C6: =+'TablasInformes (1)'!C202 -> 4 | D6: =+'TablasInformes (1)'!D202 -> 5 | E6: =+'TablasInformes (1)'!E202 -> 6 | F6: =+'TablasInformes (1)'!F202 -> 7 | G6: =+'TablasInformes (1)'!G202 -> 8 | H6: =+'TablasInformes (1)'!H202 -> 8 | I6: =SUM(H4:H6) -> 25
A7: Portugal | B7: Refrescos | C7: =+'TablasInformes (1)'!C203 -> 6 | D7: =+'TablasInformes (1)'!D203 -> 8 | E7: =+'TablasInformes (1)'!E203 -> 9 | F7: =+'TablasInformes (1)'!F203 -> 10 | G7: =+'TablasInformes (1)'!G203 -> 10 | H7: =+'TablasInformes (1)'!H203 -> 11
B8: Isotonicas | C8: =+'TablasInformes (1)'!C204 -> 2 | D8: =+'TablasInformes (1)'!D204 -> 3 | E8: =+'TablasInformes (1)'!E204 -> 4 | F8: =+'TablasInformes (1)'!F204 -> 5 | G8: =+'TablasInformes (1)'!G204 -> 5 | H8: =+'TablasInformes (1)'!H204 -> 6
B9: Zumos | C9: =+'TablasInformes (1)'!C205 -> 4 | D9: =+'TablasInformes (1)'!D205 -> 5 | E9: =+'TablasInformes (1)'!E205 -> 6 | F9: =+'TablasInformes (1)'!F205 -> 7 | G9: =+'TablasInformes (1)'!G205 -> 8 | H9: =+'TablasInformes (1)'!H205 -> 8 | I9: =SUM(H7:H9) -> 25
A10: Francia | B10: Refrescos | C10: =+'TablasInformes (1)'!C206 -> 6 | D10: =+'TablasInformes (1)'!D206 -> 8 | E10: =+'TablasInformes (1)'!E206 -> 9 | F10: =+'TablasInformes (1)'!F206 -> 10 | G10: =+'TablasInformes (1)'!G206 -> 10 | H10: =+'TablasInformes (1)'!H206 -> 11
B11: Isotonicas | C11: =+'TablasInformes (1)'!C207 -> 2 | D11: =+'TablasInformes (1)'!D207 -> 3 | E11: =+'TablasInformes (1)'!E207 -> 4 | F11: =+'TablasInformes (1)'!F207 -> 5 | G11: =+'TablasInformes (1)'!G207 -> 5 | H11: =+'TablasInformes (1)'!H207 -> 6
B12: Zumos | C12: =+'TablasInformes (1)'!C208 -> 4 | D12: =+'TablasInformes (1)'!D208 -> 5 | E12: =+'TablasInformes (1)'!E208 -> 6 | F12: =+'TablasInformes (1)'!F208 -> 7 | G12: =+'TablasInformes (1)'!G208 -> 8 | H12: =+'TablasInformes (1)'!H208 -> 8 | I12: =SUM(H10:H12) -> 25
A13: Italia | B13: Refrescos | C13: =+'TablasInformes (1)'!C209 -> 0 | D13: =+'TablasInformes (1)'!D209 -> 4 | E13: =+'TablasInformes (1)'!E209 -> 8 | F13: =+'TablasInformes (1)'!F209 -> 10 | G13: =+'TablasInformes (1)'!G209 -> 10 | H13: =+'TablasInformes (1)'!H209 -> 11
B14: Isotonicas | C14: =+'TablasInformes (1)'!C210 -> 0 | D14: =+'TablasInformes (1)'!D210 -> 2 | E14: =+'TablasInformes (1)'!E210 -> 4 | F14: =+'TablasInformes (1)'!F210 -> 5 | G14: =+'TablasInformes (1)'!G210 -> 5 | H14: =+'TablasInformes (1)'!H210 -> 6
B15: Zumos | C15: =+'TablasInformes (1)'!C211 -> 0 | D15: =+'TablasInformes (1)'!D211 -> 3 | E15: =+'TablasInformes (1)'!E211 -> 6 | F15: =+'TablasInformes (1)'!F211 -> 7 | G15: =+'TablasInformes (1)'!G211 -> 8 | H15: =+'TablasInformes (1)'!H211 -> 8
A16: Centro Europa | B16: Refrescos | C16: =+'TablasInformes (1)'!C212 -> 0 | D16: =+'TablasInformes (1)'!D212 -> 0 | E16: =+'TablasInformes (1)'!E212 -> 0 | F16: =+'TablasInformes (1)'!F212 -> 0 | G16: =+'TablasInformes (1)'!G212 -> 10 | H16: =+'TablasInformes (1)'!H212 -> 11 | I16: =SUM(H14:H16) -> 25
B17: Isotonicas | C17: =+'TablasInformes (1)'!C213 -> 0 | D17: =+'TablasInformes (1)'!D213 -> 0 | E17: =+'TablasInformes (1)'!E213 -> 0 | F17: =+'TablasInformes (1)'!F213 -> 0 | G17: =+'TablasInformes (1)'!G213 -> 5 | H17: =+'TablasInformes (1)'!H213 -> 6
B18: Zumos | C18: =+'TablasInformes (1)'!C214 -> 0 | D18: =+'TablasInformes (1)'!D214 -> 0 | E18: =+'TablasInformes (1)'!E214 -> 0 | F18: =+'TablasInformes (1)'!F214 -> 0 | G18: =+'TablasInformes (1)'!G214 -> 5 | H18: =+'TablasInformes (1)'!H214 -> 8
A19: Polonia | B19: Refrescos | C19: =+'TablasInformes (1)'!C215 -> 0 | D19: =+'TablasInformes (1)'!D215 -> 0 | E19: =+'TablasInformes (1)'!E215 -> 0 | F19: =+'TablasInformes (1)'!F215 -> 2 | G19: =+'TablasInformes (1)'!G215 -> 10 | H19: =+'TablasInformes (1)'!H215 -> 11 | I19: =SUM(H17:H19) -> 25
B20: Isotonicas | C20: =+'TablasInformes (1)'!C216 -> 0 | D20: =+'TablasInformes (1)'!D216 -> 0 | E20: =+'TablasInformes (1)'!E216 -> 0 | F20: =+'TablasInformes (1)'!F216 -> 2 | G20: =+'TablasInformes (1)'!G216 -> 6 | H20: =+'TablasInformes (1)'!H216 -> 6
B21: Zumos | C21: =+'TablasInformes (1)'!C217 -> 0 | D21: =+'TablasInformes (1)'!D217 -> 0 | E21: =+'TablasInformes (1)'!E217 -> 0 | F21: =+'TablasInformes (1)'!F217 -> 2 | G21: =+'TablasInformes (1)'!G217 -> 6 | H21: =+'TablasInformes (1)'!H217 -> 8
A22: Mexico | B22: Refrescos | C22: =+'TablasInformes (1)'!C218 -> 0 | D22: =+'TablasInformes (1)'!D218 -> 0 | E22: =+'TablasInformes (1)'!E218 -> 4 | F22: =+'TablasInformes (1)'!F218 -> 5 | G22: =+'TablasInformes (1)'!G218 -> 10 | H22: =+'TablasInformes (1)'!H218 -> 11 | I22: =SUM(H20:H22) -> 25
B23: Isotonicas | C23: =+'TablasInformes (1)'!C219 -> 0 | D23: =+'TablasInformes (1)'!D219 -> 0 | E23: =+'TablasInformes (1)'!E219 -> 4 | F23: =+'TablasInformes (1)'!F219 -> 5 | G23: =+'TablasInformes (1)'!G219 -> 6 | H23: =+'TablasInformes (1)'!H219 -> 6
B24: Zumos | C24: =+'TablasInformes (1)'!C220 -> 0 | D24: =+'TablasInformes (1)'!D220 -> 0 | E24: =+'TablasInformes (1)'!E220 -> 5 | F24: =+'TablasInformes (1)'!F220 -> 6 | G24: =+'TablasInformes (1)'!G220 -> 7 | H24: =+'TablasInformes (1)'!H220 -> 8 | I24: =SUM(H22:H24) -> 25
G25: TOTAL GENERAL | I25: =SUM(I6:I24) -> 175

Sheet 12
A1: 12
A2: Gama por producto por compania.
C3: =+'TablasInformes (1)'!C223 -> 2027 | D3: =+'TablasInformes (1)'!D223 -> 2027 | E3: =+'TablasInformes (1)'!E223 -> 2027 | F3: =+'TablasInformes (1)'!F223 -> 2028 | G3: =+'TablasInformes (1)'!G223 -> 2028 | H3: =+'TablasInformes (1)'!H223 -> 2028
C4: Refrescos | D4: Isotonicas | E4: Zumos | F4: Refrescos | G4: Isotonicas | H4: Zumos
A5: GlobalBiz | B5: Espana | C5: =+'TablasInformes (1)'!C225 -> 11 | D5: =+'TablasInformes (1)'!D225 -> 6 | E5: =+'TablasInformes (1)'!E225 -> 8 | F5: =+'TablasInformes (1)'!F225 -> 12 | G5: =+'TablasInformes (1)'!G225 -> 6 | H5: =+'TablasInformes (1)'!H225 -> 8
B6: Portugal | C6: =+'TablasInformes (1)'!C226 -> 11 | D6: =+'TablasInformes (1)'!D226 -> 6 | E6: =+'TablasInformes (1)'!E226 -> 8 | F6: =+'TablasInformes (1)'!F226 -> 12 | G6: =+'TablasInformes (1)'!G226 -> 6 | H6: =+'TablasInformes (1)'!H226 -> 8
B7: Francia | C7: =+'TablasInformes (1)'!C227 -> 11 | D7: =+'TablasInformes (1)'!D227 -> 6 | E7: =+'TablasInformes (1)'!E227 -> 8 | F7: =+'TablasInformes (1)'!F227 -> 12 | G7: =+'TablasInformes (1)'!G227 -> 6 | H7: =+'TablasInformes (1)'!H227 -> 8
B8: Italia | C8: =+'TablasInformes (1)'!C228 -> 12 | D8: =+'TablasInformes (1)'!D228 -> 6 | E8: =+'TablasInformes (1)'!E228 -> 8 | F8: =+'TablasInformes (1)'!F228 -> 12 | G8: =+'TablasInformes (1)'!G228 -> 6 | H8: =+'TablasInformes (1)'!H228 -> 8
B9: Centro Europa | C9: =+'TablasInformes (1)'!C229 -> 12 | D9: =+'TablasInformes (1)'!D229 -> 6 | E9: =+'TablasInformes (1)'!E229 -> 8 | F9: =+'TablasInformes (1)'!F229 -> 12 | G9: =+'TablasInformes (1)'!G229 -> 6 | H9: =+'TablasInformes (1)'!H229 -> 8
B10: Polonia | C10: =+'TablasInformes (1)'!C230 -> 12 | D10: =+'TablasInformes (1)'!D230 -> 6 | E10: =+'TablasInformes (1)'!E230 -> 8 | F10: =+'TablasInformes (1)'!F230 -> 12 | G10: =+'TablasInformes (1)'!G230 -> 6 | H10: =+'TablasInformes (1)'!H230 -> 8
B11: Mexico | C11: =+'TablasInformes (1)'!C231 -> 12 | D11: =+'TablasInformes (1)'!D231 -> 6 | E11: =+'TablasInformes (1)'!E231 -> 8 | F11: =+'TablasInformes (1)'!F231 -> 12 | G11: =+'TablasInformes (1)'!G231 -> 6 | H11: =+'TablasInformes (1)'!H231 -> 8
A12: FreshMarket | B12: Espana | C12: =+'TablasInformes (1)'!C232 -> 12 | D12: =+'TablasInformes (1)'!D232 -> 6 | E12: =+'TablasInformes (1)'!E232 -> 8 | F12: =+'TablasInformes (1)'!F232 -> 12 | G12: =+'TablasInformes (1)'!G232 -> 6 | H12: =+'TablasInformes (1)'!H232 -> 8
B13: Portugal | C13: =+'TablasInformes (1)'!C233 -> 12 | D13: =+'TablasInformes (1)'!D233 -> 6 | E13: =+'TablasInformes (1)'!E233 -> 8 | F13: =+'TablasInformes (1)'!F233 -> 12 | G13: =+'TablasInformes (1)'!G233 -> 6 | H13: =+'TablasInformes (1)'!H233 -> 8
B14: Francia | C14: =+'TablasInformes (1)'!C234 -> 12 | D14: =+'TablasInformes (1)'!D234 -> 6 | E14: =+'TablasInformes (1)'!E234 -> 8 | F14: =+'TablasInformes (1)'!F234 -> 12 | G14: =+'TablasInformes (1)'!G234 -> 6 | H14: =+'TablasInformes (1)'!H234 -> 8
B15: Italia | C15: =+'TablasInformes (1)'!C235 -> 12 | D15: =+'TablasInformes (1)'!D235 -> 6 | E15: =+'TablasInformes (1)'!E235 -> 8 | F15: =+'TablasInformes (1)'!F235 -> 12 | G15: =+'TablasInformes (1)'!G235 -> 6 | H15: =+'TablasInformes (1)'!H235 -> 8
B16: Centro Europa | C16: =+'TablasInformes (1)'!C236 -> 12 | D16: =+'TablasInformes (1)'!D236 -> 6 | E16: =+'TablasInformes (1)'!E236 -> 8 | F16: =+'TablasInformes (1)'!F236 -> 12 | G16: =+'TablasInformes (1)'!G236 -> 6 | H16: =+'TablasInformes (1)'!H236 -> 8
B17: Polonia | C17: =+'TablasInformes (1)'!C237 -> 12 | D17: =+'TablasInformes (1)'!D237 -> 6 | E17: =+'TablasInformes (1)'!E237 -> 8 | F17: =+'TablasInformes (1)'!F237 -> 12 | G17: =+'TablasInformes (1)'!G237 -> 6 | H17: =+'TablasInformes (1)'!H237 -> 8
B18: Mexico | C18: =+'TablasInformes (1)'!C238 -> 12 | D18: =+'TablasInformes (1)'!D238 -> 6 | E18: =+'TablasInformes (1)'!E238 -> 8 | F18: =+'TablasInformes (1)'!F238 -> 12 | G18: =+'TablasInformes (1)'!G238 -> 6 | H18: =+'TablasInformes (1)'!H238 -> 8
A19: SparklingCo | B19: Espana | C19: =+'TablasInformes (1)'!C239 -> 10 | D19: =+'TablasInformes (1)'!D239 -> 4 | E19: =+'TablasInformes (1)'!E239 -> 8 | F19: =+'TablasInformes (1)'!F239 -> 11 | G19: =+'TablasInformes (1)'!G239 -> 4 | H19: =+'TablasInformes (1)'!H239 -> 8
B20: Portugal | C20: =+'TablasInformes (1)'!C240 -> 10 | D20: =+'TablasInformes (1)'!D240 -> 4 | E20: =+'TablasInformes (1)'!E240 -> 8 | F20: =+'TablasInformes (1)'!F240 -> 11 | G20: =+'TablasInformes (1)'!G240 -> 4 | H20: =+'TablasInformes (1)'!H240 -> 8
B21: Francia | C21: =+'TablasInformes (1)'!C241 -> 10 | D21: =+'TablasInformes (1)'!D241 -> 4 | E21: =+'TablasInformes (1)'!E241 -> 8 | F21: =+'TablasInformes (1)'!F241 -> 11 | G21: =+'TablasInformes (1)'!G241 -> 4 | H21: =+'TablasInformes (1)'!H241 -> 8
B22: Italia | C22: =+'TablasInformes (1)'!C242 -> 10 | D22: =+'TablasInformes (1)'!D242 -> 4 | E22: =+'TablasInformes (1)'!E242 -> 8 | F22: =+'TablasInformes (1)'!F242 -> 11 | G22: =+'TablasInformes (1)'!G242 -> 4 | H22: =+'TablasInformes (1)'!H242 -> 8
B23: Centro Europa | C23: =+'TablasInformes (1)'!C243 -> 10 | D23: =+'TablasInformes (1)'!D243 -> 4 | E23: =+'TablasInformes (1)'!E243 -> 8 | F23: =+'TablasInformes (1)'!F243 -> 11 | G23: =+'TablasInformes (1)'!G243 -> 4 | H23: =+'TablasInformes (1)'!H243 -> 8
B24: Polonia | C24: =+'TablasInformes (1)'!C244 -> 10 | D24: =+'TablasInformes (1)'!D244 -> 4 | E24: =+'TablasInformes (1)'!E244 -> 8 | F24: =+'TablasInformes (1)'!F244 -> 11 | G24: =+'TablasInformes (1)'!G244 -> 4 | H24: =+'TablasInformes (1)'!H244 -> 8
B25: Mexico | C25: =+'TablasInformes (1)'!C245 -> 10 | D25: =+'TablasInformes (1)'!D245 -> 4 | E25: =+'TablasInformes (1)'!E245 -> 8 | F25: =+'TablasInformes (1)'!F245 -> 11 | G25: =+'TablasInformes (1)'!G245 -> 4 | H25: =+'TablasInformes (1)'!H245 -> 8
A26: QualityMax | B26: Espana | C26: =+'TablasInformes (1)'!C246 -> 9 | D26: =+'TablasInformes (1)'!D246 -> 4 | E26: =+'TablasInformes (1)'!E246 -> 6 | F26: =+'TablasInformes (1)'!F246 -> 11 | G26: =+'TablasInformes (1)'!G246 -> 6 | H26: =+'TablasInformes (1)'!H246 -> 7
B27: Portugal | C27: =+'TablasInformes (1)'!C247 -> 9 | D27: =+'TablasInformes (1)'!D247 -> 4 | E27: =+'TablasInformes (1)'!E247 -> 6 | F27: =+'TablasInformes (1)'!F247 -> 11 | G27: =+'TablasInformes (1)'!G247 -> 6 | H27: =+'TablasInformes (1)'!H247 -> 7
B28: Francia | C28: =+'TablasInformes (1)'!C248 -> 9 | D28: =+'TablasInformes (1)'!D248 -> 4 | E28: =+'TablasInformes (1)'!E248 -> 6 | F28: =+'TablasInformes (1)'!F248 -> 11 | G28: =+'TablasInformes (1)'!G248 -> 6 | H28: =+'TablasInformes (1)'!H248 -> 7
B29: Italia | C29: =+'TablasInformes (1)'!C249 -> 9 | D29: =+'TablasInformes (1)'!D249 -> 4 | E29: =+'TablasInformes (1)'!E249 -> 5 | F29: =+'TablasInformes (1)'!F249 -> 11 | G29: =+'TablasInformes (1)'!G249 -> 6 | H29: =+'TablasInformes (1)'!H249 -> 7
B30: Centro Europa | C30: =+'TablasInformes (1)'!C250 -> 5 | D30: =+'TablasInformes (1)'!D250 -> 3 | E30: =+'TablasInformes (1)'!E250 -> 5 | F30: =+'TablasInformes (1)'!F250 -> 11 | G30: =+'TablasInformes (1)'!G250 -> 6 | H30: =+'TablasInformes (1)'!H250 -> 7
B31: Polonia | C31: =+'TablasInformes (1)'!C251 -> 7 | D31: =+'TablasInformes (1)'!D251 -> 4 | E31: =+'TablasInformes (1)'!E251 -> 5 | F31: =+'TablasInformes (1)'!F251 -> 11 | G31: =+'TablasInformes (1)'!G251 -> 6 | H31: =+'TablasInformes (1)'!H251 -> 7
B32: Mexico | C32: =+'TablasInformes (1)'!C252 -> 9 | D32: =+'TablasInformes (1)'!D252 -> 4 | E32: =+'TablasInformes (1)'!E252 -> 5 | F32: =+'TablasInformes (1)'!F252 -> 11 | G32: =+'TablasInformes (1)'!G252 -> 6 | H32: =+'TablasInformes (1)'!H252 -> 7
A33: Drink2Go | B33: Espana | C33: =+'TablasInformes (1)'!C253 -> 10 | D33: =+'TablasInformes (1)'!D253 -> 5 | E33: =+'TablasInformes (1)'!E253 -> 8 | F33: =+'TablasInformes (1)'!F253 -> 11 | G33: =+'TablasInformes (1)'!G253 -> 6 | H33: =+'TablasInformes (1)'!H253 -> 8
B34: Portugal | C34: =+'TablasInformes (1)'!C254 -> 10 | D34: =+'TablasInformes (1)'!D254 -> 5 | E34: =+'TablasInformes (1)'!E254 -> 8 | F34: =+'TablasInformes (1)'!F254 -> 11 | G34: =+'TablasInformes (1)'!G254 -> 6 | H34: =+'TablasInformes (1)'!H254 -> 8
B35: Francia | C35: =+'TablasInformes (1)'!C255 -> 10 | D35: =+'TablasInformes (1)'!D255 -> 5 | E35: =+'TablasInformes (1)'!E255 -> 8 | F35: =+'TablasInformes (1)'!F255 -> 11 | G35: =+'TablasInformes (1)'!G255 -> 6 | H35: =+'TablasInformes (1)'!H255 -> 8
B36: Italia | C36: =+'TablasInformes (1)'!C256 -> 10 | D36: =+'TablasInformes (1)'!D256 -> 5 | E36: =+'TablasInformes (1)'!E256 -> 8 | F36: =+'TablasInformes (1)'!F256 -> 11 | G36: =+'TablasInformes (1)'!G256 -> 6 | H36: =+'TablasInformes (1)'!H256 -> 8
B37: Centro Europa | C37: =+'TablasInformes (1)'!C257 -> 10 | D37: =+'TablasInformes (1)'!D257 -> 5 | E37: =+'TablasInformes (1)'!E257 -> 5 | F37: =+'TablasInformes (1)'!F257 -> 11 | G37: =+'TablasInformes (1)'!G257 -> 6 | H37: =+'TablasInformes (1)'!H257 -> 8
B38: Polonia | C38: =+'TablasInformes (1)'!C258 -> 10 | D38: =+'TablasInformes (1)'!D258 -> 6 | E38: =+'TablasInformes (1)'!E258 -> 6 | F38: =+'TablasInformes (1)'!F258 -> 11 | G38: =+'TablasInformes (1)'!G258 -> 6 | H38: =+'TablasInformes (1)'!H258 -> 8
B39: Mexico | C39: =+'TablasInformes (1)'!C259 -> 10 | D39: =+'TablasInformes (1)'!D259 -> 6 | E39: =+'TablasInformes (1)'!E259 -> 7 | F39: =+'TablasInformes (1)'!F259 -> 11 | G39: =+'TablasInformes (1)'!G259 -> 6 | H39: =+'TablasInformes (1)'!H259 -> 8

Sheet 13, 14 y 15
A1: 13
A2: Priorizacion segmentos de demanda. Drink2Go
B3: =+'TablasInformes (1)'!B263 -> 2023 | C3: =+'TablasInformes (1)'!C263 -> 2024 | D3: =+'TablasInformes (1)'!D263 -> 2025 | E3: =+'TablasInformes (1)'!E263 -> 2026 | F3: =+'TablasInformes (1)'!F263 -> 2027 | G3: =+'TablasInformes (1)'!G263 -> 2028
A4: Jovenes | B4: =+'TablasInformes (1)'!B265 -> 7 | C4: =+'TablasInformes (1)'!C265 -> 4 | D4: =+'TablasInformes (1)'!D265 -> 4 | E4: =+'TablasInformes (1)'!E265 -> 4 | F4: =+'TablasInformes (1)'!F265 -> 4 | G4: =+'TablasInformes (1)'!G265 -> 4
A5: Adultos | B5: =+'TablasInformes (1)'!B266 -> 7 | C5: =+'TablasInformes (1)'!C266 -> 8 | D5: =+'TablasInformes (1)'!D266 -> 8 | E5: =+'TablasInformes (1)'!E266 -> 8 | F5: =+'TablasInformes (1)'!F266 -> 8 | G5: =+'TablasInformes (1)'!G266 -> 8
A6: Deportistas | B6: =+'TablasInformes (1)'!B267 -> 7 | C6: =+'TablasInformes (1)'!C267 -> 9 | D6: =+'TablasInformes (1)'!D267 -> 9 | E6: =+'TablasInformes (1)'!E267 -> 9 | F6: =+'TablasInformes (1)'!F267 -> 9 | G6: =+'TablasInformes (1)'!G267 -> 9
A16: 14
A19: Gasto en marca por producto. Drink2Go
B20: =+'TablasInformes (1)'!B271 -> 2023 | C20: =+'TablasInformes (1)'!C271 -> 2024 | D20: =+'TablasInformes (1)'!D271 -> 2025 | E20: =+'TablasInformes (1)'!E271 -> 2026 | F20: =+'TablasInformes (1)'!F271 -> 2027 | G20: =+'TablasInformes (1)'!G271 -> 2028
A21: Refrescos | B21: =+'TablasInformes (1)'!B273 -> 332640 | C21: =+'TablasInformes (1)'!C273 -> 489952 | D21: =+'TablasInformes (1)'!D273 -> 974081 | E21: =+'TablasInformes (1)'!E273 -> 1024081 | F21: =+'TablasInformes (1)'!F273 -> 1141436 | G21: =+'TablasInformes (1)'!G273 -> 1448298
A22: Isotonicas | B22: =+'TablasInformes (1)'!B274 -> 175560 | C22: =+'TablasInformes (1)'!C274 -> 284592 | D22: =+'TablasInformes (1)'!D274 -> 601072 | E22: =+'TablasInformes (1)'!E274 -> 661072 | F22: =+'TablasInformes (1)'!F274 -> 762428 | G22: =+'TablasInformes (1)'!G274 -> 1368725
A23: Zumos | B23: =+'TablasInformes (1)'!B275 -> 145530 | C23: =+'TablasInformes (1)'!C275 -> 223608 | D23: =+'TablasInformes (1)'!D275 -> 462079 | E23: =+'TablasInformes (1)'!E275 -> 522079 | F23: =+'TablasInformes (1)'!F275 -> 638668 | G23: =+'TablasInformes (1)'!G275 -> 1299978
A34: 15
A36: Evolucion del Valor de marca. Escala 10 a 100. Drink2Go
B37: =+'TablasInformes (1)'!B279 -> 2027 | C37: =+'TablasInformes (1)'!C279 -> 2027 | D37: =+'TablasInformes (1)'!D279 -> 2027 | E37: =+'TablasInformes (1)'!E279 -> 2028 | F37: =+'TablasInformes (1)'!F279 -> 2028 | G37: =+'TablasInformes (1)'!G279 -> 2028
B38: Refrescos | C38: Isotonicas | D38: Zumos | E38: Refrescos | F38: Isotonicas | G38: Zumos
A39: Espana | B39: =+'TablasInformes (1)'!B281 -> 46.8 | C39: =+'TablasInformes (1)'!C281 -> 34.1 | D39: =+'TablasInformes (1)'!D281 -> 37.7 | E39: =+'TablasInformes (1)'!E281 -> 63.6 | F39: =+'TablasInformes (1)'!F281 -> 51.6 | G39: =+'TablasInformes (1)'!G281 -> 59.8
A40: Portugal | B40: =+'TablasInformes (1)'!B282 -> 36.6 | C40: =+'TablasInformes (1)'!C282 -> 27.8 | D40: =+'TablasInformes (1)'!D282 -> 33.7 | E40: =+'TablasInformes (1)'!E282 -> 56.3 | F40: =+'TablasInformes (1)'!F282 -> 48.9 | G40: =+'TablasInformes (1)'!G282 -> 56.2
A41: Francia | B41: =+'TablasInformes (1)'!B283 -> 39.6 | C41: =+'TablasInformes (1)'!C283 -> 31.1 | D41: =+'TablasInformes (1)'!D283 -> 34.3 | E41: =+'TablasInformes (1)'!E283 -> 57.4 | F41: =+'TablasInformes (1)'!F283 -> 49 | G41: =+'TablasInformes (1)'!G283 -> 56.7
A42: Italia | B42: =+'TablasInformes (1)'!B284 -> 25.8 | C42: =+'TablasInformes (1)'!C284 -> 27.3 | D42: =+'TablasInformes (1)'!D284 -> 29.7 | E42: =+'TablasInformes (1)'!E284 -> 45.1 | F42: =+'TablasInformes (1)'!F284 -> 47.3 | G42: =+'TablasInformes (1)'!G284 -> 53.6
A43: Centro Europa | B43: =+'TablasInformes (1)'!B285 -> 17.6 | C43: =+'TablasInformes (1)'!C285 -> 16.9 | D43: =+'TablasInformes (1)'!D285 -> 17.6 | E43: =+'TablasInformes (1)'!E285 -> 37.5 | F43: =+'TablasInformes (1)'!F285 -> 38.6 | G43: =+'TablasInformes (1)'!G285 -> 41.8
A44: Polonia | B44: =+'TablasInformes (1)'!B286 -> 19.2 | C44: =+'TablasInformes (1)'!C286 -> 18 | D44: =+'TablasInformes (1)'!D286 -> 20.7 | E44: =+'TablasInformes (1)'!E286 -> 43.4 | F44: =+'TablasInformes (1)'!F286 -> 41.8 | G44: =+'TablasInformes (1)'!G286 -> 43.5
A45: Mexico | B45: =+'TablasInformes (1)'!B287 -> 23.9 | C45: =+'TablasInformes (1)'!C287 -> 21.2 | D45: =+'TablasInformes (1)'!D287 -> 26.5 | E45: =+'TablasInformes (1)'!E287 -> 43.6 | F45: =+'TablasInformes (1)'!F287 -> 42.7 | G45: =+'TablasInformes (1)'!G287 -> 46.5

Sheet 16
A1: 16
A2: Descuento Canal. Porcentaje. Drink2Go
C3: =+'TablasInformes (1)'!C291 -> 2023 | D3: =+'TablasInformes (1)'!D291 -> 2024 | E3: =+'TablasInformes (1)'!E291 -> 2025 | F3: =+'TablasInformes (1)'!F291 -> 2026 | G3: =+'TablasInformes (1)'!G291 -> 2027 | H3: =+'TablasInformes (1)'!H291 -> 2028
A4: Espana | B4: Tienda Tradicional | C4: =+'TablasInformes (1)'!C293 -> 13 | D4: =+'TablasInformes (1)'!D293 -> 16 | E4: =+'TablasInformes (1)'!E293 -> 18 | F4: =+'TablasInformes (1)'!F293 -> 19 | G4: =+'TablasInformes (1)'!G293 -> 25 | H4: =+'TablasInformes (1)'!H293 -> 29
B5: Gran Superficie | C5: =+'TablasInformes (1)'!C294 -> 25 | D5: =+'TablasInformes (1)'!D294 -> 28 | E5: =+'TablasInformes (1)'!E294 -> 31 | F5: =+'TablasInformes (1)'!F294 -> 31 | G5: =+'TablasInformes (1)'!G294 -> 31 | H5: =+'TablasInformes (1)'!H294 -> 31
B6: Hosteleria | C6: =+'TablasInformes (1)'!C295 -> 18 | D6: =+'TablasInformes (1)'!D295 -> 21 | E6: =+'TablasInformes (1)'!E295 -> 23 | F6: =+'TablasInformes (1)'!F295 -> 24 | G6: =+'TablasInformes (1)'!G295 -> 33 | H6: =+'TablasInformes (1)'!H295 -> 33
A7: Portugal | B7: Tienda Tradicional | C7: =+'TablasInformes (1)'!C296 -> 12 | D7: =+'TablasInformes (1)'!D296 -> 15 | E7: =+'TablasInformes (1)'!E296 -> 17 | F7: =+'TablasInformes (1)'!F296 -> 18 | G7: =+'TablasInformes (1)'!G296 -> 26 | H7: =+'TablasInformes (1)'!H296 -> 30
B8: Gran Superficie | C8: =+'TablasInformes (1)'!C297 -> 22 | D8: =+'TablasInformes (1)'!D297 -> 25 | E8: =+'TablasInformes (1)'!E297 -> 28 | F8: =+'TablasInformes (1)'!F297 -> 29 | G8: =+'TablasInformes (1)'!G297 -> 29 | H8: =+'TablasInformes (1)'!H297 -> 29
B9: Hosteleria | C9: =+'TablasInformes (1)'!C298 -> 21 | D9: =+'TablasInformes (1)'!D298 -> 24 | E9: =+'TablasInformes (1)'!E298 -> 26 | F9: =+'TablasInformes (1)'!F298 -> 27 | G9: =+'TablasInformes (1)'!G298 -> 31 | H9: =+'TablasInformes (1)'!H298 -> 31
A10: Francia | B10: Tienda Tradicional | C10: =+'TablasInformes (1)'!C299 -> 15 | D10: =+'TablasInformes (1)'!D299 -> 18 | E10: =+'TablasInformes (1)'!E299 -> 21 | F10: =+'TablasInformes (1)'!F299 -> 22 | G10: =+'TablasInformes (1)'!G299 -> 27 | H10: =+'TablasInformes (1)'!H299 -> 31
B11: Gran Superficie | C11: =+'TablasInformes (1)'!C300 -> 27 | D11: =+'TablasInformes (1)'!D300 -> 30 | E11: =+'TablasInformes (1)'!E300 -> 33 | F11: =+'TablasInformes (1)'!F300 -> 33 | G11: =+'TablasInformes (1)'!G300 -> 33 | H11: =+'TablasInformes (1)'!H300 -> 33
B12: Hosteleria | C12: =+'TablasInformes (1)'!C301 -> 13 | D12: =+'TablasInformes (1)'!D301 -> 16 | E12: =+'TablasInformes (1)'!E301 -> 18 | F12: =+'TablasInformes (1)'!F301 -> 19 | G12: =+'TablasInformes (1)'!G301 -> 28 | H12: =+'TablasInformes (1)'!H301 -> 30
A13: Italia | B13: Tienda Tradicional | C13: =+'TablasInformes (1)'!C302 -> 0 | D13: =+'TablasInformes (1)'!D302 -> 16 | E13: =+'TablasInformes (1)'!E302 -> 18 | F13: =+'TablasInformes (1)'!F302 -> 19 | G13: =+'TablasInformes (1)'!G302 -> 26 | H13: =+'TablasInformes (1)'!H302 -> 32
B14: Gran Superficie | C14: =+'TablasInformes (1)'!C303 -> 0 | D14: =+'TablasInformes (1)'!D303 -> 28 | E14: =+'TablasInformes (1)'!E303 -> 31 | F14: =+'TablasInformes (1)'!F303 -> 31 | G14: =+'TablasInformes (1)'!G303 -> 31 | H14: =+'TablasInformes (1)'!H303 -> 31
B15: Hosteleria | C15: =+'TablasInformes (1)'!C304 -> 0 | D15: =+'TablasInformes (1)'!D304 -> 21 | E15: =+'TablasInformes (1)'!E304 -> 23 | F15: =+'TablasInformes (1)'!F304 -> 24 | G15: =+'TablasInformes (1)'!G304 -> 30 | H15: =+'TablasInformes (1)'!H304 -> 30
A16: Centro Europa | B16: Tienda Tradicional | C16: =+'TablasInformes (1)'!C305 -> 0 | D16: =+'TablasInformes (1)'!D305 -> 0 | E16: =+'TablasInformes (1)'!E305 -> 0 | F16: =+'TablasInformes (1)'!F305 -> 0 | G16: =+'TablasInformes (1)'!G305 -> 22 | H16: =+'TablasInformes (1)'!H305 -> 29
B17: Gran Superficie | C17: =+'TablasInformes (1)'!C306 -> 0 | D17: =+'TablasInformes (1)'!D306 -> 0 | E17: =+'TablasInformes (1)'!E306 -> 0 | F17: =+'TablasInformes (1)'!F306 -> 0 | G17: =+'TablasInformes (1)'!G306 -> 24 | H17: =+'TablasInformes (1)'!H306 -> 24
B18: Hosteleria | C18: =+'TablasInformes (1)'!C307 -> 0 | D18: =+'TablasInformes (1)'!D307 -> 0 | E18: =+'TablasInformes (1)'!E307 -> 0 | F18: =+'TablasInformes (1)'!F307 -> 0 | G18: =+'TablasInformes (1)'!G307 -> 25 | H18: =+'TablasInformes (1)'!H307 -> 30
A19: Polonia | B19: Tienda Tradicional | C19: =+'TablasInformes (1)'!C308 -> 0 | D19: =+'TablasInformes (1)'!D308 -> 0 | E19: =+'TablasInformes (1)'!E308 -> 0 | F19: =+'TablasInformes (1)'!F308 -> 16 | G19: =+'TablasInformes (1)'!G308 -> 24 | H19: =+'TablasInformes (1)'!H308 -> 31
B20: Gran Superficie | C20: =+'TablasInformes (1)'!C309 -> 0 | D20: =+'TablasInformes (1)'!D309 -> 0 | E20: =+'TablasInformes (1)'!E309 -> 0 | F20: =+'TablasInformes (1)'!F309 -> 20 | G20: =+'TablasInformes (1)'!G309 -> 27 | H20: =+'TablasInformes (1)'!H309 -> 29
B21: Hosteleria | C21: =+'TablasInformes (1)'!C310 -> 0 | D21: =+'TablasInformes (1)'!D310 -> 0 | E21: =+'TablasInformes (1)'!E310 -> 0 | F21: =+'TablasInformes (1)'!F310 -> 22 | G21: =+'TablasInformes (1)'!G310 -> 29 | H21: =+'TablasInformes (1)'!H310 -> 31
A22: Mexico | B22: Tienda Tradicional | C22: =+'TablasInformes (1)'!C311 -> 0 | D22: =+'TablasInformes (1)'!D311 -> 0 | E22: =+'TablasInformes (1)'!E311 -> 16 | F22: =+'TablasInformes (1)'!F311 -> 20 | G22: =+'TablasInformes (1)'!G311 -> 28 | H22: =+'TablasInformes (1)'!H311 -> 31
B23: Gran Superficie | C23: =+'TablasInformes (1)'!C312 -> 0 | D23: =+'TablasInformes (1)'!D312 -> 0 | E23: =+'TablasInformes (1)'!E312 -> 19 | F23: =+'TablasInformes (1)'!F312 -> 20 | G23: =+'TablasInformes (1)'!G312 -> 27 | H23: =+'TablasInformes (1)'!H312 -> 29
B24: Hosteleria | C24: =+'TablasInformes (1)'!C313 -> 0 | D24: =+'TablasInformes (1)'!D313 -> 0 | E24: =+'TablasInformes (1)'!E313 -> 21 | F24: =+'TablasInformes (1)'!F313 -> 26 | G24: =+'TablasInformes (1)'!G313 -> 31 | H24: =+'TablasInformes (1)'!H313 -> 31

Sheet 17, 18 y 19
A1: 17
A2: Promocion punto de venta por canal. Drink2Go
B3: =+'TablasInformes (1)'!B317 -> 2027 | C3: =+'TablasInformes (1)'!C317 -> 2027 | D3: =+'TablasInformes (1)'!D317 -> 2027 | E3: =+'TablasInformes (1)'!E317 -> 2028 | F3: =+'TablasInformes (1)'!F317 -> 2028 | G3: =+'TablasInformes (1)'!G317 -> 2028
B4: Tienda Tradicional | C4: Gran Superficie | D4: Hosteleria | E4: Tienda Tradicional | F4: Gran Superficie | G4: Hosteleria
A5: Espana | B5: =+'TablasInformes (1)'!B319 -> 104186 | C5: =+'TablasInformes (1)'!C319 -> 157894 | D5: =+'TablasInformes (1)'!D319 -> 43410 | E5: =+'TablasInformes (1)'!E319 -> 192394 | F5: =+'TablasInformes (1)'!F319 -> 157894 | G5: =+'TablasInformes (1)'!G319 -> 143234
A6: Portugal | B6: =+'TablasInformes (1)'!B320 -> 38524 | C6: =+'TablasInformes (1)'!C320 -> 81997 | D6: =+'TablasInformes (1)'!D320 -> 17363 | E6: =+'TablasInformes (1)'!E320 -> 234543 | F6: =+'TablasInformes (1)'!F320 -> 176788 | G6: =+'TablasInformes (1)'!G320 -> 232345
A7: Francia | B7: =+'TablasInformes (1)'!B321 -> 83927 | C7: =+'TablasInformes (1)'!C321 -> 192937 | D7: =+'TablasInformes (1)'!D321 -> 150550 | E7: =+'TablasInformes (1)'!E321 -> 165367 | F7: =+'TablasInformes (1)'!F321 -> 192937 | G7: =+'TablasInformes (1)'!G321 -> 150550
A8: Italia | B8: =+'TablasInformes (1)'!B322 -> 108526 | C8: =+'TablasInformes (1)'!C322 -> 165375 | D8: =+'TablasInformes (1)'!D322 -> 123498 | E8: =+'TablasInformes (1)'!E322 -> 108526 | F8: =+'TablasInformes (1)'!F322 -> 165375 | G8: =+'TablasInformes (1)'!G322 -> 123498
A9: Centro Europa | B9: =+'TablasInformes (1)'!B323 -> 95000 | C9: =+'TablasInformes (1)'!C323 -> 90520 | D9: =+'TablasInformes (1)'!D323 -> 85730 | E9: =+'TablasInformes (1)'!E323 -> 196534 | F9: =+'TablasInformes (1)'!F323 -> 154345 | G9: =+'TablasInformes (1)'!G323 -> 178943
A10: Polonia | B10: =+'TablasInformes (1)'!B324 -> 132540 | C10: =+'TablasInformes (1)'!C324 -> 164600 | D10: =+'TablasInformes (1)'!D324 -> 122340 | E10: =+'TablasInformes (1)'!E324 -> 132540 | F10: =+'TablasInformes (1)'!F324 -> 164600 | G10: =+'TablasInformes (1)'!G324 -> 154567
A11: Mexico | B11: =+'TablasInformes (1)'!B325 -> 120150 | C11: =+'TablasInformes (1)'!C325 -> 164600 | D11: =+'TablasInformes (1)'!D325 -> 132234 | E11: =+'TablasInformes (1)'!E325 -> 187654 | F11: =+'TablasInformes (1)'!F325 -> 164600 | G11: =+'TablasInformes (1)'!G325 -> 156765
A22: 18
A24: Cobertura por canal. Porcentaje.Drink2Go
B25: Tienda Tradicional | C25: Gran Superficie | D25: Hosteleria
A26: Espana | B26: =+'TablasInformes (1)'!B330 -> 0.118 | C26: =+'TablasInformes (1)'!C330 -> 0.076 | D26: =+'TablasInformes (1)'!D330 -> 0.03
A27: Portugal | B27: =+'TablasInformes (1)'!B331 -> 0.063 | C27: =+'TablasInformes (1)'!C331 -> 0.062 | D27: =+'TablasInformes (1)'!D331 -> 0.019
A28: Francia | B28: =+'TablasInformes (1)'!B332 -> 0.058 | C28: =+'TablasInformes (1)'!C332 -> 0.049 | D28: =+'TablasInformes (1)'!D332 -> 0.026
A29: Italia | B29: =+'TablasInformes (1)'!B333 -> 0.029 | C29: =+'TablasInformes (1)'!C333 -> 0.021 | D29: =+'TablasInformes (1)'!D333 -> 0.028
A30: Centro Europa | B30: =+'TablasInformes (1)'!B334 -> 0.026 | C30: =+'TablasInformes (1)'!C334 -> 0.021 | D30: =+'TablasInformes (1)'!D334 -> 0.026
A31: Polonia | B31: =+'TablasInformes (1)'!B335 -> 0.033 | C31: =+'TablasInformes (1)'!C335 -> 0.027 | D31: =+'TablasInformes (1)'!D335 -> 0.029
A32: Mexico | B32: =+'TablasInformes (1)'!B336 -> 0.032 | C32: =+'TablasInformes (1)'!C336 -> 0.021 | D32: =+'TablasInformes (1)'!D336 -> 0.031
A41: 19
A42: Incentivo de ventas por producto. Drink2Go
B43: =+'TablasInformes (1)'!B340 -> 2027 | C43: =+'TablasInformes (1)'!C340 -> 2027 | D43: =+'TablasInformes (1)'!D340 -> 2027 | E43: =+'TablasInformes (1)'!E340 -> 2028 | F43: =+'TablasInformes (1)'!F340 -> 2028 | G43: =+'TablasInformes (1)'!G340 -> 2028
B44: Refrescos | C44: Isotonicas | D44: Zumos | E44: Refrescos | F44: Isotonicas | G44: Zumos
A45: Ingresos | B45: =+'TablasInformes (1)'!B342 -> 10519803 | C45: =+'TablasInformes (1)'!C342 -> 5061799 | D45: =+'TablasInformes (1)'!D342 -> 4247517 | E45: =+'TablasInformes (1)'!E342 -> 12402359 | F45: =+'TablasInformes (1)'!F342 -> 5176663 | G45: =+'TablasInformes (1)'!G342 -> 3938970
A46: % Incentivos | B46: =+'TablasInformes (1)'!B343 -> 0.93 | C46: =+'TablasInformes (1)'!C343 -> 0.84 | D46: =+'TablasInformes (1)'!D343 -> 0.78 | E46: =+'TablasInformes (1)'!E343 -> 1.05 | F46: =+'TablasInformes (1)'!F343 -> 1 | G46: =+'TablasInformes (1)'!G343 -> 1.09
A47: Volumen Incentivos | B47: =+'TablasInformes (1)'!B344 -> 978342 | C47: =+'TablasInformes (1)'!C344 -> 425191 | D47: =+'TablasInformes (1)'!D344 -> 331306 | E47: =+'TablasInformes (1)'!E344 -> 1302248 | F47: =+'TablasInformes (1)'!F344 -> 517666 | G47: =+'TablasInformes (1)'!G344 -> 429348

Sheet 20
A1: 20
A2: Nivel de precios por compania.
C3: =+'TablasInformes (1)'!C348 -> 2027 | D3: =+'TablasInformes (1)'!D348 -> 2027 | E3: =+'TablasInformes (1)'!E348 -> 2027 | F3: =+'TablasInformes (1)'!F348 -> 2027 | G3: =+'TablasInformes (1)'!G348 -> 2027 | H3: =+'TablasInformes (1)'!H348 -> 2028 | I3: =+'TablasInformes (1)'!I348 -> 2028 | J3: =+'TablasInformes (1)'!J348 -> 2028 | ... L3: =+'TablasInformes (1)'!L348 -> 2028
C4: GlobalBiz | D4: FreshMarket | E4: SparklingCo | F4: QualityMax | G4: Drink2Go | H4: GlobalBiz | I4: FreshMarket | J4: SparklingCo | K4: QualityMax | L4: Drink2Go
A5: Espana | B5: Refrescos | C5: =+'TablasInformes (1)'!C350 -> 18 | D5: =+'TablasInformes (1)'!D350 -> 16 | E5: =+'TablasInformes (1)'!E350 -> 17 | F5: =+'TablasInformes (1)'!F350 -> 2 | G5: =+'TablasInformes (1)'!G350 -> 2 | H5: =+'TablasInformes (1)'!H350 -> 19 | I5: =+'TablasInformes (1)'!I350 -> 17 | J5: =+'TablasInformes (1)'!J350 -> 17 | ... L5: =+'TablasInformes (1)'!L350 -> 25
B6: Isotonicas | C6: =+'TablasInformes (1)'!C351 -> 28 | D6: =+'TablasInformes (1)'!D351 -> 25 | E6: =+'TablasInformes (1)'!E351 -> 24 | F6: =+'TablasInformes (1)'!F351 -> 27 | G6: =+'TablasInformes (1)'!G351 -> 28 | H6: =+'TablasInformes (1)'!H351 -> 28 | I6: =+'TablasInformes (1)'!I351 -> 26 | J6: =+'TablasInformes (1)'!J351 -> 24 | ... L6: =+'TablasInformes (1)'!L351 -> 28
B7: Zumos | C7: =+'TablasInformes (1)'!C352 -> 31 | D7: =+'TablasInformes (1)'!D352 -> 28 | E7: =+'TablasInformes (1)'!E352 -> 27 | F7: =+'TablasInformes (1)'!F352 -> 32 | G7: =+'TablasInformes (1)'!G352 -> 3 | H7: =+'TablasInformes (1)'!H352 -> 31 | I7: =+'TablasInformes (1)'!I352 -> 3 | J7: =+'TablasInformes (1)'!J352 -> 27 | ... L7: =+'TablasInformes (1)'!L352 -> 29
A8: Portugal | B8: Refrescos | C8: =+'TablasInformes (1)'!C353 -> 18 | D8: =+'TablasInformes (1)'!D353 -> 16 | E8: =+'TablasInformes (1)'!E353 -> 17 | F8: =+'TablasInformes (1)'!F353 -> 19 | G8: =+'TablasInformes (1)'!G353 -> 2 | H8: =+'TablasInformes (1)'!H353 -> 19 | I8: =+'TablasInformes (1)'!I353 -> 17 | J8: =+'TablasInformes (1)'!J353 -> 17 | ... L8: =+'TablasInformes (1)'!L353 -> 24
B9: Isotonicas | C9: =+'TablasInformes (1)'!C354 -> 25 | D9: =+'TablasInformes (1)'!D354 -> 24 | E9: =+'TablasInformes (1)'!E354 -> 23 | F9: =+'TablasInformes (1)'!F354 -> 27 | G9: =+'TablasInformes (1)'!G354 -> 28 | H9: =+'TablasInformes (1)'!H354 -> 26 | I9: =+'TablasInformes (1)'!I354 -> 25 | J9: =+'TablasInformes (1)'!J354 -> 23 | ... L9: =+'TablasInformes (1)'!L354 -> 28
B10: Zumos | C10: =+'TablasInformes (1)'!C355 -> 32 | D10: =+'TablasInformes (1)'!D355 -> 28 | E10: =+'TablasInformes (1)'!E355 -> 27 | F10: =+'TablasInformes (1)'!F355 -> 34 | G10: =+'TablasInformes (1)'!G355 -> 3 | H10: =+'TablasInformes (1)'!H355 -> 31 | I10: =+'TablasInformes (1)'!I355 -> 3 | J10: =+'TablasInformes (1)'!J355 -> 27 | ... L10: =+'TablasInformes (1)'!L355 -> 29
A11: Francia | B11: Refrescos | C11: =+'TablasInformes (1)'!C356 -> 2 | D11: =+'TablasInformes (1)'!D356 -> 19 | E11: =+'TablasInformes (1)'!E356 -> 17 | F11: =+'TablasInformes (1)'!F356 -> 21 | G11: =+'TablasInformes (1)'!G356 -> 23 | H11: =+'TablasInformes (1)'!H356 -> 2 | I11: =+'TablasInformes (1)'!I356 -> 2 | J11: =+'TablasInformes (1)'!J356 -> 18 | ... L11: =+'TablasInformes (1)'!L356 -> 27
B12: Isotonicas | C12: =+'TablasInformes (1)'!C357 -> 28 | D12: =+'TablasInformes (1)'!D357 -> 28 | E12: =+'TablasInformes (1)'!E357 -> 25 | F12: =+'TablasInformes (1)'!F357 -> 28 | G12: =+'TablasInformes (1)'!G357 -> 28 | H12: =+'TablasInformes (1)'!H357 -> 28 | I12: =+'TablasInformes (1)'!I357 -> 29 | J12: =+'TablasInformes (1)'!J357 -> 27 | ... L12: =+'TablasInformes (1)'!L357 -> 28
B13: Zumos | C13: =+'TablasInformes (1)'!C358 -> 32 | D13: =+'TablasInformes (1)'!D358 -> 33 | E13: =+'TablasInformes (1)'!E358 -> 3 | F13: =+'TablasInformes (1)'!F358 -> 33 | G13: =+'TablasInformes (1)'!G358 -> 32 | H13: =+'TablasInformes (1)'!H358 -> 32 | I13: =+'TablasInformes (1)'!I358 -> 35 | J13: =+'TablasInformes (1)'!J358 -> 32 | ... L13: =+'TablasInformes (1)'!L358 -> 3
A14: Italia | B14: Refrescos | C14: =+'TablasInformes (1)'!C359 -> 22 | D14: =+'TablasInformes (1)'!D359 -> 16 | E14: =+'TablasInformes (1)'!E359 -> 17 | F14: =+'TablasInformes (1)'!F359 -> 22 | G14: =+'TablasInformes (1)'!G359 -> 24 | H14: =+'TablasInformes (1)'!H359 -> 22 | I14: =+'TablasInformes (1)'!I359 -> 17 | J14: =+'TablasInformes (1)'!J359 -> 17 | ... L14: =+'TablasInformes (1)'!L359 -> 28
B15: Isotonicas | C15: =+'TablasInformes (1)'!C360 -> 29 | D15: =+'TablasInformes (1)'!D360 -> 25 | E15: =+'TablasInformes (1)'!E360 -> 24 | F15: =+'TablasInformes (1)'!F360 -> 27 | G15: =+'TablasInformes (1)'!G360 -> 3 | H15: =+'TablasInformes (1)'!H360 -> 29 | I15: =+'TablasInformes (1)'!I360 -> 26 | J15: =+'TablasInformes (1)'!J360 -> 24 | ... L15: =+'TablasInformes (1)'!L360 -> 31
B16: Zumos | C16: =+'TablasInformes (1)'!C361 -> 36 | D16: =+'TablasInformes (1)'!D361 -> 28 | E16: =+'TablasInformes (1)'!E361 -> 27 | F16: =+'TablasInformes (1)'!F361 -> 32 | G16: =+'TablasInformes (1)'!G361 -> 34 | H16: =+'TablasInformes (1)'!H361 -> 36 | I16: =+'TablasInformes (1)'!I361 -> 3 | J16: =+'TablasInformes (1)'!J361 -> 27 | ... L16: =+'TablasInformes (1)'!L361 -> 34
A17: Centro Europa | B17: Refrescos | C17: =+'TablasInformes (1)'!C362 -> 22 | D17: =+'TablasInformes (1)'!D362 -> 16 | E17: =+'TablasInformes (1)'!E362 -> 15 | F17: =+'TablasInformes (1)'!F362 -> 25 | G17: =+'TablasInformes (1)'!G362 -> 28 | H17: =+'TablasInformes (1)'!H362 -> 23 | I17: =+'TablasInformes (1)'!I362 -> 17 | J17: =+'TablasInformes (1)'!J362 -> 16 | ... L17: =+'TablasInformes (1)'!L362 -> 28
B18: Isotonicas | C18: =+'TablasInformes (1)'!C363 -> 3 | D18: =+'TablasInformes (1)'!D363 -> 25 | E18: =+'TablasInformes (1)'!E363 -> 24 | F18: =+'TablasInformes (1)'!F363 -> 3 | G18: =+'TablasInformes (1)'!G363 -> 34 | H18: =+'TablasInformes (1)'!H363 -> 3 | I18: =+'TablasInformes (1)'!I363 -> 26 | J18: =+'TablasInformes (1)'!J363 -> 24 | ... L18: =+'TablasInformes (1)'!L363 -> 32
B19: Zumos | C19: =+'TablasInformes (1)'!C364 -> 35 | D19: =+'TablasInformes (1)'!D364 -> 28 | E19: =+'TablasInformes (1)'!E364 -> 23 | F19: =+'TablasInformes (1)'!F364 -> 35 | G19: =+'TablasInformes (1)'!G364 -> 35 | H19: =+'TablasInformes (1)'!H364 -> 35 | I19: =+'TablasInformes (1)'!I364 -> 3 | J19: =+'TablasInformes (1)'!J364 -> 27 | ... L19: =+'TablasInformes (1)'!L364 -> 32
A20: Polonia | B20: Refrescos | C20: =+'TablasInformes (1)'!C365 -> 22 | D20: =+'TablasInformes (1)'!D365 -> 17 | E20: =+'TablasInformes (1)'!E365 -> 16 | F20: =+'TablasInformes (1)'!F365 -> 25 | G20: =+'TablasInformes (1)'!G365 -> 26 | H20: =+'TablasInformes (1)'!H365 -> 22 | I20: =+'TablasInformes (1)'!I365 -> 18 | J20: =+'TablasInformes (1)'!J365 -> 16 | ... L20: =+'TablasInformes (1)'!L365 -> 27
B21: Isotonicas | C21: =+'TablasInformes (1)'!C366 -> 31 | D21: =+'TablasInformes (1)'!D366 -> 26 | E21: =+'TablasInformes (1)'!E366 -> 25 | F21: =+'TablasInformes (1)'!F366 -> 3 | G21: =+'TablasInformes (1)'!G366 -> 32 | H21: =+'TablasInformes (1)'!H366 -> 31 | I21: =+'TablasInformes (1)'!I366 -> 27 | J21: =+'TablasInformes (1)'!J366 -> 25 | ... L21: =+'TablasInformes (1)'!L366 -> 32
B22: Zumos | C22: =+'TablasInformes (1)'!C367 -> 36 | D22: =+'TablasInformes (1)'!D367 -> 31 | E22: =+'TablasInformes (1)'!E367 -> 3 | F22: =+'TablasInformes (1)'!F367 -> 35 | G22: =+'TablasInformes (1)'!G367 -> 38 | H22: =+'TablasInformes (1)'!H367 -> 36 | I22: =+'TablasInformes (1)'!I367 -> 33 | J22: =+'TablasInformes (1)'!J367 -> 3 | ... L22: =+'TablasInformes (1)'!L367 -> 35
A23: Mexico | B23: Refrescos | C23: =+'TablasInformes (1)'!C368 -> 22 | D23: =+'TablasInformes (1)'!D368 -> 16 | E23: =+'TablasInformes (1)'!E368 -> 15 | F23: =+'TablasInformes (1)'!F368 -> 23 | G23: =+'TablasInformes (1)'!G368 -> 3 | H23: =+'TablasInformes (1)'!H368 -> 23 | I23: =+'TablasInformes (1)'!I368 -> 17 | J23: =+'TablasInformes (1)'!J368 -> 16 | ... L23: =+'TablasInformes (1)'!L368 -> 32
B24: Isotonicas | C24: =+'TablasInformes (1)'!C369 -> 31 | D24: =+'TablasInformes (1)'!D369 -> 25 | E24: =+'TablasInformes (1)'!E369 -> 24 | F24: =+'TablasInformes (1)'!F369 -> 28 | G24: =+'TablasInformes (1)'!G369 -> 29 | H24: =+'TablasInformes (1)'!H369 -> 31 | I24: =+'TablasInformes (1)'!I369 -> 26 | J24: =+'TablasInformes (1)'!J369 -> 24 | ... L24: =+'TablasInformes (1)'!L369 -> 33
B25: Zumos | C25: =+'TablasInformes (1)'!C370 -> 36 | D25: =+'TablasInformes (1)'!D370 -> 28 | E25: =+'TablasInformes (1)'!E370 -> 27 | F25: =+'TablasInformes (1)'!F370 -> 33 | G25: =+'TablasInformes (1)'!G370 -> 5 | H25: =+'TablasInformes (1)'!H370 -> 36 | I25: =+'TablasInformes (1)'!I370 -> 3 | J25: =+'TablasInformes (1)'!J370 -> 27 | ... L25: =+'TablasInformes (1)'!L370 -> 38

Sheet 21, 22, 23, y 24
A1: 21
A2: Analisis del valor de marca de las companias por mercados.
B3: GlobalBiz | C3: FreshMarket | D3: SparklingCo | E3: QualityMax | F3: Drink2Go
A4: Espana | B4: =+'TablasInformes (1)'!B375 -> 52 | C4: =+'TablasInformes (1)'!C375 -> 60 | D4: =+'TablasInformes (1)'!D375 -> 38 | E4: =+'TablasInformes (1)'!E375 -> 38 | F4: =+'TablasInformes (1)'!F375 -> 60
A5: Portugal | B5: =+'TablasInformes (1)'!B376 -> 44 | C5: =+'TablasInformes (1)'!C376 -> 51 | D5: =+'TablasInformes (1)'!D376 -> 32 | E5: =+'TablasInformes (1)'!E376 -> 32 | F5: =+'TablasInformes (1)'!F376 -> 56
A6: Francia | B6: =+'TablasInformes (1)'!B377 -> 50 | C6: =+'TablasInformes (1)'!C377 -> 55 | D6: =+'TablasInformes (1)'!D377 -> 37 | E6: =+'TablasInformes (1)'!E377 -> 34 | F6: =+'TablasInformes (1)'!F377 -> 54
A7: Italia | B7: =+'TablasInformes (1)'!B378 -> 38 | C7: =+'TablasInformes (1)'!C378 -> 48 | D7: =+'TablasInformes (1)'!D378 -> 29 | E7: =+'TablasInformes (1)'!E378 -> 26 | F7: =+'TablasInformes (1)'!F378 -> 47
A8: Centro Europa | B8: =+'TablasInformes (1)'!B379 -> 26 | C8: =+'TablasInformes (1)'!C379 -> 36 | D8: =+'TablasInformes (1)'!D379 -> 14 | E8: =+'TablasInformes (1)'!E379 -> 15 | F8: =+'TablasInformes (1)'!F379 -> 38
A9: Polonia | B9: =+'TablasInformes (1)'!B380 -> 31 | C9: =+'TablasInformes (1)'!C380 -> 40 | D9: =+'TablasInformes (1)'!D380 -> 20 | E9: =+'TablasInformes (1)'!E380 -> 20 | F9: =+'TablasInformes (1)'!F380 -> 43
A10: Mexico | B10: =+'TablasInformes (1)'!B381 -> 35 | C10: =+'TablasInformes (1)'!C381 -> 44 | D10: =+'TablasInformes (1)'!D381 -> 24 | E10: =+'TablasInformes (1)'!E381 -> 24 | F10: =+'TablasInformes (1)'!F381 -> 44
A20: 22
A21: Impacto de las celebridades por mercado.
A22: Puntos adicionales en Valor de Marca.
B23: Espana | C23: Portugal | D23: Francia | E23: Italia | F23: Centro Europa | G23: Polonia | H23: Mexico
A24: Mensi | B24: =+'TablasInformes (1)'!B387 -> 220 | C24: =+'TablasInformes (1)'!C387 -> 160 | D24: =+'TablasInformes (1)'!D387 -> 140 | E24: =+'TablasInformes (1)'!E387 -> 190 | F24: =+'TablasInformes (1)'!F387 -> 150 | G24: =+'TablasInformes (1)'!G387 -> 120 | H24: =+'TablasInformes (1)'!H387 -> 220
A25: Polinsky | B25: =+'TablasInformes (1)'!B388 -> 130 | C25: =+'TablasInformes (1)'!C388 -> 120 | D25: =+'TablasInformes (1)'!D388 -> 170 | E25: =+'TablasInformes (1)'!E388 -> 160 | F25: =+'TablasInformes (1)'!F388 -> 170 | G25: =+'TablasInformes (1)'!G388 -> 220 | H25: =+'TablasInformes (1)'!H388 -> 110
A26: Romano | B26: =+'TablasInformes (1)'!B389 -> 210 | C26: =+'TablasInformes (1)'!C389 -> 230 | D26: =+'TablasInformes (1)'!D389 -> 160 | E26: =+'TablasInformes (1)'!E389 -> 180 | F26: =+'TablasInformes (1)'!F389 -> 120 | G26: =+'TablasInformes (1)'!G389 -> 100 | H26: =+'TablasInformes (1)'!H389 -> 180
A27: Reno | B27: =+'TablasInformes (1)'!B390 -> 160 | C27: =+'TablasInformes (1)'!C390 -> 110 | D27: =+'TablasInformes (1)'!D390 -> 230 | E27: =+'TablasInformes (1)'!E390 -> 90 | F27: =+'TablasInformes (1)'!F390 -> 110 | G27: =+'TablasInformes (1)'!G390 -> 120 | H27: =+'TablasInformes (1)'!H390 -> 160
A28: Shakira | B28: =+'TablasInformes (1)'!B391 -> 190 | C28: =+'TablasInformes (1)'!C391 -> 200 | D28: =+'TablasInformes (1)'!D391 -> 260 | E28: =+'TablasInformes (1)'!E391 -> 150 | F28: =+'TablasInformes (1)'!F391 -> 120 | G28: =+'TablasInformes (1)'!G391 -> 110 | H28: =+'TablasInformes (1)'!H391 -> 170
A38: 23
A39: Numero de fabricas por compania.
B40: =+'TablasInformes (1)'!B395 -> 2027 | C40: =+'TablasInformes (1)'!C395 -> 2028
A41: GlobalBiz | B41: =+'TablasInformes (1)'!B397 -> 5 | C41: =+'TablasInformes (1)'!C397 -> 5
A42: FreshMarket | B42: =+'TablasInformes (1)'!B398 -> 6 | C42: =+'TablasInformes (1)'!C398 -> 6
A43: SparklingCo | B43: =+'TablasInformes (1)'!B399 -> 5 | C43: =+'TablasInformes (1)'!C399 -> 5
A44: QualityMax | B44: =+'TablasInformes (1)'!B400 -> 4 | C44: =+'TablasInformes (1)'!C400 -> 4
A45: Drink2Go | B45: =+'TablasInformes (1)'!B401 -> 4 | C45: =+'TablasInformes (1)'!C401 -> 4
A53: 24
A54: Capacidad de produccion. Drink2Go
B55: Allin One
B56: Refrescos | C56: Isotonicas | D56: Zumos
A57: Espana | B57: =+'TablasInformes (1)'!B407 -> 3304000 | C57: =+'TablasInformes (1)'!C407 -> 1227200 | D57: =+'TablasInformes (1)'!D407 -> 861400
A58: Marruecos | B58: =+'TablasInformes (1)'!B408 -> 3304000 | C58: =+'TablasInformes (1)'!C408 -> 1227200 | D58: =+'TablasInformes (1)'!D408 -> 861400
A59: Mexico | B59: =+'TablasInformes (1)'!B409 -> 0 | C59: =+'TablasInformes (1)'!C409 -> 0 | D59: =+'TablasInformes (1)'!D409 -> 0
A60: China | B60: =+'TablasInformes (1)'!B410 -> 0 | C60: =+'TablasInformes (1)'!C410 -> 0 | D60: =+'TablasInformes (1)'!D410 -> 0

Sheet 25 y 26
A1: 25 | O1: 26
A2: Analisis area de produccion. Drink2Go | P2: Porcentaje ocupacion fabrica. Costes unitario de producto.
B3: =+'TablasInformes (1)'!B414 -> 2027 | C3: =+'TablasInformes (1)'!C414 -> 2027 | D3: =+'TablasInformes (1)'!D414 -> 2027 | E3: =+'TablasInformes (1)'!E414 -> 2028 | F3: =+'TablasInformes (1)'!F414 -> 2028 | G3: =+'TablasInformes (1)'!G414 -> 2028 | R3: =+'TablasInformes (1)'!C435 -> 2027 | S3: =+'TablasInformes (1)'!D435 -> 2028
B4: Refrescos | C4: Isotonicas | D4: Zumos | E4: Refrescos | F4: Isotonicas | G4: Zumos | P4: Porcentaje Ocupacion Fabrica | Q4: Refrescos | R4: =+'TablasInformes (1)'!C437 -> 0.962 | S4: =+'TablasInformes (1)'!D437 -> 0.983
A5: Total Capacidad Produccion | B5: =+'TablasInformes (1)'!B416 -> 6440000 | C5: =+'TablasInformes (1)'!C416 -> 2392000 | D5: =+'TablasInformes (1)'!D416 -> 1679000 | E5: =+'TablasInformes (1)'!E416 -> 6608000 | F5: =+'TablasInformes (1)'!F416 -> 2454400 | G5: =+'TablasInformes (1)'!G416 -> 1722800 | Q5: Isotonicas | R5: =+'TablasInformes (1)'!C438 -> 1 | S5: =+'TablasInformes (1)'!D438 -> 1
A6: Decision Unidades a Producir | B6: =+'TablasInformes (1)'!B417 -> 7123800 | C6: =+'TablasInformes (1)'!C417 -> 3920510 | D6: =+'TablasInformes (1)'!D417 -> 2670550 | E6: =+'TablasInformes (1)'!E417 -> 7251300 | F6: =+'TablasInformes (1)'!F417 -> 4116535 | G6: =+'TablasInformes (1)'!G417 -> 2804078 | Q6: Zumos | R6: =+'TablasInformes (1)'!C439 -> 1 | S6: =+'TablasInformes (1)'!D439 -> 1
A7: Total Unid. Producidas | B7: =+'TablasInformes (1)'!B418 -> 6193504 | C7: =+'TablasInformes (1)'!C418 -> 2392000 | D7: =+'TablasInformes (1)'!D418 -> 1679000 | E7: =+'TablasInformes (1)'!E418 -> 6494808 | F7: =+'TablasInformes (1)'!F418 -> 2454400 | G7: =+'TablasInformes (1)'!G418 -> 1722800 | P7: Coste Unitario Producto | Q7: Refrescos | R7: =+'TablasInformes (1)'!C440 -> 14 | S7: =+'TablasInformes (1)'!D440 -> 13
A8: % de Ocupacion Fabricas | B8: =+'TablasInformes (1)'!B419 -> 0.962 | C8: =+'TablasInformes (1)'!C419 -> 1 | D8: =+'TablasInformes (1)'!D419 -> 1 | E8: =+'TablasInformes (1)'!E419 -> 0.983 | F8: =+'TablasInformes (1)'!F419 -> 1 | G8: =+'TablasInformes (1)'!G419 -> 1 | Q8: Isotonicas | R8: =+'TablasInformes (1)'!C441 -> 28 | S8: =+'TablasInformes (1)'!D441 -> 28
A9: Total Unidades Vendidas | B9: =+'TablasInformes (1)'!B420 -> 6029955 | C9: =+'TablasInformes (1)'!C420 -> 2393270 | D9: =+'TablasInformes (1)'!D420 -> 1723857 | E9: =+'TablasInformes (1)'!E420 -> 6383706 | F9: =+'TablasInformes (1)'!F420 -> 2432002 | G9: =+'TablasInformes (1)'!G420 -> 1721926 | Q9: Zumos | R9: =+'TablasInformes (1)'!C442 -> 49 | S9: =+'TablasInformes (1)'!D442 -> 48
A10: Unidades Inventario | B10: =+'TablasInformes (1)'!B421 -> 830692 | C10: =+'TablasInformes (1)'!C421 -> 173136 | D10: =+'TablasInformes (1)'!D421 -> 124214 | E10: =+'TablasInformes (1)'!E421 -> 941786 | F10: =+'TablasInformes (1)'!F421 -> 195526 | G10: =+'TablasInformes (1)'!G421 -> 125090
A11: % de Inventario sobre Ventas | B11: =+'TablasInformes (1)'!B422 -> 1.38 | C11: =+'TablasInformes (1)'!C422 -> 0.72 | D11: =+'TablasInformes (1)'!D422 -> 0.72 | E11: =+'TablasInformes (1)'!E422 -> 1.48 | F11: =+'TablasInformes (1)'!F422 -> 0.8 | G11: =+'TablasInformes (1)'!G422 -> 0.73
A12: Valor Inventario | B12: =+'TablasInformes (1)'!B423 -> 110477 | C12: =+'TablasInformes (1)'!C423 -> 49675 | D12: =+'TablasInformes (1)'!D423 -> 61516 | E12: =+'TablasInformes (1)'!E423 -> 119075 | F12: =+'TablasInformes (1)'!F423 -> 54748 | G12: =+'TablasInformes (1)'!G423 -> 60223
A13: Unidades Invertario Perdidas | B13: =+'TablasInformes (1)'!B424 -> 0 | C13: =+'TablasInformes (1)'!C424 -> 0 | D13: =+'TablasInformes (1)'!D424 -> 0 | E13: =+'TablasInformes (1)'!E424 -> 0 | F13: =+'TablasInformes (1)'!F424 -> 0 | G13: =+'TablasInformes (1)'!G424 -> 0
A14: Coste Unitario de Materia Prima | B14: =+'TablasInformes (1)'!B425 -> 8 | C14: =+'TablasInformes (1)'!C425 -> 14 | D14: =+'TablasInformes (1)'!D425 -> 28 | E14: =+'TablasInformes (1)'!E425 -> 8 | F14: =+'TablasInformes (1)'!F425 -> 14 | G14: =+'TablasInformes (1)'!G425 -> 28
A15: Coste Unitario de Fabricacion | B15: =+'TablasInformes (1)'!B426 -> 14 | C15: =+'TablasInformes (1)'!C426 -> 28 | D15: =+'TablasInformes (1)'!D426 -> 49 | E15: =+'TablasInformes (1)'!E426 -> 13 | F15: =+'TablasInformes (1)'!F426 -> 28 | G15: =+'TablasInformes (1)'!G426 -> 48
A16: Coste Total Fabricacion | B16: =+'TablasInformes (1)'!B427 -> 815845 | C16: =+'TablasInformes (1)'!C427 -> 682014 | D16: =+'TablasInformes (1)'!D427 -> 844986 | E16: =+'TablasInformes (1)'!E427 -> 831040 | F16: =+'TablasInformes (1)'!F427 -> 680963 | G16: =+'TablasInformes (1)'!G427 -> 818085
A17: Coste Almacenaje | B17: =+'TablasInformes (1)'!B428 -> 123002 | C17: =+'TablasInformes (1)'!C428 -> 139039 | D17: =+'TablasInformes (1)'!D428 -> 93953 | E17: =+'TablasInformes (1)'!E428 -> 138915 | F17: =+'TablasInformes (1)'!F428 -> 141511 | G17: =+'TablasInformes (1)'!G428 -> 80536
A18: Coste Transporte | B18: =+'TablasInformes (1)'!B429 -> 262229 | C18: =+'TablasInformes (1)'!C429 -> 116124 | D18: =+'TablasInformes (1)'!D429 -> 63222 | E18: =+'TablasInformes (1)'!E429 -> 294954 | F18: =+'TablasInformes (1)'!F429 -> 108744 | G18: =+'TablasInformes (1)'!G429 -> 73174
A19: Coste Distribucion | B19: =+'TablasInformes (1)'!B430 -> 422097 | C19: =+'TablasInformes (1)'!C430 -> 119664 | D19: =+'TablasInformes (1)'!D430 -> 103431 | E19: =+'TablasInformes (1)'!E430 -> 446859 | F19: =+'TablasInformes (1)'!F430 -> 121600 | G19: =+'TablasInformes (1)'!G430 -> 103316
A20: Coste Logistica Total | B20: =+'TablasInformes (1)'!B431 -> 807328 | C20: =+'TablasInformes (1)'!C431 -> 374827 | D20: =+'TablasInformes (1)'!D431 -> 260606 | E20: =+'TablasInformes (1)'!E431 -> 880728 | F20: =+'TablasInformes (1)'!F431 -> 371855 | G20: =+'TablasInformes (1)'!G431 -> 257025

Sheet 27, 28
A1: 27
A2: Analisis area de produccion. Espana Drink2Go
B3: Refrescos | C3: Isotonicas | D3: Zumos
A4: Total Capacidad Produccion | B4: =+'TablasInformes (1)'!B447 -> 3304000 | C4: =+'TablasInformes (1)'!C447 -> 1227200 | D4: =+'TablasInformes (1)'!D447 -> 861400
A5: Decision Unidades a Producir | B5: =+'TablasInformes (1)'!B448 -> 4573800 | C5: =+'TablasInformes (1)'!C448 -> 2488720 | D5: =+'TablasInformes (1)'!D448 -> 1627857
A6: Total Unid. Producidas | B6: =+'TablasInformes (1)'!B449 -> 3304000 | C6: =+'TablasInformes (1)'!C449 -> 1227200 | D6: =+'TablasInformes (1)'!D449 -> 861400
A7: % de Ocupacion Fabricas | B7: =+'TablasInformes (1)'!B450 -> 10 | C7: =+'TablasInformes (1)'!C450 -> 10 | D7: =+'TablasInformes (1)'!D450 -> 10
A8: Total Unidades Vendidas | B8: =+'TablasInformes (1)'!B451 -> 3249701 | C8: =+'TablasInformes (1)'!C451 -> 1224126 | D8: =+'TablasInformes (1)'!D451 -> 855248
A9: Unidades Inventario | B9: =+'TablasInformes (1)'!B452 -> 303026 | C9: =+'TablasInformes (1)'!C452 -> 56520 | D9: =+'TablasInformes (1)'!D452 -> 35708
A10: % de Inventario sobre Ventas | B10: =+'TablasInformes (1)'!B453 -> 0.93 | C10: =+'TablasInformes (1)'!C453 -> 0.46 | D10: =+'TablasInformes (1)'!D453 -> 0.42
A11: Unidades Invertario Perdidas | B11: =+'TablasInformes (1)'!B454 -> 0 | C11: =+'TablasInformes (1)'!C454 -> 0 | D11: =+'TablasInformes (1)'!D454 -> 0
A12: Coste Unitario de Materia Prima | B12: =+'TablasInformes (1)'!B455 -> 8 | C12: =+'TablasInformes (1)'!C455 -> 14 | D12: =+'TablasInformes (1)'!D455 -> 28
A13: Coste Unitario de Elaboracion | B13: =+'TablasInformes (1)'!B456 -> 6 | C13: =+'TablasInformes (1)'!C456 -> 14 | D13: =+'TablasInformes (1)'!D456 -> 18
A14: Coste Unitario de Fabricacion | B14: =+'TablasInformes (1)'!B457 -> 14 | C14: =+'TablasInformes (1)'!C457 -> 28 | D14: =+'TablasInformes (1)'!D457 -> 46
A15: Coste Total Fabricacion Ventas | B15: =+'TablasInformes (1)'!B458 -> 454958 | C15: =+'TablasInformes (1)'!C458 -> 342755 | D15: =+'TablasInformes (1)'!D458 -> 393414
... A17: Coste Transporte | B17: =+'TablasInformes (1)'!B460 -> 119587 | C17: =+'TablasInformes (1)'!C460 -> 44003 | D17: =+'TablasInformes (1)'!D460 -> 28026
A20: 28
A21: Analisis area de produccion. Marruecos Drink2Go
B22: Refrescos | C22: Isotonicas | D22: Zumos
A23: Total Capacidad Produccion | B23: =+'TablasInformes (1)'!B465 -> 3304000 | C23: =+'TablasInformes (1)'!C465 -> 1227200 | D23: =+'TablasInformes (1)'!D465 -> 861400
A24: Decision Unidades a Producir | B24: =+'TablasInformes (1)'!B466 -> 2677500 | C24: =+'TablasInformes (1)'!C466 -> 1627815 | D24: =+'TablasInformes (1)'!D466 -> 1176221
A25: Total Unid. Producidas | B25: =+'TablasInformes (1)'!B467 -> 3190809 | C25: =+'TablasInformes (1)'!C467 -> 1227200 | D25: =+'TablasInformes (1)'!D467 -> 861400
A26: % de Ocupacion Fabricas | B26: =+'TablasInformes (1)'!B468 -> 0.966 | C26: =+'TablasInformes (1)'!C468 -> 1 | D26: =+'TablasInformes (1)'!D468 -> 1
A27: Total Unidades Vendidas | B27: =+'TablasInformes (1)'!B469 -> 3134013 | C27: =+'TablasInformes (1)'!C469 -> 1207884 | D27: =+'TablasInformes (1)'!D469 -> 866676
A28: Unidades Inventario | B28: =+'TablasInformes (1)'!B470 -> 638760 | C28: =+'TablasInformes (1)'!C470 -> 139006 | D28: =+'TablasInformes (1)'!D470 -> 89382
A29: % de Inventario sobre Ventas | B29: =+'TablasInformes (1)'!B471 -> 0.204 | C29: =+'TablasInformes (1)'!C471 -> 0.115 | D29: =+'TablasInformes (1)'!D471 -> 0.103
A30: Unidades Invertario Perdidas | B30: =+'TablasInformes (1)'!B472 -> 0 | C30: =+'TablasInformes (1)'!C472 -> 0 | D30: =+'TablasInformes (1)'!D472 -> 0
A31: Coste Unitario de Materia Prima | B31: =+'TablasInformes (1)'!B473 -> 7 | C31: =+'TablasInformes (1)'!C473 -> 16 | D31: =+'TablasInformes (1)'!D473 -> 32
A32: Coste Unitario de Elaboracion | B32: =+'TablasInformes (1)'!B474 -> 5 | C32: =+'TablasInformes (1)'!C474 -> 12 | D32: =+'TablasInformes (1)'!D474 -> 17
A33: Coste Unitario de Fabricacion | B33: =+'TablasInformes (1)'!B475 -> 12 | C33: =+'TablasInformes (1)'!C475 -> 28 | D33: =+'TablasInformes (1)'!D475 -> 49
A34: Coste Total Fabricacion Ventas | B34: =+'TablasInformes (1)'!B476 -> 376082 | C34: =+'TablasInformes (1)'!C476 -> 338208 | D34: =+'TablasInformes (1)'!D476 -> 424671
... A36: Coste Transporte | B36: =+'TablasInformes (1)'!B478 -> 175367 | C36: =+'TablasInformes (1)'!C478 -> 64741 | D36: =+'TablasInformes (1)'!D478 -> 45148

Sheet 29 - 33
A1: 29
A2: Indice de coste de elaboracion segun ocupacion fabrica.
B3: Refrescos | C3: Isotonicas | D3: Zumos
A4: Tasa Ocupacion: 10 | B4: =+'TablasInformes (1)'!B483 -> 0.79 | C4: =+'TablasInformes (1)'!C483 -> 0.79 | D4: =+'TablasInformes (1)'!D483 -> 0.79
A5: Tasa Ocupacion: 30 | B5: =+'TablasInformes (1)'!B484 -> 0.58 | C5: =+'TablasInformes (1)'!C484 -> 0.58 | D5: =+'TablasInformes (1)'!D484 -> 0.58
A6: Tasa Ocupacion: 50 | B6: =+'TablasInformes (1)'!B485 -> 0.35 | C6: =+'TablasInformes (1)'!C485 -> 0.35 | D6: =+'TablasInformes (1)'!D485 -> 0.35
A7: Tasa Ocupacion: 70 | B7: =+'TablasInformes (1)'!B486 -> 0.2 | C7: =+'TablasInformes (1)'!C486 -> 0.2 | D7: =+'TablasInformes (1)'!D486 -> 0.2
A8: Tasa Ocupacion: 90 | B8: =+'TablasInformes (1)'!B487 -> 0.08 | C8: =+'TablasInformes (1)'!C487 -> 0.08 | D8: =+'TablasInformes (1)'!D487 -> 0.08
A9: Tasa Ocupacion: 100 | B9: =+'TablasInformes (1)'!B488 -> 0.04 | C9: =+'TablasInformes (1)'!C488 -> 0.04 | D9: =+'TablasInformes (1)'!D488 -> 0.04
A22: 30
A23: Indice de coste de elaboracion por amplitud de gama.
B24: Refrescos | C24: Isotonicas | D24: Zumos
A25: AMPLITUD GAMA: 1 | B25: =+'TablasInformes (1)'!B493 -> 0 | C25: =+'TablasInformes (1)'!C493 -> 0 | D25: =+'TablasInformes (1)'!D493 -> 0
A26: AMPLITUD GAMA: 3 | B26: =+'TablasInformes (1)'!B494 -> 0.4 | C26: =+'TablasInformes (1)'!C494 -> 0.7 | D26: =+'TablasInformes (1)'!D494 -> 0.5
A27: AMPLITUD GAMA: 5 | B27: =+'TablasInformes (1)'!B495 -> 0.6 | C27: =+'TablasInformes (1)'!C495 -> 1.7 | D27: =+'TablasInformes (1)'!D495 -> 0.8
A28: AMPLITUD GAMA: 6 | B28: =+'TablasInformes (1)'!B496 -> 0.8 | C28: =+'TablasInformes (1)'!C496 -> 2.6 | D28: =+'TablasInformes (1)'!D496 -> 1
A29: AMPLITUD GAMA: 7 | B29: =+'TablasInformes (1)'!B497 -> 0.9 | C29: =+'TablasInformes (1)'!C497 -> 2.6 | D29: =+'TablasInformes (1)'!D497 -> 1.2
A30: AMPLITUD GAMA: 9 | B30: =+'TablasInformes (1)'!B498 -> 1.4 | C30: =+'TablasInformes (1)'!C498 -> 2.6 | D30: =+'TablasInformes (1)'!D498 -> 1.4
A31: AMPLITUD GAMA: 11 | B31: =+'TablasInformes (1)'!B499 -> 2.1 | C31: =+'TablasInformes (1)'!C499 -> 2.6 | D31: =+'TablasInformes (1)'!D499 -> 1.4
A32: AMPLITUD GAMA: 12 | B32: =+'TablasInformes (1)'!B500 -> 2.4 | C32: =+'TablasInformes (1)'!C500 -> 2.6 | D32: =+'TablasInformes (1)'!D500 -> 1.4
A42: 31
A43: Prioridades logisticas Mercado-Pais.
B44: España | C44: Marruecos | D44: Mexico | E44: China
A45: España | B45: =+'TablasInformes (1)'!B505 -> 1 | C45: =+'TablasInformes (1)'!C505 -> 2 | D45: =+'TablasInformes (1)'!D505 -> 4 | E45: =+'TablasInformes (1)'!E505 -> 5
A46: Portugal | B46: =+'TablasInformes (1)'!B506 -> 2 | C46: =+'TablasInformes (1)'!C506 -> 2 | D46: =+'TablasInformes (1)'!D506 -> 4 | E46: =+'TablasInformes (1)'!E506 -> 5
A47: Francia | B47: =+'TablasInformes (1)'!B507 -> 2 | C47: =+'TablasInformes (1)'!C507 -> 3 | D47: =+'TablasInformes (1)'!D507 -> 3 | E47: =+'TablasInformes (1)'!E507 -> 5
A48: Italia | B48: =+'TablasInformes (1)'!B508 -> 2 | C48: =+'TablasInformes (1)'!C508 -> 2 | D48: =+'TablasInformes (1)'!D508 -> 4 | E48: =+'TablasInformes (1)'!E508 -> 5
A49: Centro Europa | B49: =+'TablasInformes (1)'!B509 -> 3 | C49: =+'TablasInformes (1)'!C509 -> 3 | D49: =+'TablasInformes (1)'!D509 -> 4 | E49: =+'TablasInformes (1)'!E509 -> 5
A50: Polonia | B50: =+'TablasInformes (1)'!B510 -> 3 | C50: =+'TablasInformes (1)'!C510 -> 3 | D50: =+'TablasInformes (1)'!D510 -> 4 | E50: =+'TablasInformes (1)'!E510 -> 5
A51: Mexico | B51: =+'TablasInformes (1)'!B511 -> 4 | C51: =+'TablasInformes (1)'!C511 -> 4 | D51: =+'TablasInformes (1)'!D511 -> 2 | E51: =+'TablasInformes (1)'!E511 -> 4
A61: 32
A62: Coste transporte por caja de 10 unidades.
A63: Drink2Go
B64: Drink2Go
A65: Categoria 1 | B65: =+'TablasInformes (1)'!B517 -> 15
A66: Categoria 2 | B66: =+'TablasInformes (1)'!B518 -> 30
A67: Categoria 3 | B67: =+'TablasInformes (1)'!B519 -> 50
A68: Categoria 4 | B68: =+'TablasInformes (1)'!B520 -> 100
A69: Categoria 5 | B69: =+'TablasInformes (1)'!B521 -> 150
A77: 33
A78: Numero de fabricas.
C79: =+'TablasInformes (1)'!C525 -> 2023 | D79: =+'TablasInformes (1)'!D525 -> 2023 | E79: =+'TablasInformes (1)'!E525 -> 2023 | F79: =+'TablasInformes (1)'!F525 -> 2023 | G79: =+'TablasInformes (1)'!G525 -> 2023 | H79: =+'TablasInformes (1)'!H525 -> 2024 | I79: =+'TablasInformes (1)'!I525 -> 2024 | J79: =+'TablasInformes (1)'!J525 -> 2024 | ... AF79: =+'TablasInformes (1)'!AF525 -> 2028
C80: GlobalBiz | D80: FreshMarket | E80: SparklingCo | F80: QualityMax | G80: Drink2Go | H80: GlobalBiz | I80: FreshMarket | J80: SparklingCo | K80: QualityMax | L80: Drink2Go | M80: GlobalBiz | N80: FreshMarket | O80: SparklingCo | P80: QualityMax | Q80: Drink2Go | R80: GlobalBiz | S80: FreshMarket | T80: SparklingCo | U80: QualityMax | V80: Drink2Go | W80: GlobalBiz | X80: FreshMarket | Y80: SparklingCo | Z80: QualityMax | AA80: Drink2Go | AB80: GlobalBiz | AC80: FreshMarket | AD80: SparklingCo | AE80: QualityMax | AF80: Drink2Go
A81: Espana | B81: Allin One | C81: =+'TablasInformes (1)'!C527 -> 2 | D81: =+'TablasInformes (1)'!D527 -> 2 | E81: =+'TablasInformes (1)'!E527 -> 2 | F81: =+'TablasInformes (1)'!F527 -> 2 | G81: =+'TablasInformes (1)'!G527 -> 2 | H81: =+'TablasInformes (1)'!H527 -> 2 | I81: =+'TablasInformes (1)'!I527 -> 2 | J81: =+'TablasInformes (1)'!J527 -> 2 | ... AF81: =+'TablasInformes (1)'!AF527 -> 2
A82: Marruecos | B82: Allin One | C82: =+'TablasInformes (1)'!C528 -> 1 | D82: =+'TablasInformes (1)'!D528 -> 1 | E82: =+'TablasInformes (1)'!E528 -> 1 | F82: =+'TablasInformes (1)'!F528 -> 1 | G82: =+'TablasInformes (1)'!G528 -> 1 | H82: =+'TablasInformes (1)'!H528 -> 1 | I82: =+'TablasInformes (1)'!I528 -> 2 | J82: =+'TablasInformes (1)'!J528 -> 2 | ... AF82: =+'TablasInformes (1)'!AF528 -> 2
A83: Mexico | B83: Allin One | C83: =+'TablasInformes (1)'!C529 -> 0 | D83: =+'TablasInformes (1)'!D529 -> 0 | E83: =+'TablasInformes (1)'!E529 -> 0 | F83: =+'TablasInformes (1)'!F529 -> 0 | G83: =+'TablasInformes (1)'!G529 -> 0 | H83: =+'TablasInformes (1)'!H529 -> 0 | I83: =+'TablasInformes (1)'!I529 -> 0 | J83: =+'TablasInformes (1)'!J529 -> 0 | ... AF83: =+'TablasInformes (1)'!AF529 -> 0
A84: China | B84: Allin One | C84: =+'TablasInformes (1)'!C530 -> 0 | D84: =+'TablasInformes (1)'!D530 -> 0 | E84: =+'TablasInformes (1)'!E530 -> 0 | F84: =+'TablasInformes (1)'!F530 -> 0 | G84: =+'TablasInformes (1)'!G530 -> 0 | H84: =+'TablasInformes (1)'!H530 -> 0 | I84: =+'TablasInformes (1)'!I530 -> 0 | J84: =+'TablasInformes (1)'!J530 -> 0 | ... AF84: =+'TablasInformes (1)'!AF530 -> 0
C88: Espana | D88: Marruecos | E88: Mexico | F88: China
C89: Allin One | D89: Allin One | E89: Allin One | F89: Allin One
A90: =+C79 -> 2023 | B90: GlobalBiz | C90: =+C81 -> 2 | D90: =+C82 -> 1 | E90: =+C83 -> 0 | F90: =+C84 -> 0
B91: FreshMarket | C91: =+D81 -> 2 | D91: =+D82 -> 1 | E91: =+D83 -> 0 | F91: =+D84 -> 0
B92: SparklingCo | C92: =+E81 -> 2 | D92: =+E82 -> 1 | E92: =+E83 -> 0 | F92: =+E84 -> 0
B93: QualityMax | C93: =+F81 -> 2 | D93: =+F82 -> 1 | E93: =+F83 -> 0 | F93: =+F84 -> 0
B94: Drink2Go | C94: =+G81 -> 2 | D94: =+G82 -> 1 | E94: =+G83 -> 0 | F94: =+G84 -> 0
A95: =+H79 -> 2024 | B95: GlobalBiz | C95: =+H81 -> 2 | D95: =+H82 -> 1 | E95: =+H83 -> 0 | F95: =+H84 -> 0
B96: FreshMarket | C96: =+I81 -> 2 | D96: =+I82 -> 2 | E96: =+I83 -> 0 | F96: =+I84 -> 0
B97: SparklingCo | C97: =+J81 -> 2 | D97: =+J82 -> 2 | E97: =+J83 -> 0 | F97: =+J84 -> 0
B98: QualityMax | C98: =+K81 -> 3 | D98: =+K82 -> 1 | E98: =+K83 -> 0 | F98: =+K84 -> 0
B99: Drink2Go | C99: =+L81 -> 2 | D99: =+L82 -> 1 | E99: =+L83 -> 0 | F99: =+L84 -> 0
A100: =+M79 -> 2025 | B100: GlobalBiz | C100: =+M81 -> 2 | D100: =+M82 -> 2 | E100: =+M83 -> 0 | F100: =+M84 -> 0
B101: FreshMarket | C101: =+N81 -> 2 | D101: =+N82 -> 2 | E101: =+N83 -> 1 | F101: =+N84 -> 0
B102: SparklingCo | C102: =+O81 -> 2 | D102: =+O82 -> 2 | E102: =+O83 -> 0 | F102: =+O84 -> 0
B103: QualityMax | C103: =+P81 -> 3 | D103: =+P82 -> 1 | E103: =+P83 -> 0 | F103: =+P84 -> 0
B104: Drink2Go | C104: =+Q81 -> 2 | D104: =+Q82 -> 2 | E104: =+Q83 -> 0 | F104: =+Q84 -> 0
A105: =+R79 -> 2026 | B105: GlobalBiz | C105: =+R81 -> 2 | D105: =+R82 -> 2 | E105: =+R83 -> 1 | F105: =+R84 -> 0
B106: FreshMarket | C106: =+S81 -> 2 | D106: =+S82 -> 2 | E106: =+S83 -> 1 | F106: =+S84 -> 1
B107: SparklingCo | C107: =+T81 -> 2 | D107: =+T82 -> 2 | E107: =+T83 -> 0 | F107: =+T84 -> 0
B108: QualityMax | C108: =+U81 -> 3 | D108: =+U82 -> 1 | E108: =+U83 -> 0 | F108: =+U84 -> 0
B109: Drink2Go | C109: =+V81 -> 2 | D109: =+V82 -> 2 | E109: =+V83 -> 0 | F109: =+V84 -> 0
A110: =+W79 -> 2027 | B110: GlobalBiz | C110: =+W81 -> 2 | D110: =+W82 -> 2 | E110: =+W83 -> 1 | F110: =+W84 -> 0
B111: FreshMarket | C111: =+X81 -> 2 | D111: =+X82 -> 2 | E111: =+X83 -> 1 | F111: =+X84 -> 1
B112: SparklingCo | C112: =+Y81 -> 2 | D112: =+Y82 -> 2 | E112: =+Y83 -> 1 | F112: =+Y84 -> 0
B113: QualityMax | C113: =+Z81 -> 3 | D113: =+Z82 -> 1 | E113: =+Z83 -> 0 | F113: =+Z84 -> 0
B114: Drink2Go | C114: =+AA81 -> 2 | D114: =+AA82 -> 2 | E114: =+AA83 -> 0 | F114: =+AA84 -> 0
A115: =+AB79 -> 2028 | B115: GlobalBiz | C115: =+AB81 -> 2 | D115: =+AB82 -> 2 | E115: =+AB83 -> 1 | F115: =+AB84 -> 0
B116: FreshMarket | C116: =+AC81 -> 2 | D116: =+AC82 -> 2 | E116: =+AC83 -> 1 | F116: =+AC84 -> 1
B117: SparklingCo | C117: =+AD81 -> 2 | D117: =+AD82 -> 2 | E117: =+AD83 -> 1 | F117: =+AD84 -> 0
B118: QualityMax | C118: =+AE81 -> 3 | D118: =+AE82 -> 1 | E118: =+AE83 -> 0 | F118: =+AE84 -> 0
B119: Drink2Go | C119: =+AF81 -> 2 | D119: =+AF82 -> 2 | E119: =+AF83 -> 0 | F119: =+AF84 -> 0

Sheet 34 - 39
A1: 34
A2: Inventario de producto acabado en unidades por productos. Drink2Go
A3: Analisis por Trimestres
B4: =+'TablasInformes (1)'!B535 -> 2027 | C4: =+'TablasInformes (1)'!C535 -> 2027 | D4: =+'TablasInformes (1)'!D535 -> 2027 | E4: =+'TablasInformes (1)'!E535 -> 2027 | F4: =+'TablasInformes (1)'!F535 -> 2028 | G4: =+'TablasInformes (1)'!G535 -> 2028 | H4: =+'TablasInformes (1)'!H535 -> 2028 | I4: =+'TablasInformes (1)'!I535 -> 2028
B5: 1er Trim | C5: 2do Trim | D5: 3er Trim | E5: 4to Trim | F5: 1er Trim | G5: 2do Trim | H5: 3er Trim | I5: 4to Trim
A6: Refrescos | B6: =+'TablasInformes (1)'!B537 -> 527121 | C6: =+'TablasInformes (1)'!C537 -> 568007 | D6: =+'TablasInformes (1)'!D537 -> 1030954 | E6: =+'TablasInformes (1)'!E537 -> 830692 | F6: =+'TablasInformes (1)'!F537 -> 666954 | G6: =+'TablasInformes (1)'!G537 -> 694733 | H6: =+'TablasInformes (1)'!H537 -> 1169400 | I6: =+'TablasInformes (1)'!I537 -> 941786
A7: Isotonicas | B7: =+'TablasInformes (1)'!B538 -> 126236 | C7: =+'TablasInformes (1)'!C538 -> 437024 | D7: =+'TablasInformes (1)'!D538 -> 699960 | E7: =+'TablasInformes (1)'!E538 -> 173136 | F7: =+'TablasInformes (1)'!F538 -> 125308 | G7: =+'TablasInformes (1)'!G538 -> 444935 | H7: =+'TablasInformes (1)'!H538 -> 733292 | I7: =+'TablasInformes (1)'!I538 -> 195526
A8: Zumos | B8: =+'TablasInformes (1)'!B539 -> 140625 | C8: =+'TablasInformes (1)'!C539 -> 146649 | D8: =+'TablasInformes (1)'!D539 -> 169904 | E8: =+'TablasInformes (1)'!E539 -> 124214 | F8: =+'TablasInformes (1)'!F539 -> 107215 | G8: =+'TablasInformes (1)'!G539 -> 124644 | H8: =+'TablasInformes (1)'!H539 -> 159305 | I8: =+'TablasInformes (1)'!I539 -> 125090
A20: 35
A21: Coste unitario logistico. Por modalidad y producto.
B22: Mod. 1 | C22: Mod. 2 | D22: Mod. 3 | E22: Mod. 4 | F22: Mod. 5
A23: Refrescos | B23: =+'TablasInformes (1)'!B544 -> 3 | C23: =+'TablasInformes (1)'!C544 -> 4 | D23: =+'TablasInformes (1)'!D544 -> 5 | E23: =+'TablasInformes (1)'!E544 -> 7 | F23: =+'TablasInformes (1)'!F544 -> 9
A24: Isotonicas | B24: =+'TablasInformes (1)'!B545 -> 2 | C24: =+'TablasInformes (1)'!C545 -> 3 | D24: =+'TablasInformes (1)'!D545 -> 4 | E24: =+'TablasInformes (1)'!E545 -> 5 | F24: =+'TablasInformes (1)'!F545 -> 7
A25: Zumos | B25: =+'TablasInformes (1)'!B546 -> 2 | C25: =+'TablasInformes (1)'!C546 -> 3 | D25: =+'TablasInformes (1)'!D546 -> 4 | E25: =+'TablasInformes (1)'!E546 -> 6 | F25: =+'TablasInformes (1)'!F546 -> 8
A38: 36
A39: Coste base de materia prima del producto.
A40: Segun pais.
B41: Refrescos | C41: Isotonicas | D41: Zumos
A42: Espana | B42: =+'TablasInformes (1)'!B552 -> 8 | C42: =+'TablasInformes (1)'!C552 -> 14 | D42: =+'TablasInformes (1)'!D552 -> 28
A43: Marruecos | B43: =+'TablasInformes (1)'!B553 -> 7 | C43: =+'TablasInformes (1)'!C553 -> 16 | D43: =+'TablasInformes (1)'!D553 -> 32
A44: Mexico | B44: =+'TablasInformes (1)'!B554 -> 6 | C44: =+'TablasInformes (1)'!C554 -> 15 | D44: =+'TablasInformes (1)'!D554 -> 29
A45: China | B45: =+'TablasInformes (1)'!B555 -> 5 | C45: =+'TablasInformes (1)'!C555 -> 12 | D45: =+'TablasInformes (1)'!D555 -> 23
A56: 37
A57: Coste base de elaboracion del producto. Segun pais.
B58: Refrescos | C58: Isotonicas | D58: Zumos
A59: Espana | B59: =+'TablasInformes (1)'!B560 -> 8 | C59: =+'TablasInformes (1)'!C560 -> 18 | D59: =+'TablasInformes (1)'!D560 -> 27
A60: Marruecos | B60: =+'TablasInformes (1)'!B561 -> 7 | C60: =+'TablasInformes (1)'!C561 -> 16 | D60: =+'TablasInformes (1)'!D561 -> 25
A61: Mexico | B61: =+'TablasInformes (1)'!B562 -> 6 | C61: =+'TablasInformes (1)'!C562 -> 15 | D61: =+'TablasInformes (1)'!D562 -> 23
A62: China | B62: =+'TablasInformes (1)'!B563 -> 5 | C62: =+'TablasInformes (1)'!C563 -> 14 | D62: =+'TablasInformes (1)'!D563 -> 21
A75: 38
B76: Inversion | C76: Gasto Implantacion
A77: Espana | B77: =+'TablasInformes (1)'!B567 -> 8730000 | C77: =+'TablasInformes (1)'!C567 -> 780000
A78: Marruecos | B78: =+'TablasInformes (1)'!B568 -> 7639000 | C78: =+'TablasInformes (1)'!C568 -> 680000
A79: Mexico | B79: =+'TablasInformes (1)'!B569 -> 7049500 | C79: =+'TablasInformes (1)'!C569 -> 635000
A80: China | B80: =+'TablasInformes (1)'!B570 -> 6003000 | C80: =+'TablasInformes (1)'!C570 -> 490000
A94: 39
A95: Gasto en Tecnologia requerido
A96: segun nivel alcanzado.
B97: Presupuesto
A98: Nivel 3 | B98: =+'TablasInformes (1)'!B576 -> 60000
A99: Nivel 4 | B99: =+'TablasInformes (1)'!B577 -> 75000
A100: Nivel 5 | B100: =+'TablasInformes (1)'!B578 -> 150000
A101: Nivel 6 | B101: =+'TablasInformes (1)'!B579 -> 200000
A102: Nivel 7 | B102: =+'TablasInformes (1)'!B580 -> 300000
A103: Nivel 8 | B103: =+'TablasInformes (1)'!B581 -> 400000
A104: Nivel 9 | B104: =+'TablasInformes (1)'!B582 -> 500000

Sheet 40 - 47
A1: 40
A2: Ingresos totales por mercado y producto.
A3: Total companias.Euros.
B4: =+'TablasInformes (1)'!B587 -> 2027 | C4: =+'TablasInformes (1)'!C587 -> 2027 | D4: =+'TablasInformes (1)'!D587 -> 2027 | E4: =+'TablasInformes (1)'!E587 -> 2028 | F4: =+'TablasInformes (1)'!F587 -> 2028 | G4: =+'TablasInformes (1)'!G587 -> 2028
B5: Refrescos | C5: Isotonicas | D5: Zumos | E5: Refrescos | F5: Isotonicas | G5: Zumos
A6: Espana | B6: =+'TablasInformes (1)'!B589 -> 10605481 | C6: =+'TablasInformes (1)'!C589 -> 3705810 | D6: =+'TablasInformes (1)'!D589 -> 4001631 | E6: =+'TablasInformes (1)'!E589 -> 10580197 | F6: =+'TablasInformes (1)'!F589 -> 3790728 | G6: =+'TablasInformes (1)'!G589 -> 3557589
A7: Portugal | B7: =+'TablasInformes (1)'!B590 -> 2292670 | C7: =+'TablasInformes (1)'!C590 -> 398376 | D7: =+'TablasInformes (1)'!D590 -> 859426 | E7: =+'TablasInformes (1)'!E590 -> 2494104 | F7: =+'TablasInformes (1)'!F590 -> 412517 | G7: =+'TablasInformes (1)'!G590 -> 795520
A8: Francia | B8: =+'TablasInformes (1)'!B591 -> 8231616 | C8: =+'TablasInformes (1)'!C591 -> 3250815 | D8: =+'TablasInformes (1)'!D591 -> 1852396 | E8: =+'TablasInformes (1)'!E591 -> 8687127 | F8: =+'TablasInformes (1)'!F591 -> 3256484 | G8: =+'TablasInformes (1)'!G591 -> 1696616
A9: Italia | B9: =+'TablasInformes (1)'!B592 -> 17841302 | C9: =+'TablasInformes (1)'!C592 -> 12605335 | D9: =+'TablasInformes (1)'!D592 -> 10097705 | E9: =+'TablasInformes (1)'!E592 -> 16906666 | F9: =+'TablasInformes (1)'!F592 -> 11196107 | G9: =+'TablasInformes (1)'!G592 -> 8556443
A10: Centro Europa | B10: =+'TablasInformes (1)'!B593 -> 2061466 | C10: =+'TablasInformes (1)'!C593 -> 661279 | D10: =+'TablasInformes (1)'!D593 -> 171167 | E10: =+'TablasInformes (1)'!E593 -> 3007553 | F10: =+'TablasInformes (1)'!F593 -> 960933 | G10: =+'TablasInformes (1)'!G593 -> 531920
A11: Polonia | B11: =+'TablasInformes (1)'!B594 -> 5742097 | C11: =+'TablasInformes (1)'!C594 -> 2774172 | D11: =+'TablasInformes (1)'!D594 -> 1369002 | E11: =+'TablasInformes (1)'!E594 -> 7071705 | F11: =+'TablasInformes (1)'!F594 -> 3787605 | G11: =+'TablasInformes (1)'!G594 -> 2852573
A12: Mexico | B12: =+'TablasInformes (1)'!B595 -> 9466816 | C12: =+'TablasInformes (1)'!C595 -> 5454364 | D12: =+'TablasInformes (1)'!D595 -> 4874076 | E12: =+'TablasInformes (1)'!E595 -> 10359491 | F12: =+'TablasInformes (1)'!F595 -> 5654902 | G12: =+'TablasInformes (1)'!G595 -> 6548832
A13: Total ingresos | B13: =+'TablasInformes (1)'!B596 -> 56241448 | C13: =+'TablasInformes (1)'!C596 -> 28850150 | D13: =+'TablasInformes (1)'!D596 -> 23225402 | E13: =+'TablasInformes (1)'!E596 -> 59106840 | F13: =+'TablasInformes (1)'!F596 -> 29059274 | G13: =+'TablasInformes (1)'!G596 -> 24539492
A14: Variacion - | B14: =+'TablasInformes (1)'!B597 -> 0.94 | C14: =+'TablasInformes (1)'!C597 -> 0.8 | D14: =+'TablasInformes (1)'!D597 -> 1.18 | E14: =+'TablasInformes (1)'!E597 -> 0.51 | F14: =+'TablasInformes (1)'!F597 -> 0.07 | G14: =+'TablasInformes (1)'!G597 -> 0.57
A43: 41
A44: Ingresos por producto. Total companias.
B45: =+'TablasInformes (1)'!B601 -> 2023 | C45: =+'TablasInformes (1)'!C601 -> 2024 | D45: =+'TablasInformes (1)'!D601 -> 2025 | E45: =+'TablasInformes (1)'!E601 -> 2026 | F45: =+'TablasInformes (1)'!F601 -> 2027 | G45: =+'TablasInformes (1)'!G601 -> 2028
A46: Refrescos | B46: =+'TablasInformes (1)'!B602 -> 20750238 | C46: =+'TablasInformes (1)'!C602 -> 29467588 | D46: =+'TablasInformes (1)'!D602 -> 39808016 | E46: =+'TablasInformes (1)'!E602 -> 51422984 | F46: =+'TablasInformes (1)'!F602 -> 56241448 | G46: =+'TablasInformes (1)'!G602 -> 59106840
A47: Isotonicas | B47: =+'TablasInformes (1)'!B603 -> 10279750 | C47: =+'TablasInformes (1)'!C603 -> 15031299 | D47: =+'TablasInformes (1)'!D603 -> 22046504 | E47: =+'TablasInformes (1)'!E603 -> 26718448 | F47: =+'TablasInformes (1)'!F603 -> 28850150 | G47: =+'TablasInformes (1)'!G603 -> 29059274
A48: Zumos | B48: =+'TablasInformes (1)'!B604 -> 8850177 | C48: =+'TablasInformes (1)'!C604 -> 12730449 | D48: =+'TablasInformes (1)'!D604 -> 16566863 | E48: =+'TablasInformes (1)'!E604 -> 20770072 | F48: =+'TablasInformes (1)'!F604 -> 23225402 | G48: =+'TablasInformes (1)'!G604 -> 24539492
A49: Total Ingresos Companias | B49: =+'TablasInformes (1)'!B605 -> 39880164 | C49: =+'TablasInformes (1)'!C605 -> 57229336 | D49: =+'TablasInformes (1)'!D605 -> 78421384 | E49: =+'TablasInformes (1)'!E605 -> 98911504 | F49: =+'TablasInformes (1)'!F605 -> 108317000 | G49: =+'TablasInformes (1)'!G605 -> 112705608
A62: 42
A63: Unidades vendidas. Analisis por segmentos de demanda.
A64: Total companias.
B65: =+'TablasInformes (1)'!B610 -> 2023 | C65: =+'TablasInformes (1)'!C610 -> 2024 | D65: =+'TablasInformes (1)'!D610 -> 2025 | E65: =+'TablasInformes (1)'!E610 -> 2026 | F65: =+'TablasInformes (1)'!F610 -> 2027 | G65: =+'TablasInformes (1)'!G610 -> 2028
A66: Jovenes | B66: =+'TablasInformes (1)'!B611 -> 17020170 | C66: =+'TablasInformes (1)'!C611 -> 15417759 | D66: =+'TablasInformes (1)'!D611 -> 17111050 | E66: =+'TablasInformes (1)'!E611 -> 18546624 | F66: =+'TablasInformes (1)'!F611 -> 19100578 | G66: =+'TablasInformes (1)'!G611 -> 19072832
A67: Adultos | B67: =+'TablasInformes (1)'!B612 -> 9621910 | C67: =+'TablasInformes (1)'!C612 -> 14286203 | D67: =+'TablasInformes (1)'!D612 -> 21900294 | E67: =+'TablasInformes (1)'!E612 -> 27833484 | F67: =+'TablasInformes (1)'!F612 -> 31823272 | G67: =+'TablasInformes (1)'!G612 -> 32789020
A68: Deportistas | B68: =+'TablasInformes (1)'!B613 -> 6563660 | C68: =+'TablasInformes (1)'!C613 -> 6870671 | D68: =+'TablasInformes (1)'!D613 -> 8515846 | E68: =+'TablasInformes (1)'!E613 -> 9730260 | F68: =+'TablasInformes (1)'!F613 -> 10583917 | G68: =+'TablasInformes (1)'!G613 -> 10954919
A80: 43
A81: Unidades vendidas. Total companias.
B82: =+'TablasInformes (1)'!B617 -> 2023 | C82: =+'TablasInformes (1)'!C617 -> 2023 | D82: =+'TablasInformes (1)'!D617 -> 2024 | E82: =+'TablasInformes (1)'!E617 -> 2024 | F82: =+'TablasInformes (1)'!F617 -> 2025 | G82: =+'TablasInformes (1)'!G617 -> 2025 | H82: =+'TablasInformes (1)'!H617 -> 2026 | I82: =+'TablasInformes (1)'!I617 -> 2026 | ... M82: =+'TablasInformes (1)'!M617 -> 2028
A83: Refrescos | B83: =+'TablasInformes (1)'!B618 -> 21307944 | C83: =+'TablasInformes (1)'!C618 -> 0.068 | D83: =+'TablasInformes (1)'!D618 -> 22593284 | E83: =+'TablasInformes (1)'!E618 -> 0.06 | F83: =+'TablasInformes (1)'!F618 -> 28986518 | G83: =+'TablasInformes (1)'!G618 -> 0.283 | H83: =+'TablasInformes (1)'!H618 -> 34730520 | I83: =+'TablasInformes (1)'!I618 -> 0.198 | ... M83: =+'TablasInformes (1)'!M618 -> 0.017
A84: Isotonicas | B84: =+'TablasInformes (1)'!B619 -> 7014970 | C84: =+'TablasInformes (1)'!C619 -> 0.052 | D84: =+'TablasInformes (1)'!D619 -> 8085762 | E84: =+'TablasInformes (1)'!E619 -> 0.153 | F84: =+'TablasInformes (1)'!F619 -> 11183116 | G84: =+'TablasInformes (1)'!G619 -> 0.383 | H84: =+'TablasInformes (1)'!H619 -> 12857418 | I84: =+'TablasInformes (1)'!I619 -> 0.15 | ... M84: =+'TablasInformes (1)'!M619 -> 0.007
A85: Zumos | B85: =+'TablasInformes (1)'!B620 -> 4882825 | C85: =+'TablasInformes (1)'!C620 -> -0.041 | D85: =+'TablasInformes (1)'!D620 -> 5895588 | E85: =+'TablasInformes (1)'!E620 -> 0.207 | F85: =+'TablasInformes (1)'!F620 -> 7357556 | G85: =+'TablasInformes (1)'!G620 -> 0.248 | H85: =+'TablasInformes (1)'!H620 -> 8522433 | I85: =+'TablasInformes (1)'!I620 -> 0.158 | ... M85: =+'TablasInformes (1)'!M620 -> 0.06
A86: Ventas Total Companias | B86: =+'TablasInformes (1)'!B621 -> 33205740 | C86: =+'TablasInformes (1)'!C621 -> 0.047 | D86: =+'TablasInformes (1)'!D621 -> 36574632 | E86: =+'TablasInformes (1)'!E621 -> 0.102 | F86: =+'TablasInformes (1)'!F621 -> 47527192 | G86: =+'TablasInformes (1)'!G621 -> 0.3 | H86: =+'TablasInformes (1)'!H621 -> 56110368 | I86: =+'TablasInformes (1)'!I621 -> 0.181 | ... M86: =+'TablasInformes (1)'!M621 -> 0.021
A111: 44
A112: Unidades vendidas. Analisis por canal de distribucion.
A113: Total companias.
B114: =+'TablasInformes (1)'!B626 -> 2023 | C114: =+'TablasInformes (1)'!C626 -> 2024 | D114: =+'TablasInformes (1)'!D626 -> 2025 | E114: =+'TablasInformes (1)'!E626 -> 2026 | F114: =+'TablasInformes (1)'!F626 -> 2027 | G114: =+'TablasInformes (1)'!G626 -> 2028
A115: Tienda Tradicional | B115: =+'TablasInformes (1)'!B627 -> 11638165 | C115: =+'TablasInformes (1)'!C627 -> 11922127 | D115: =+'TablasInformes (1)'!D627 -> 14852909 | E115: =+'TablasInformes (1)'!E627 -> 17358234 | F115: =+'TablasInformes (1)'!F627 -> 19059052 | G115: =+'TablasInformes (1)'!G627 -> 19688648
A116: Gran Superficie | B116: =+'TablasInformes (1)'!B628 -> 16467075 | C116: =+'TablasInformes (1)'!C628 -> 19106984 | D116: =+'TablasInformes (1)'!D628 -> 25559708 | E116: =+'TablasInformes (1)'!E628 -> 30538352 | F116: =+'TablasInformes (1)'!F628 -> 33475790 | G116: =+'TablasInformes (1)'!G628 -> 33924140
A117: Hosteleria | B117: =+'TablasInformes (1)'!B629 -> 5100500 | C117: =+'TablasInformes (1)'!C629 -> 5545521 | D117: =+'TablasInformes (1)'!D629 -> 7114573 | E117: =+'TablasInformes (1)'!E629 -> 8213782 | F117: =+'TablasInformes (1)'!F629 -> 8972924 | G117: =+'TablasInformes (1)'!G629 -> 9203981
A129: 45
A130: Total ventas (unidades) por mercado.
B131: =+'TablasInformes (1)'!B633 -> 2023 | C131: =+'TablasInformes (1)'!C633 -> 2024 | D131: =+'TablasInformes (1)'!D633 -> 2025 | E131: =+'TablasInformes (1)'!E633 -> 2026 | F131: =+'TablasInformes (1)'!F633 -> 2027 | G131: =+'TablasInformes (1)'!G633 -> 2028
A132: Espana | B132: =+'TablasInformes (1)'!B635 -> 16590560 | C132: =+'TablasInformes (1)'!C635 -> 13054421 | D132: =+'TablasInformes (1)'!D635 -> 12860853 | E132: =+'TablasInformes (1)'!E635 -> 12034516 | F132: =+'TablasInformes (1)'!F635 -> 11214240 | G132: =+'TablasInformes (1)'!G635 -> 10747892
A133: Portugal | B133: =+'TablasInformes (1)'!B636 -> 3589160 | C133: =+'TablasInformes (1)'!C636 -> 2764815 | D133: =+'TablasInformes (1)'!D636 -> 2491974 | E133: =+'TablasInformes (1)'!E636 -> 2375358 | F133: =+'TablasInformes (1)'!F636 -> 2191326 | G133: =+'TablasInformes (1)'!G636 -> 2217306
A134: Francia | B134: =+'TablasInformes (1)'!B637 -> 13026020 | C134: =+'TablasInformes (1)'!C637 -> 9542213 | D134: =+'TablasInformes (1)'!D637 -> 8968522 | E134: =+'TablasInformes (1)'!E637 -> 8424715 | F134: =+'TablasInformes (1)'!F637 -> 7750497 | G134: =+'TablasInformes (1)'!G637 -> 7752181
A135: Italia | B135: =+'TablasInformes (1)'!B638 -> 0 | C135: =+'TablasInformes (1)'!C638 -> 11213184 | D135: =+'TablasInformes (1)'!D638 -> 17493522 | E135: =+'TablasInformes (1)'!E638 -> 21284244 | F135: =+'TablasInformes (1)'!F638 -> 22675292 | G135: =+'TablasInformes (1)'!G638 -> 20562648
A136: Centro Europa | B136: =+'TablasInformes (1)'!B639 -> 0 | C136: =+'TablasInformes (1)'!C639 -> 0 | D136: =+'TablasInformes (1)'!D639 -> 0 | E136: =+'TablasInformes (1)'!E639 -> 0 | F136: =+'TablasInformes (1)'!F639 -> 1608734 | G136: =+'TablasInformes (1)'!G639 -> 2374397
A137: Polonia | B137: =+'TablasInformes (1)'!B640 -> 0 | C137: =+'TablasInformes (1)'!C640 -> 0 | D137: =+'TablasInformes (1)'!D640 -> 0 | E137: =+'TablasInformes (1)'!E640 -> 3555289 | F137: =+'TablasInformes (1)'!F640 -> 5402704 | G137: =+'TablasInformes (1)'!G640 -> 7308045
A138: Mexico | B138: =+'TablasInformes (1)'!B641 -> 0 | C138: =+'TablasInformes (1)'!C641 -> 0 | D138: =+'TablasInformes (1)'!D641 -> 5712319 | E138: =+'TablasInformes (1)'!E641 -> 8436247 | F138: =+'TablasInformes (1)'!F641 -> 10664973 | G138: =+'TablasInformes (1)'!G641 -> 11854299
A139: Total Unidades Vendidas | B139: =+'TablasInformes (1)'!B642 -> 33205740 | C139: =+'TablasInformes (1)'!C642 -> 36574632 | D139: =+'TablasInformes (1)'!D642 -> 47527192 | E139: =+'TablasInformes (1)'!E642 -> 56110368 | F139: =+'TablasInformes (1)'!F642 -> 61507768 | G139: =+'TablasInformes (1)'!G642 -> 62816768
A140: Variacion - | B140: =+'TablasInformes (1)'!B643 -> 0.047 | C140: =+'TablasInformes (1)'!C643 -> 0.102 | D140: =+'TablasInformes (1)'!D643 -> 0.3 | E140: =+'TablasInformes (1)'!E643 -> 0.181 | F140: =+'TablasInformes (1)'!F643 -> 0.096 | G140: =+'TablasInformes (1)'!G643 -> 0.021
A180: 46
A181: % cuota en unidades de los segmentos
A182: en cada uno de los mercados.
B183: Jovenes | C183: Adultos | D183: Deportistas
A184: Espana | B184: =+'TablasInformes (1)'!B649 -> 544 | C184: =+'TablasInformes (1)'!C649 -> 271 | D184: =+'TablasInformes (1)'!D649 -> 185
A185: Portugal | B185: =+'TablasInformes (1)'!B650 -> 579 | C185: =+'TablasInformes (1)'!C650 -> 278 | D185: =+'TablasInformes (1)'!D650 -> 143
A186: Francia | B186: =+'TablasInformes (1)'!B651 -> 558 | C186: =+'TablasInformes (1)'!C651 -> 235 | D186: =+'TablasInformes (1)'!D651 -> 207
A187: Italia | B187: =+'TablasInformes (1)'!B652 -> 214 | C187: =+'TablasInformes (1)'!C652 -> 587 | D187: =+'TablasInformes (1)'!D652 -> 199
A188: Centro Europa | B188: =+'TablasInformes (1)'!B653 -> 178 | C188: =+'TablasInformes (1)'!C653 -> 663 | D188: =+'TablasInformes (1)'!D653 -> 160
A189: Polonia | B189: =+'TablasInformes (1)'!B654 -> 159 | C189: =+'TablasInformes (1)'!C654 -> 692 | D189: =+'TablasInformes (1)'!D654 -> 149
A190: Mexico | B190: =+'TablasInformes (1)'!B655 -> 137 | C190: =+'TablasInformes (1)'!C655 -> 738 | D190: =+'TablasInformes (1)'!D655 -> 126
A198: 47
A199: Unidades totales vendidas por mercado y producto.
A200: Total companias. Unidades.
B201: Refrescos | C201: Isotonicas | D201: Zumos
A202: Espana | B202: =+'TablasInformes (1)'!B661 -> 7249513 | C202: =+'TablasInformes (1)'!C661 -> 1895281 | D202: =+'TablasInformes (1)'!D661 -> 1603098
A203: Portugal | B203: =+'TablasInformes (1)'!B662 -> 1665580 | C203: =+'TablasInformes (1)'!C662 -> 206014 | D203: =+'TablasInformes (1)'!D662 -> 345712
A204: Francia | B204: =+'TablasInformes (1)'!B663 -> 5497313 | C204: =+'TablasInformes (1)'!C663 -> 1545216 | D204: =+'TablasInformes (1)'!D663 -> 709652
A205: Italia | B205: =+'TablasInformes (1)'!B664 -> 11241436 | C205: =+'TablasInformes (1)'!C664 -> 5624942 | D205: =+'TablasInformes (1)'!D664 -> 3696271
A206: Centro Europa | B206: =+'TablasInformes (1)'!B665 -> 1718926 | C206: =+'TablasInformes (1)'!C665 -> 439817 | D206: =+'TablasInformes (1)'!D665 -> 215654
A207: Polonia | B207: =+'TablasInformes (1)'!B666 -> 4499582 | C207: =+'TablasInformes (1)'!C666 -> 1709246 | D207: =+'TablasInformes (1)'!D666 -> 1099217
A208: Mexico | B208: =+'TablasInformes (1)'!B667 -> 6445053 | C208: =+'TablasInformes (1)'!C667 -> 2712864 | D208: =+'TablasInformes (1)'!D667 -> 2696382
A209: Total Unidades Vendidas | B209: =+'TablasInformes (1)'!B668 -> 38317404 | C209: =+'TablasInformes (1)'!C668 -> 14133380 | D209: =+'TablasInformes (1)'!D668 -> 10365986

Sheet 48 - 54
A1: 48
A2: Analisis Demanda-Ventas.Unidades. Mercado: Espana
C3: Refrescos | D3: Isotonicas | E3: Zumos
A4: Demanda Potencial | B4: Jovenes | C4: =+'TablasInformes (1)'!C673 -> 12378027 | D4: =+'TablasInformes (1)'!D673 -> 11002691 | E4: =+'TablasInformes (1)'!E673 -> 4456090
B5: Adultos | C5: =+'TablasInformes (1)'!C674 -> 38990784 | D5: =+'TablasInformes (1)'!D674 -> 25672946 | E5: =+'TablasInformes (1)'!E674 -> 16586556
B6: Deportistas | C6: =+'TablasInformes (1)'!C675 -> 11759126 | D6: =+'TablasInformes (1)'!D675 -> 9168909 | E6: =+'TablasInformes (1)'!E675 -> 3713408
A7: Demanda Efectiva | B7: Jovenes | C7: =+'TablasInformes (1)'!C676 -> 12363942 | D7: =+'TablasInformes (1)'!D676 -> 2025018 | E7: =+'TablasInformes (1)'!E676 -> 2472291
B8: Adultos | C8: =+'TablasInformes (1)'!C677 -> 4381155 | D8: =+'TablasInformes (1)'!D677 -> 1645289 | E8: =+'TablasInformes (1)'!E677 -> 3280633
B9: Deportistas | C9: =+'TablasInformes (1)'!C678 -> 1835358 | D9: =+'TablasInformes (1)'!D678 -> 4533172 | E9: =+'TablasInformes (1)'!E678 -> 511396
A10: Ventas Total Companias | B10: Jovenes | C10: =+'TablasInformes (1)'!C679 -> 4754383 | D10: =+'TablasInformes (1)'!D679 -> 467561 | E10: =+'TablasInformes (1)'!E679 -> 627341
B11: Adultos | C11: =+'TablasInformes (1)'!C680 -> 1711465 | D11: =+'TablasInformes (1)'!D680 -> 366737 | E11: =+'TablasInformes (1)'!E680 -> 834172
B12: Deportistas | C12: =+'TablasInformes (1)'!C681 -> 783665 | D12: =+'TablasInformes (1)'!D681 -> 1060983 | E12: =+'TablasInformes (1)'!E681 -> 141585
A13: Penetracion Ventas/Demanda | B13: Jovenes | C13: =+'TablasInformes (1)'!C682 -> 38 | D13: =+'TablasInformes (1)'!D682 -> 23 | E13: =+'TablasInformes (1)'!E682 -> 25
B14: Adultos | C14: =+'TablasInformes (1)'!C683 -> 39 | D14: =+'TablasInformes (1)'!D683 -> 22 | E14: =+'TablasInformes (1)'!E683 -> 25
B15: Deportistas | C15: =+'TablasInformes (1)'!C684 -> 43 | D15: =+'TablasInformes (1)'!D684 -> 23 | E15: =+'TablasInformes (1)'!E684 -> 28
A35: 49
A36: Analisis Demanda-Ventas.Unidades. Mercado: Portugal
C37: Refrescos | D37: Isotonicas | E37: Zumos
A38: Demanda Potencial | B38: Jovenes | C38: =+'TablasInformes (1)'!C689 -> 1469758 | D38: =+'TablasInformes (1)'!D689 -> 979838 | E38: =+'TablasInformes (1)'!E689 -> 480139
B39: Adultos | C39: =+'TablasInformes (1)'!C690 -> 5414896 | D39: =+'TablasInformes (1)'!D690 -> 3352079 | E39: =+'TablasInformes (1)'!E690 -> 2336675
B40: Deportistas | C40: =+'TablasInformes (1)'!C691 -> 1315046 | D40: =+'TablasInformes (1)'!D691 -> 825127 | E40: =+'TablasInformes (1)'!E691 -> 448129
A41: Demanda Efectiva | B41: Jovenes | C41: =+'TablasInformes (1)'!C692 -> 3111287 | D41: =+'TablasInformes (1)'!D692 -> 166693 | E41: =+'TablasInformes (1)'!E692 -> 396635
B42: Adultos | C42: =+'TablasInformes (1)'!C693 -> 1052753 | D42: =+'TablasInformes (1)'!D693 -> 208284 | E42: =+'TablasInformes (1)'!E693 -> 622125
B43: Deportistas | C43: =+'TablasInformes (1)'!C694 -> 317631 | D43: =+'TablasInformes (1)'!D694 -> 548181 | E43: =+'TablasInformes (1)'!E694 -> 261508
A44: Ventas Total Companias | B44: Jovenes | C44: =+'TablasInformes (1)'!C695 -> 1145959 | D44: =+'TablasInformes (1)'!D695 -> 36691 | E44: =+'TablasInformes (1)'!E695 -> 101434
B45: Adultos | C45: =+'TablasInformes (1)'!C696 -> 400405 | D45: =+'TablasInformes (1)'!D696 -> 46960 | E45: =+'TablasInformes (1)'!E696 -> 169578
B46: Deportistas | C46: =+'TablasInformes (1)'!C697 -> 119216 | D46: =+'TablasInformes (1)'!D697 -> 122363 | E46: =+'TablasInformes (1)'!E697 -> 74700
A47: Penetracion Ventas/Demanda | B47: Jovenes | C47: =+'TablasInformes (1)'!C698 -> 37 | D47: =+'TablasInformes (1)'!D698 -> 22 | E47: =+'TablasInformes (1)'!E698 -> 26
B48: Adultos | C48: =+'TablasInformes (1)'!C699 -> 38 | D48: =+'TablasInformes (1)'!D699 -> 23 | E48: =+'TablasInformes (1)'!E699 -> 27
B49: Deportistas | C49: =+'TablasInformes (1)'!C700 -> 38 | D49: =+'TablasInformes (1)'!D700 -> 22 | E49: =+'TablasInformes (1)'!E700 -> 29
A67: 50
A68: Analisis Demanda-Ventas.Unidades. Mercado: Francia
C69: Refrescos | D69: Isotonicas | E69: Zumos
A70: Demanda Potencial | B70: Jovenes | C70: =+'TablasInformes (1)'!C705 -> 15444485 | D70: =+'TablasInformes (1)'!D705 -> 16216709 | E70: =+'TablasInformes (1)'!E705 -> 6081266
B71: Adultos | C71: =+'TablasInformes (1)'!C706 -> 48650128 | D71: =+'TablasInformes (1)'!D706 -> 37838988 | E71: =+'TablasInformes (1)'!E706 -> 22635824
B72: Deportistas | C72: =+'TablasInformes (1)'!C707 -> 14672261 | D72: =+'TablasInformes (1)'!D707 -> 13513924 | E72: =+'TablasInformes (1)'!E707 -> 5067722
A73: Demanda Efectiva | B73: Jovenes | C73: =+'TablasInformes (1)'!C708 -> 9880303 | D73: =+'TablasInformes (1)'!D708 -> 1799430 | E73: =+'TablasInformes (1)'!E708 -> 775973
B74: Adultos | C74: =+'TablasInformes (1)'!C709 -> 3257186 | D74: =+'TablasInformes (1)'!D709 -> 997061 | E74: =+'TablasInformes (1)'!E709 -> 1019767
B75: Deportistas | C75: =+'TablasInformes (1)'!C710 -> 1243250 | D75: =+'TablasInformes (1)'!D710 -> 3835623 | E75: =+'TablasInformes (1)'!E710 -> 638632
A76: Ventas Total Companias | B76: Jovenes | C76: =+'TablasInformes (1)'!C711 -> 3694566 | D76: =+'TablasInformes (1)'!D711 -> 416369 | E76: =+'TablasInformes (1)'!E711 -> 216599
B77: Adultos | C77: =+'TablasInformes (1)'!C712 -> 1291251 | D77: =+'TablasInformes (1)'!D712 -> 229099 | E77: =+'TablasInformes (1)'!E712 -> 297221
B78: Deportistas | C78: =+'TablasInformes (1)'!C713 -> 511496 | D78: =+'TablasInformes (1)'!D713 -> 899748 | E78: =+'TablasInformes (1)'!E713 -> 195832
A79: Penetracion Ventas/Demanda | B79: Jovenes | C79: =+'TablasInformes (1)'!C714 -> 37 | D79: =+'TablasInformes (1)'!D714 -> 23 | E79: =+'TablasInformes (1)'!E714 -> 28
B80: Adultos | C80: =+'TablasInformes (1)'!C715 -> 40 | D80: =+'TablasInformes (1)'!D715 -> 23 | E80: =+'TablasInformes (1)'!E715 -> 29
B81: Deportistas | C81: =+'TablasInformes (1)'!C716 -> 41 | D81: =+'TablasInformes (1)'!D716 -> 23 | E81: =+'TablasInformes (1)'!E716 -> 31
A99: 51
A100: Analisis Demanda-Ventas.Unidades. Mercado: Italia
C101: Refrescos | D101: Isotonicas | E101: Zumos
A102: Demanda Potencial | B102: Jovenes | C102: =+'TablasInformes (1)'!C721 -> 13409072 | D102: =+'TablasInformes (1)'!D721 -> 11919175 | E102: =+'TablasInformes (1)'!E721 -> 4827266
B103: Adultos | C103: =+'TablasInformes (1)'!C722 -> 42238576 | D103: =+'TablasInformes (1)'!D722 -> 27811408 | E103: =+'TablasInformes (1)'!E722 -> 17968156
B104: Deportistas | C104: =+'TablasInformes (1)'!C723 -> 12738618 | D104: =+'TablasInformes (1)'!D723 -> 9932646 | E104: =+'TablasInformes (1)'!E723 -> 4022722
A105: Demanda Efectiva | B105: Jovenes | C105: =+'TablasInformes (1)'!C724 -> 7059949 | D105: =+'TablasInformes (1)'!D724 -> 6333084 | E105: =+'TablasInformes (1)'!E724 -> 2983378
B106: Adultos | C106: =+'TablasInformes (1)'!C725 -> 20104746 | D106: =+'TablasInformes (1)'!D725 -> 13486283 | E106: =+'TablasInformes (1)'!E725 -> 9714395
B107: Deportistas | C107: =+'TablasInformes (1)'!C726 -> 6467437 | D107: =+'TablasInformes (1)'!D726 -> 5042836 | E107: =+'TablasInformes (1)'!E726 -> 2356809
A108: Ventas Total Companias | B108: Jovenes | C108: =+'TablasInformes (1)'!C727 -> 2289030 | D108: =+'TablasInformes (1)'!D727 -> 1419229 | E108: =+'TablasInformes (1)'!E727 -> 697730
B109: Adultos | C109: =+'TablasInformes (1)'!C728 -> 6690382 | D109: =+'TablasInformes (1)'!D728 -> 3029522 | E109: =+'TablasInformes (1)'!E728 -> 2349422
B110: Deportistas | C110: =+'TablasInformes (1)'!C729 -> 2262024 | D110: =+'TablasInformes (1)'!D729 -> 1176191 | E110: =+'TablasInformes (1)'!E729 -> 649119
A111: Penetracion Ventas/Demanda | B111: Jovenes | C111: =+'TablasInformes (1)'!C730 -> 32 | D111: =+'TablasInformes (1)'!D730 -> 22 | E111: =+'TablasInformes (1)'!E730 -> 23
B112: Adultos | C112: =+'TablasInformes (1)'!C731 -> 33 | D112: =+'TablasInformes (1)'!D731 -> 22 | E112: =+'TablasInformes (1)'!E731 -> 24
B113: Deportistas | C113: =+'TablasInformes (1)'!C732 -> 35 | D113: =+'TablasInformes (1)'!D732 -> 23 | E113: =+'TablasInformes (1)'!E732 -> 28
A132: 52
A133: Analisis Demanda-Ventas.Unidades. Mercado: Centro Europa
C134: Refrescos | D134: Isotonicas | E134: Zumos
A135: Demanda Potencial | B135: Jovenes | C135: =+'TablasInformes (1)'!C737 -> 2616870 | D135: =+'TablasInformes (1)'!D737 -> 1665281 | E135: =+'TablasInformes (1)'!E737 -> 774731
B136: Adultos | C136: =+'TablasInformes (1)'!C738 -> 9641098 | D136: =+'TablasInformes (1)'!D738 -> 5697013 | E136: =+'TablasInformes (1)'!E738 -> 3770358
B137: Deportistas | C137: =+'TablasInformes (1)'!C739 -> 2341410 | D137: =+'TablasInformes (1)'!D739 -> 1402342 | E137: =+'TablasInformes (1)'!E739 -> 723082
A138: Demanda Efectiva | B138: Jovenes | C138: =+'TablasInformes (1)'!C740 -> 1232737 | D138: =+'TablasInformes (1)'!D740 -> 791666 | E138: =+'TablasInformes (1)'!E740 -> 450052
B139: Adultos | C139: =+'TablasInformes (1)'!C741 -> 4292279 | D139: =+'TablasInformes (1)'!D741 -> 2536347 | E139: =+'TablasInformes (1)'!E741 -> 2019870
B140: Deportistas | C140: =+'TablasInformes (1)'!C742 -> 1102975 | D140: =+'TablasInformes (1)'!D742 -> 660605 | E140: =+'TablasInformes (1)'!E742 -> 408963
A141: Ventas Total Companias | B141: Jovenes | C141: =+'TablasInformes (1)'!C743 -> 305465 | D141: =+'TablasInformes (1)'!D743 -> 84682 | E141: =+'TablasInformes (1)'!E743 -> 31456
B142: Adultos | C142: =+'TablasInformes (1)'!C744 -> 1134625 | D142: =+'TablasInformes (1)'!D744 -> 284889 | E142: =+'TablasInformes (1)'!E744 -> 153467
B143: Deportistas | C143: =+'TablasInformes (1)'!C745 -> 278836 | D143: =+'TablasInformes (1)'!D745 -> 70246 | E143: =+'TablasInformes (1)'!E745 -> 30731
A144: Penetracion Ventas/Demanda | B144: Jovenes | C144: =+'TablasInformes (1)'!C746 -> 34 | D144: =+'TablasInformes (1)'!D746 -> 18 | E144: =+'TablasInformes (1)'!E746 -> 21
B145: Adultos | C145: =+'TablasInformes (1)'!C747 -> 37 | D145: =+'TablasInformes (1)'!D747 -> 19 | E145: =+'TablasInformes (1)'!E747 -> 22
B146: Deportistas | C146: =+'TablasInformes (1)'!C748 -> 35 | D146: =+'TablasInformes (1)'!D748 -> 18 | E146: =+'TablasInformes (1)'!E748 -> 22
A167: 53
A168: Analisis Demanda-Ventas.Unidades. Mercado: Polonia
C169: Refrescos | D169: Isotonicas | E169: Zumos
A170: Demanda Potencial | B170: Jovenes | C170: =+'TablasInformes (1)'!C753 -> 3624562 | D170: =+'TablasInformes (1)'!D753 -> 2230500 | E170: =+'TablasInformes (1)'!E753 -> 1268597
B171: Adultos | C171: =+'TablasInformes (1)'!C754 -> 15907798 | D171: =+'TablasInformes (1)'!D754 -> 10594872 | E171: =+'TablasInformes (1)'!E754 -> 7067895
B172: Deportistas | C172: =+'TablasInformes (1)'!C755 -> 3020468 | D172: =+'TablasInformes (1)'!D755 -> 2230500 | E172: =+'TablasInformes (1)'!E755 -> 1268597
A173: Demanda Efectiva | B173: Jovenes | C173: =+'TablasInformes (1)'!C756 -> 2181983 | D173: =+'TablasInformes (1)'!D756 -> 1366737 | E173: =+'TablasInformes (1)'!E756 -> 791213
B174: Adultos | C174: =+'TablasInformes (1)'!C757 -> 9000091 | D174: =+'TablasInformes (1)'!D757 -> 6048220 | E174: =+'TablasInformes (1)'!E757 -> 3998775
B175: Deportistas | C175: =+'TablasInformes (1)'!C758 -> 1802228 | D175: =+'TablasInformes (1)'!D758 -> 1342759 | E175: =+'TablasInformes (1)'!E758 -> 763694
A176: Ventas Total Companias | B176: Jovenes | C176: =+'TablasInformes (1)'!C759 -> 741224 | D176: =+'TablasInformes (1)'!D759 -> 267927 | E176: =+'TablasInformes (1)'!E759 -> 151886
B177: Adultos | C177: =+'TablasInformes (1)'!C760 -> 3095508 | D177: =+'TablasInformes (1)'!D760 -> 1174832 | E177: =+'TablasInformes (1)'!E760 -> 786831
B178: Deportistas | C178: =+'TablasInformes (1)'!C761 -> 662850 | D178: =+'TablasInformes (1)'!D761 -> 266487 | E178: =+'TablasInformes (1)'!E761 -> 160500
A179: Penetracion Ventas/Demanda | B179: Jovenes | C179: =+'TablasInformes (1)'!C762 -> 38 | D179: =+'TablasInformes (1)'!D762 -> 23 | E179: =+'TablasInformes (1)'!E762 -> 28
B180: Adultos | C180: =+'TablasInformes (1)'!C763 -> 38 | D180: =+'TablasInformes (1)'!D763 -> 23 | E180: =+'TablasInformes (1)'!E763 -> 29
B181: Deportistas | C181: =+'TablasInformes (1)'!C764 -> 41 | D181: =+'TablasInformes (1)'!D764 -> 23 | E181: =+'TablasInformes (1)'!E764 -> 31
A201: 54
A202: Analisis Demanda-Ventas.Unidades. Mercado: Mexico
C203: Refrescos | D203: Isotonicas | E203: Zumos
A204: Demanda Potencial | B204: Jovenes | C204: =+'TablasInformes (1)'!C768 -> 5658070 | D204: =+'TablasInformes (1)'!D768 -> 3371267 | E204: =+'TablasInformes (1)'!E768 -> 2370422
B205: Adultos | C205: =+'TablasInformes (1)'!C769 -> 30058494 | D205: =+'TablasInformes (1)'!D769 -> 21783568 | E205: =+'TablasInformes (1)'!E769 -> 15134231
B206: Deportistas | C206: =+'TablasInformes (1)'!C770 -> 4243552 | D206: =+'TablasInformes (1)'!D770 -> 3371267 | E206: =+'TablasInformes (1)'!E770 -> 2370422
A207: Demanda Efectiva | B207: Jovenes | C207: =+'TablasInformes (1)'!C771 -> 3060995 | D207: =+'TablasInformes (1)'!D771 -> 1743152 | E207: =+'TablasInformes (1)'!E771 -> 1530626
B208: Adultos | C208: =+'TablasInformes (1)'!C772 -> 14703449 | D208: =+'TablasInformes (1)'!D772 -> 10273433 | E208: =+'TablasInformes (1)'!E772 -> 8483300
B209: Deportistas | C209: =+'TablasInformes (1)'!C773 -> 2213579 | D209: =+'TablasInformes (1)'!D773 -> 1696043 | E209: =+'TablasInformes (1)'!E773 -> 1439066
A210: Ventas Total Companias | B210: Jovenes | C210: =+'TablasInformes (1)'!C774 -> 952820 | D210: =+'TablasInformes (1)'!D774 -> 337665 | E210: =+'TablasInformes (1)'!E774 -> 332814
...

Sheet 55 - 60
A1: 55
A2: Ventas por compania y mercado. Drink2Go
B3: =+'TablasInformes (1)'!B783 -> 2023 | C3: =+'TablasInformes (1)'!C783 -> 2023 | D3: =+'TablasInformes (1)'!D783 -> 2024 | E3: =+'TablasInformes (1)'!E783 -> 2024 | F3: =+'TablasInformes (1)'!F783 -> 2025 | G3: =+'TablasInformes (1)'!G783 -> 2025 | H3: =+'TablasInformes (1)'!H783 -> 2026 | I3: =+'TablasInformes (1)'!I783 -> 2026 | ... M3: =+'TablasInformes (1)'!M783 -> 2028
B4: Unidades | C4: - Variacion | D4: Unidades | E4: - Variacion | F4: Unidades | G4: - Variacion | H4: Unidades | I4: - Variacion | J4: Unidades | K4: - Variacion | L4: Unidades | M4: - Variacion
A5: Espana | B5: =+'TablasInformes (1)'!B785 -> 3318112 | C5: =+'TablasInformes (1)'!C785 -> 0.062 | D5: =+'TablasInformes (1)'!D785 -> 2500758 | E5: =+'TablasInformes (1)'!E785 -> -0.246 | F5: =+'TablasInformes (1)'!F785 -> 2464238 | G5: =+'TablasInformes (1)'!G785 -> -0.015 | H5: =+'TablasInformes (1)'!H785 -> 2152115 | I5: =+'TablasInformes (1)'!I785 -> -0.127 | ... M5: =+'TablasInformes (1)'!M785 -> -0.118
A6: Portugal | B6: =+'TablasInformes (1)'!B786 -> 717828 | C6: =+'TablasInformes (1)'!C786 -> 0.011 | D6: =+'TablasInformes (1)'!D786 -> 512375 | E6: =+'TablasInformes (1)'!E786 -> -0.286 | F6: =+'TablasInformes (1)'!F786 -> 391470 | G6: =+'TablasInformes (1)'!G786 -> -0.236 | H6: =+'TablasInformes (1)'!H786 -> 355435 | I6: =+'TablasInformes (1)'!I786 -> -0.092 | ... M6: =+'TablasInformes (1)'!M786 -> 0.147
A7: Francia | B7: =+'TablasInformes (1)'!B787 -> 2605181 | C7: =+'TablasInformes (1)'!C787 -> 0.016 | D7: =+'TablasInformes (1)'!D787 -> 1732288 | E7: =+'TablasInformes (1)'!E787 -> -0.335 | F7: =+'TablasInformes (1)'!F787 -> 1452455 | G7: =+'TablasInformes (1)'!G787 -> -0.162 | H7: =+'TablasInformes (1)'!H787 -> 1222403 | I7: =+'TablasInformes (1)'!I787 -> -0.158 | ... M7: =+'TablasInformes (1)'!M787 -> 0.108
A8: Italia | B8: =+'TablasInformes (1)'!B788 -> 0 | C8: =+'TablasInformes (1)'!C788 -> 0 | D8: =+'TablasInformes (1)'!D788 -> 2095624 | E8: =+'TablasInformes (1)'!E788 -> 0 | F8: =+'TablasInformes (1)'!F788 -> 2619066 | G8: =+'TablasInformes (1)'!G788 -> 0.025 | H8: =+'TablasInformes (1)'!H788 -> 2673406 | I8: =+'TablasInformes (1)'!I788 -> -0.021 | ... M8: =+'TablasInformes (1)'!M788 -> -0.098
A9: Centro Europa | B9: =+'TablasInformes (1)'!B789 -> 0 | C9: =+'TablasInformes (1)'!C789 -> 0 | D9: =+'TablasInformes (1)'!D789 -> 0 | E9: =+'TablasInformes (1)'!E789 -> 0 | F9: =+'TablasInformes (1)'!F789 -> 0 | G9: =+'TablasInformes (1)'!G789 -> 0 | H9: =+'TablasInformes (1)'!H789 -> 0 | I9: =+'TablasInformes (1)'!I789 -> 0 | ... M9: =+'TablasInformes (1)'!M789 -> 0.795
A10: Polonia | B10: =+'TablasInformes (1)'!B790 -> 0 | C10: =+'TablasInformes (1)'!C790 -> 0 | D10: =+'TablasInformes (1)'!D790 -> 0 | E10: =+'TablasInformes (1)'!E790 -> 0 | F10: =+'TablasInformes (1)'!F790 -> 0 | G10: =+'TablasInformes (1)'!G790 -> 0 | H10: =+'TablasInformes (1)'!H790 -> 718484 | I10: =+'TablasInformes (1)'!I790 -> 0 | ... M10: =+'TablasInformes (1)'!M790 -> 0.428
A11: Mexico | B11: =+'TablasInformes (1)'!B791 -> 0 | C11: =+'TablasInformes (1)'!C791 -> 0 | D11: =+'TablasInformes (1)'!D791 -> 0 | E11: =+'TablasInformes (1)'!E791 -> 0 | F11: =+'TablasInformes (1)'!F791 -> 1151336 | G11: =+'TablasInformes (1)'!G791 -> 0 | H11: =+'TablasInformes (1)'!H791 -> 1564357 | I11: =+'TablasInformes (1)'!I791 -> 0.359 | ... M11: =+'TablasInformes (1)'!M791 -> 0.006
A12: Total unidades vendidas | B12: =+'TablasInformes (1)'!B792 -> 6641121 | C12: =+'TablasInformes (1)'!C792 -> 0.038 | D12: =+'TablasInformes (1)'!D792 -> 6841045 | E12: =+'TablasInformes (1)'!E792 -> 0.003 | F12: =+'TablasInformes (1)'!F792 -> 8078565 | G12: =+'TablasInformes (1)'!G792 -> 0.181 | H12: =+'TablasInformes (1)'!H792 -> 8686200 | I12: =+'TablasInformes (1)'!I792 -> 0.075 | ... M12: =+'TablasInformes (1)'!M792 -> 0.004
A36: 56
A37: Ventas por mercado y producto. Drink2Go
B38: =+'TablasInformes (1)'!B796 -> 2027 | C38: =+'TablasInformes (1)'!C796 -> 2027 | D38: =+'TablasInformes (1)'!D796 -> 2027 | E38: =+'TablasInformes (1)'!E796 -> 2028 | F38: =+'TablasInformes (1)'!F796 -> 2028 | G38: =+'TablasInformes (1)'!G796 -> 2028
B39: Refrescos | C39: Isotonicas | D39: Zumos | E39: Refrescos | F39: Isotonicas | G39: Zumos
A40: Espana | B40: =+'TablasInformes (1)'!B798 -> 1363773 | C40: =+'TablasInformes (1)'!C798 -> 346899 | D40: =+'TablasInformes (1)'!D798 -> 409136 | E40: =+'TablasInformes (1)'!E798 -> 1114287 | F40: =+'TablasInformes (1)'!F798 -> 390292 | G40: =+'TablasInformes (1)'!G798 -> 364240
A41: Portugal | B41: =+'TablasInformes (1)'!B799 -> 244641 | C41: =+'TablasInformes (1)'!C799 -> 34504 | D41: =+'TablasInformes (1)'!D799 -> 105458 | E41: =+'TablasInformes (1)'!E799 -> 297430 | F41: =+'TablasInformes (1)'!F799 -> 40773 | G41: =+'TablasInformes (1)'!G799 -> 102921
A42: Francia | B42: =+'TablasInformes (1)'!B800 -> 698854 | C42: =+'TablasInformes (1)'!C800 -> 316979 | D42: =+'TablasInformes (1)'!D800 -> 204176 | E42: =+'TablasInformes (1)'!E800 -> 783718 | F42: =+'TablasInformes (1)'!F800 -> 347769 | G42: =+'TablasInformes (1)'!G800 -> 202367
A43: Italia | B43: =+'TablasInformes (1)'!B801 -> 1802447 | C43: =+'TablasInformes (1)'!C801 -> 751264 | D43: =+'TablasInformes (1)'!D801 -> 667571 | E43: =+'TablasInformes (1)'!E801 -> 1786991 | F43: =+'TablasInformes (1)'!F801 -> 661276 | G43: =+'TablasInformes (1)'!G801 -> 457068
A44: Centro Europa | B44: =+'TablasInformes (1)'!B802 -> 235194 | C44: =+'TablasInformes (1)'!C802 -> 57012 | D44: =+'TablasInformes (1)'!D802 -> 13922 | E44: =+'TablasInformes (1)'!E802 -> 419602 | F44: =+'TablasInformes (1)'!F802 -> 97257 | G44: =+'TablasInformes (1)'!G802 -> 32730
A45: Polonia | B45: =+'TablasInformes (1)'!B803 -> 531249 | C45: =+'TablasInformes (1)'!C803 -> 325054 | D45: =+'TablasInformes (1)'!D803 -> 151267 | E45: =+'TablasInformes (1)'!E803 -> 657555 | F45: =+'TablasInformes (1)'!F803 -> 477260 | G45: =+'TablasInformes (1)'!G803 -> 303816
A46: Mexico | B46: =+'TablasInformes (1)'!B804 -> 1153797 | C46: =+'TablasInformes (1)'!C804 -> 561558 | D46: =+'TablasInformes (1)'!D804 -> 172327 | E46: =+'TablasInformes (1)'!E804 -> 1324123 | F46: =+'TablasInformes (1)'!F804 -> 417375 | G46: =+'TablasInformes (1)'!G804 -> 258784
A47: Total unidades vendidas | B47: =+'TablasInformes (1)'!B805 -> 6029955 | C47: =+'TablasInformes (1)'!C805 -> 2393270 | D47: =+'TablasInformes (1)'!D805 -> 1723857 | E47: =+'TablasInformes (1)'!E805 -> 6383706 | F47: =+'TablasInformes (1)'!F805 -> 2432002 | G47: =+'TablasInformes (1)'!G805 -> 1721926
A48: - Variacion | B48: =+'TablasInformes (1)'!B806 -> 0.115 | C48: =+'TablasInformes (1)'!C806 -> 0.256 | D48: =+'TablasInformes (1)'!D806 -> 0.256 | E48: =+'TablasInformes (1)'!E806 -> 0.059 | F48: =+'TablasInformes (1)'!F806 -> 0.016 | G48: =+'TablasInformes (1)'!G806 -> -0.001
A73: 57
A74: Unidades vendidas por canal. Drink2Go
B75: =+'TablasInformes (1)'!B810 -> 2023 | C75: =+'TablasInformes (1)'!C810 -> 2023 | D75: =+'TablasInformes (1)'!D810 -> 2024 | E75: =+'TablasInformes (1)'!E810 -> 2024 | F75: =+'TablasInformes (1)'!F810 -> 2025 | G75: =+'TablasInformes (1)'!G810 -> 2025 | H75: =+'TablasInformes (1)'!H810 -> 2026 | I75: =+'TablasInformes (1)'!I810 -> 2026 | ... M75: =+'TablasInformes (1)'!M810 -> 2028
B76: Unidades | C76: % Variacion | D76: Unidades | E76: % Variacion | F76: Unidades | G76: % Variacion | H76: Unidades | I76: % Variacion | J76: Unidades | K76: % Variacion | L76: Unidades | M76: % Variacion
A77: Tienda Tradicional | B77: =+'TablasInformes (1)'!B812 -> 2327633 | C77: =+'TablasInformes (1)'!C812 -> 0.005 | D77: =+'TablasInformes (1)'!D812 -> 2246961 | E77: =+'TablasInformes (1)'!E812 -> -0.035 | F77: =+'TablasInformes (1)'!F812 -> 2545594 | G77: =+'TablasInformes (1)'!G812 -> 0.133 | H77: =+'TablasInformes (1)'!H812 -> 2792165 | I77: =+'TablasInformes (1)'!I812 -> 0.097 | ... M77: =+'TablasInformes (1)'!M812 -> 0.093
A78: Gran Superficie | B78: =+'TablasInformes (1)'!B813 -> 3293415 | C78: =+'TablasInformes (1)'!C813 -> 0.045 | D78: =+'TablasInformes (1)'!D813 -> 3603492 | E78: =+'TablasInformes (1)'!E813 -> 0.094 | F78: =+'TablasInformes (1)'!F813 -> 4373715 | G78: =+'TablasInformes (1)'!G813 -> 0.214 | H78: =+'TablasInformes (1)'!H813 -> 4736625 | I78: =+'TablasInformes (1)'!I813 -> 0.083 | ... M78: =+'TablasInformes (1)'!M813 -> -0.002
A79: Hosteleria | B79: =+'TablasInformes (1)'!B814 -> 1020100 | C79: =+'TablasInformes (1)'!C814 -> 0.047 | D79: =+'TablasInformes (1)'!D814 -> 990063 | E79: =+'TablasInformes (1)'!E814 -> -0.029 | F79: =+'TablasInformes (1)'!F814 -> 1159357 | G79: =+'TablasInformes (1)'!G814 -> 0.171 | H79: =+'TablasInformes (1)'!H814 -> 1157484 | I79: =+'TablasInformes (1)'!I814 -> -0.002 | ... M79: =+'TablasInformes (1)'!M814 -> 0.109
A80: Total ventas compania | B80: =+'TablasInformes (1)'!B815 -> 6641121 | C80: =+'TablasInformes (1)'!C815 -> 0.038 | D80: =+'TablasInformes (1)'!D815 -> 6841045 | E80: =+'TablasInformes (1)'!E815 -> 0.003 | F80: =+'TablasInformes (1)'!F815 -> 8078565 | G80: =+'TablasInformes (1)'!G815 -> 0.181 | H80: =+'TablasInformes (1)'!H815 -> 8686200 | I80: =+'TablasInformes (1)'!I815 -> 0.075 | ... M80: =+'TablasInformes (1)'!M815 -> 0.004
A105: 58
A106: Unidades vendidas por trimestre. Analisis por producto. Drink2Go
B107: =+'TablasInformes (1)'!B819 -> 2027 | C107: =+'TablasInformes (1)'!C819 -> 2027 | D107: =+'TablasInformes (1)'!D819 -> 2027 | E107: =+'TablasInformes (1)'!E819 -> 2027 | F107: =+'TablasInformes (1)'!F819 -> 2028 | G107: =+'TablasInformes (1)'!G819 -> 2028 | H107: =+'TablasInformes (1)'!H819 -> 2028 | I107: =+'TablasInformes (1)'!I819 -> 2028
B108: 1er Trim | C108: 2do Trim | D108: 3er Trim | E108: 4to Trim | F108: 1er Trim | G108: 2do Trim | H108: 3er Trim | I108: 4to Trim
A109: Refrescos | B109: =+'TablasInformes (1)'!B821 -> 1688351 | C109: =+'TablasInformes (1)'!C821 -> 1507460 | D109: =+'TablasInformes (1)'!D821 -> 1085374 | E109: =+'TablasInformes (1)'!E821 -> 1748655 | F109: =+'TablasInformes (1)'!F821 -> 1787446 | G109: =+'TablasInformes (1)'!G821 -> 1595929 | H109: =+'TablasInformes (1)'!H821 -> 1149070 | I109: =+'TablasInformes (1)'!I821 -> 1851280
A110: Isotonicas | B110: =+'TablasInformes (1)'!B822 -> 646168 | C110: =+'TablasInformes (1)'!C822 -> 287186 | D110: =+'TablasInformes (1)'!D822 -> 335050 | E110: =+'TablasInformes (1)'!E822 -> 1124817 | F110: =+'TablasInformes (1)'!F822 -> 661418 | G110: =+'TablasInformes (1)'!G822 -> 293961 | H110: =+'TablasInformes (1)'!H822 -> 342954 | I110: =+'TablasInformes (1)'!I822 -> 1151353
A111: Zumos | B111: =+'TablasInformes (1)'!B823 -> 448197 | C111: =+'TablasInformes (1)'!C823 -> 413715 | D111: =+'TablasInformes (1)'!D823 -> 396483 | E111: =+'TablasInformes (1)'!E823 -> 465442 | F111: =+'TablasInformes (1)'!F823 -> 447699 | G111: =+'TablasInformes (1)'!G823 -> 413259 | H111: =+'TablasInformes (1)'!H823 -> 396042 | I111: =+'TablasInformes (1)'!I823 -> 464920
A112: Total ventas | B112: =+'TablasInformes (1)'!B824 -> 2782716 | C112: =+'TablasInformes (1)'!C824 -> 2208361 | D112: =+'TablasInformes (1)'!D824 -> 1816907 | E112: =+'TablasInformes (1)'!E824 -> 3338914 | F112: =+'TablasInformes (1)'!F824 -> 2896563 | G112: =+'TablasInformes (1)'!G824 -> 2303149 | H112: =+'TablasInformes (1)'!H824 -> 1888066 | I112: =+'TablasInformes (1)'!I824 -> 3467553
A134: 59
A135: Unidades vendidas por compania. Drink2Go
B136: =+'TablasInformes (1)'!B828 -> 2023 | C136: =+'TablasInformes (1)'!C828 -> 2024 | D136: =+'TablasInformes (1)'!D828 -> 2025 | E136: =+'TablasInformes (1)'!E828 -> 2026 | F136: =+'TablasInformes (1)'!F828 -> 2027 | G136: =+'TablasInformes (1)'!G828 -> 2028
A137: Jovenes | B137: =+'TablasInformes (1)'!B830 -> 3404034 | C137: =+'TablasInformes (1)'!C830 -> 2787867 | D137: =+'TablasInformes (1)'!D830 -> 2585172 | E137: =+'TablasInformes (1)'!E830 -> 2446302 | F137: =+'TablasInformes (1)'!F830 -> 2804893 | G137: =+'TablasInformes (1)'!G830 -> 2770112
A138: Adultos | B138: =+'TablasInformes (1)'!B831 -> 1924382 | C138: =+'TablasInformes (1)'!C831 -> 2785542 | D138: =+'TablasInformes (1)'!D831 -> 3856766 | E138: =+'TablasInformes (1)'!E831 -> 4568349 | F138: =+'TablasInformes (1)'!F831 -> 5422284 | G138: =+'TablasInformes (1)'!G831 -> 5536867
A139: Deportistas | B139: =+'TablasInformes (1)'!B832 -> 1312732 | C139: =+'TablasInformes (1)'!C832 -> 1267107 | D139: =+'TablasInformes (1)'!D832 -> 1636728 | E139: =+'TablasInformes (1)'!E832 -> 1671623 | F139: =+'TablasInformes (1)'!F832 -> 1919905 | G139: =+'TablasInformes (1)'!G832 -> 2230655
A140: Total ventas compania | B140: =+'TablasInformes (1)'!B833 -> 6641121 | C140: =+'TablasInformes (1)'!C833 -> 6841045 | D140: =+'TablasInformes (1)'!D833 -> 8078565 | E140: =+'TablasInformes (1)'!E833 -> 8686200 | F140: =+'TablasInformes (1)'!F833 -> 10146898 | G140: =+'TablasInformes (1)'!G833 -> 10555331
A161: 60
A162: Unidades vendidas por segmento. Drink2Go
B163: =+'TablasInformes (1)'!B837 -> 2023 | C163: =+'TablasInformes (1)'!C837 -> 2023 | D163: =+'TablasInformes (1)'!D837 -> 2023 | E163: =+'TablasInformes (1)'!E837 -> 2024 | F163: =+'TablasInformes (1)'!F837 -> 2024 | G163: =+'TablasInformes (1)'!G837 -> 2024 | H163: =+'TablasInformes (1)'!H837 -> 2025 | I163: =+'TablasInformes (1)'!I837 -> 2025 | ... S163: =+'TablasInformes (1)'!S837 -> 2028
B164: Refrescos | C164: Isotonicas | D164: Zumos | E164: Refrescos | F164: Isotonicas | G164: Zumos | H164: Refrescos | I164: Isotonicas | J164: Zumos | K164: Refrescos | L164: Isotonicas | M164: Zumos | N164: Refrescos | O164: Isotonicas | P164: Zumos | Q164: Refrescos | R164: Isotonicas | S164: Zumos
A165: Jovenes | B165: =+'TablasInformes (1)'!B839 -> 2749049 | C165: =+'TablasInformes (1)'!C839 -> 333236 | D165: =+'TablasInformes (1)'!D839 -> 321749 | E165: =+'TablasInformes (1)'!E839 -> 2122148 | F165: =+'TablasInformes (1)'!F839 -> 319486 | G165: =+'TablasInformes (1)'!G839 -> 346233 | H165: =+'TablasInformes (1)'!H839 -> 1929791 | I165: =+'TablasInformes (1)'!I839 -> 330551 | ... S165: =+'TablasInformes (1)'!S839 -> 369732
A166: Adultos | B166: =+'TablasInformes (1)'!B840 -> 1125936 | C166: =+'TablasInformes (1)'!C840 -> 279902 | D166: =+'TablasInformes (1)'!D840 -> 518544 | E166: =+'TablasInformes (1)'!E840 -> 1661827 | F166: =+'TablasInformes (1)'!F840 -> 514418 | G166: =+'TablasInformes (1)'!G840 -> 609297 | H166: =+'TablasInformes (1)'!H840 -> 2396464 | I166: =+'TablasInformes (1)'!I840 -> 757885 | ... S166: =+'TablasInformes (1)'!S840 -> 1025248
A167: Deportistas | B167: =+'TablasInformes (1)'!B841 -> 386604 | C167: =+'TablasInformes (1)'!C841 -> 789856 | D167: =+'TablasInformes (1)'!D841 -> 136272 | E167: =+'TablasInformes (1)'!E841 -> 507443 | F167: =+'TablasInformes (1)'!F841 -> 600373 | G167: =+'TablasInformes (1)'!G841 -> 159291 | H167: =+'TablasInformes (1)'!H841 -> 709593 | I167: =+'TablasInformes (1)'!I841 -> 725804 | ... S167: =+'TablasInformes (1)'!S841 -> 326946
A168: Total segmentos | B168: =+'TablasInformes (1)'!B842 -> 4261589 | C168: =+'TablasInformes (1)'!C842 -> 1402994 | D168: =+'TablasInformes (1)'!D842 -> 976565 | E168: =+'TablasInformes (1)'!E842 -> 4291418 | F168: =+'TablasInformes (1)'!F842 -> 1434277 | G168: =+'TablasInformes (1)'!G842 -> 1114821 | H168: =+'TablasInformes (1)'!H842 -> 5035848 | I168: =+'TablasInformes (1)'!I842 -> 1814240 | ... S168: =+'TablasInformes (1)'!S842 -> 1721926

Sheet 61 - 66
A1: 61
A2: Ingresos por compania y mercado. Drink2Go
B3: =+'TablasInformes (1)'!B846 -> 2023 | C3: =+'TablasInformes (1)'!C846 -> 2023 | D3: =+'TablasInformes (1)'!D846 -> 2024 | E3: =+'TablasInformes (1)'!E846 -> 2024 | F3: =+'TablasInformes (1)'!F846 -> 2025 | G3: =+'TablasInformes (1)'!G846 -> 2025 | H3: =+'TablasInformes (1)'!H846 -> 2026 | I3: =+'TablasInformes (1)'!I846 -> 2026 | ... M3: =+'TablasInformes (1)'!M846 -> 2028
A4: Espana | B4: =+'TablasInformes (1)'!B848 -> 3976134 | C4: =+'TablasInformes (1)'!C848 -> 0.054 | D4: =+'TablasInformes (1)'!D848 -> 4001174 | E4: =+'TablasInformes (1)'!E848 -> 0.006 | F4: =+'TablasInformes (1)'!F848 -> 4566013 | G4: =+'TablasInformes (1)'!G848 -> 0.141 | H4: =+'TablasInformes (1)'!H848 -> 3960301 | I4: =+'TablasInformes (1)'!I848 -> -0.133 | ... M4: =+'TablasInformes (1)'!M848 -> -0.02
A5: Portugal | B5: =+'TablasInformes (1)'!B849 -> 828448 | C5: =+'TablasInformes (1)'!C849 -> 0.002 | D5: =+'TablasInformes (1)'!D849 -> 822375 | E5: =+'TablasInformes (1)'!E849 -> -0.007 | F5: =+'TablasInformes (1)'!F849 -> 741480 | G5: =+'TablasInformes (1)'!G849 -> -0.098 | H5: =+'TablasInformes (1)'!H849 -> 664000 | I5: =+'TablasInformes (1)'!I849 -> -0.104 | ... M5: =+'TablasInformes (1)'!M849 -> 0.222
A6: Francia | B6: =+'TablasInformes (1)'!B850 -> 3171451 | C6: =+'TablasInformes (1)'!C850 -> 0.027 | D6: =+'TablasInformes (1)'!D850 -> 2941689 | E6: =+'TablasInformes (1)'!E850 -> -0.072 | F6: =+'TablasInformes (1)'!F850 -> 3058114 | G6: =+'TablasInformes (1)'!G850 -> 0.004 | H6: =+'TablasInformes (1)'!H850 -> 2562803 | I6: =+'TablasInformes (1)'!I850 -> -0.162 | ... M6: =+'TablasInformes (1)'!M850 -> 0.145
A7: Italia | B7: =+'TablasInformes (1)'!B851 -> 0 | C7: =+'TablasInformes (1)'!C851 -> 0 | D7: =+'TablasInformes (1)'!D851 -> 3022663 | E7: =+'TablasInformes (1)'!E851 -> 0 | F7: =+'TablasInformes (1)'!F851 -> 5621306 | G7: =+'TablasInformes (1)'!G851 -> 0.086 | H7: =+'TablasInformes (1)'!H851 -> 7014855 | I7: =+'TablasInformes (1)'!I851 -> 0.248 | ... M7: =+'TablasInformes (1)'!M851 -> -0.058
A8: Centro Europa | B8: =+'TablasInformes (1)'!B852 -> 0 | C8: =+'TablasInformes (1)'!C852 -> 0 | D8: =+'TablasInformes (1)'!D852 -> 0 | E8: =+'TablasInformes (1)'!E852 -> 0 | F8: =+'TablasInformes (1)'!F852 -> 0 | G8: =+'TablasInformes (1)'!G852 -> 0 | H8: =+'TablasInformes (1)'!H852 -> 0 | I8: =+'TablasInformes (1)'!I852 -> 0 | ... M8: =+'TablasInformes (1)'!M852 -> 0.695
A9: Polonia | B9: =+'TablasInformes (1)'!B853 -> 0 | C9: =+'TablasInformes (1)'!C853 -> 0 | D9: =+'TablasInformes (1)'!D853 -> 0 | E9: =+'TablasInformes (1)'!E853 -> 0 | F9: =+'TablasInformes (1)'!F853 -> 0 | G9: =+'TablasInformes (1)'!G853 -> 0 | H9: =+'TablasInformes (1)'!H853 -> 1525033 | I9: =+'TablasInformes (1)'!I853 -> 0 | ... M9: =+'TablasInformes (1)'!M853 -> 0.389
A10: Mexico | B10: =+'TablasInformes (1)'!B854 -> 0 | C10: =+'TablasInformes (1)'!C854 -> 0 | D10: =+'TablasInformes (1)'!D854 -> 0 | E10: =+'TablasInformes (1)'!E854 -> 0 | F10: =+'TablasInformes (1)'!F854 -> 2620717 | G10: =+'TablasInformes (1)'!G854 -> 0 | H10: =+'TablasInformes (1)'!H854 -> 4231028 | I10: =+'TablasInformes (1)'!I854 -> 0.615 | ... M10: =+'TablasInformes (1)'!M854 -> 0.076
A11: Total ingresos compania | B11: =+'TablasInformes (1)'!B855 -> 7976033 | C11: =+'TablasInformes (1)'!C855 -> 0.037 | D11: =+'TablasInformes (1)'!D855 -> 10787901 | E11: =+'TablasInformes (1)'!E855 -> 0.353 | F11: =+'TablasInformes (1)'!F855 -> 16607629 | G11: =+'TablasInformes (1)'!G855 -> 0.054 | H11: =+'TablasInformes (1)'!H855 -> 19958018 | I11: =+'TablasInformes (1)'!I855 -> 0.202 | ... M11: =+'TablasInformes (1)'!M855 -> 0.085
A32: 62
A33: Ingresos por mercado y producto. Drink2Go
B34: Refrescos | C34: Isotonicas | D34: Zumos
A35: Espana | B35: =+'TablasInformes (1)'!B860 -> 1947966 | C35: =+'TablasInformes (1)'!C860 -> 757150 | D35: =+'TablasInformes (1)'!D860 -> 735082
A36: Portugal | B36: =+'TablasInformes (1)'!B861 -> 501603 | C36: =+'TablasInformes (1)'!C861 -> 80291 | D36: =+'TablasInformes (1)'!D861 -> 210101
A37: Francia | B37: =+'TablasInformes (1)'!B862 -> 1444671 | C37: =+'TablasInformes (1)'!C862 -> 665742 | D37: =+'TablasInformes (1)'!D862 -> 414233
A38: Italia | B38: =+'TablasInformes (1)'!B863 -> 3436237 | C38: =+'TablasInformes (1)'!C863 -> 1410052 | D38: =+'TablasInformes (1)'!D863 -> 1068130
A39: Centro Europa | B39: =+'TablasInformes (1)'!B864 -> 862566 | C39: =+'TablasInformes (1)'!C864 -> 228259 | D39: =+'TablasInformes (1)'!D864 -> 76937
A40: Polonia | B40: =+'TablasInformes (1)'!B865 -> 1245671 | C40: =+'TablasInformes (1)'!C865 -> 1072192 | D40: =+'TablasInformes (1)'!D865 -> 748094
A41: Mexico | B41: =+'TablasInformes (1)'!B866 -> 2963644 | C41: =+'TablasInformes (1)'!C866 -> 962976 | D41: =+'TablasInformes (1)'!D866 -> 686394
A42: Total ingresos | B42: =+'TablasInformes (1)'!B867 -> 12402359 | C42: =+'TablasInformes (1)'!C867 -> 5176663 | D42: =+'TablasInformes (1)'!D867 -> 3938970
A50: 63
A51: Ingresos por mercado y canal. Drink2Go
B52: Tienda Tradicional | C52: Gran Superficie | D52: Hosteleria
A53: Espana | B53: =+'TablasInformes (1)'!B872 -> 1620962 | C53: =+'TablasInformes (1)'!C872 -> 1278035 | D53: =+'TablasInformes (1)'!D872 -> 541201
A54: Portugal | B54: =+'TablasInformes (1)'!B873 -> 301781 | C54: =+'TablasInformes (1)'!C873 -> 380885 | D54: =+'TablasInformes (1)'!D873 -> 109329
A55: Francia | B55: =+'TablasInformes (1)'!B874 -> 962006 | C55: =+'TablasInformes (1)'!C874 -> 1094754 | D55: =+'TablasInformes (1)'!D874 -> 467887
A56: Italia | B56: =+'TablasInformes (1)'!B875 -> 2209550 | C56: =+'TablasInformes (1)'!C875 -> 2948325 | D56: =+'TablasInformes (1)'!D875 -> 756544
A57: Centro Europa | B57: =+'TablasInformes (1)'!B876 -> 379978 | C57: =+'TablasInformes (1)'!C876 -> 612538 | D57: =+'TablasInformes (1)'!D876 -> 175246
A58: Polonia | B58: =+'TablasInformes (1)'!B877 -> 887373 | C58: =+'TablasInformes (1)'!C877 -> 1841313 | D58: =+'TablasInformes (1)'!D877 -> 337271
A59: Mexico | B59: =+'TablasInformes (1)'!B878 -> 1699868 | C59: =+'TablasInformes (1)'!C878 -> 2138330 | D59: =+'TablasInformes (1)'!D878 -> 774817
A60: Total ingresos | B60: =+'TablasInformes (1)'!B879 -> 8061518 | C60: =+'TablasInformes (1)'!C879 -> 10294179 | D60: =+'TablasInformes (1)'!D879 -> 3162294
A71: 64
A72: Ingresos por producto. Drink2Go
B73: =+'TablasInformes (1)'!B883 -> 2023 | C73: =+'TablasInformes (1)'!C883 -> 2024 | D73: =+'TablasInformes (1)'!D883 -> 2025 | E73: =+'TablasInformes (1)'!E883 -> 2026 | F73: =+'TablasInformes (1)'!F883 -> 2027 | G73: =+'TablasInformes (1)'!G883 -> 2028
A74: Refrescos | B74: =+'TablasInformes (1)'!B885 -> 4150048 | C74: =+'TablasInformes (1)'!C885 -> 5448064 | D74: =+'TablasInformes (1)'!D885 -> 8678562 | E74: =+'TablasInformes (1)'!E885 -> 10664366 | F74: =+'TablasInformes (1)'!F885 -> 10519803 | G74: =+'TablasInformes (1)'!G885 -> 12402359
A75: Isotonicas | B75: =+'TablasInformes (1)'!B886 -> 2055950 | C75: =+'TablasInformes (1)'!C886 -> 2688542 | D75: =+'TablasInformes (1)'!D886 -> 4414969 | E75: =+'TablasInformes (1)'!E886 -> 4891159 | F75: =+'TablasInformes (1)'!F886 -> 5061799 | G75: =+'TablasInformes (1)'!G886 -> 5176663
A76: Zumos | B76: =+'TablasInformes (1)'!B887 -> 1770035 | C76: =+'TablasInformes (1)'!C887 -> 2651296 | D76: =+'TablasInformes (1)'!D887 -> 3514098 | E76: =+'TablasInformes (1)'!E887 -> 4402493 | F76: =+'TablasInformes (1)'!F887 -> 4247517 | G76: =+'TablasInformes (1)'!G887 -> 3938970
A77: Total productos | B77: =+'TablasInformes (1)'!B888 -> 7976033 | C77: =+'TablasInformes (1)'!C888 -> 10787901 | D77: =+'TablasInformes (1)'!D888 -> 16607629 | E77: =+'TablasInformes (1)'!E888 -> 19958018 | F77: =+'TablasInformes (1)'!F888 -> 19829118 | G77: =+'TablasInformes (1)'!G888 -> 21517990
A91: 65
A92: Ingresos por compania. Drink2Go
B93: Tienda Tradicional | C93: Gran Superficie | D93: Hosteleria
A94: Refrescos | B94: =+'TablasInformes (1)'!B893 -> 4848152 | C94: =+'TablasInformes (1)'!C893 -> 5797457 | D94: =+'TablasInformes (1)'!D893 -> 1756749
A95: Isotonicas | B95: =+'TablasInformes (1)'!B894 -> 1736892 | C95: =+'TablasInformes (1)'!C894 -> 2583667 | D95: =+'TablasInformes (1)'!D894 -> 856104
A96: Zumos | B96: =+'TablasInformes (1)'!B895 -> 1476474 | C96: =+'TablasInformes (1)'!C895 -> 1913055 | D96: =+'TablasInformes (1)'!D895 -> 549441
A97: Total ingresos | B97: =+'TablasInformes (1)'!B896 -> 8061518 | C97: =+'TablasInformes (1)'!C896 -> 10294179 | D97: =+'TablasInformes (1)'!D896 -> 3162294
A98: - Variacion | B98: =+'TablasInformes (1)'!B897 -> 0.112 | C98: =+'TablasInformes (1)'!C897 -> 0.004 | D98: =+'TablasInformes (1)'!D897 -> 0.018
A107: 66
A108: Desglose de ingresos Drink2Go
C109: =+'TablasInformes (1)'!C901 -> 2027 | D109: =+'TablasInformes (1)'!D901 -> 2027 | E109: =+'TablasInformes (1)'!E901 -> 2027 | F109: =+'TablasInformes (1)'!F901 -> 2028 | G109: =+'TablasInformes (1)'!G901 -> 2028 | H109: =+'TablasInformes (1)'!H901 -> 2028
C110: Refrescos | D110: Isotonicas | E110: Zumos | F110: Refrescos | G110: Isotonicas | H110: Zumos
A111: Espana | B111: Tienda Tradicional | C111: 1015700 | D111: 273699 | E111: 331563 | F111: 966414 | G111: 240089 | H111: 371583
B112: Gran Superficie | C112: 654004 | D112: 319305 | E112: 304726 | F112: 724584 | G112: 304708 | H112: 390661
B113: Hosteleria | C113: 278262 | D113: 164147 | E113: 98793 | F113: 260544 | G113: 140419 | H113: 111079
A114: Portugal | B114: Tienda Tradicional | C114: 212636 | D114: 20982 | E114: 68163 | F114: 154630 | G114: 18601 | H114: 74739
B115: Gran Superficie | C115: 226868 | D115: 42375 | E115: 111642 | F115: 156599 | G115: 35920 | H115: 119323
B116: Hosteleria | C116: 62099 | D116: 16934 | E116: 30296 | F116: 41234 | G116: 14413 | H116: 32648
A117: Francia | B117: Tienda Tradicional | C117: 634576 | D117: 189377 | E117: 138052 | F117: 491781 | G117: 180207 | H117: 151302
B118: Gran Superficie | C118: 595503 | D118: 304116 | E118: 195135 | F118: 470427 | G118: 286486 | H118: 218391
B119: Hosteleria | C119: 214592 | D119: 172249 | E119: 81045 | F119: 167087 | G119: 154037 | H119: 86170
A120: Italia | B120: Tienda Tradicional | C120: 1244245 | D120: 534060 | E120: 431245 | F120: 1080658 | G120: 606755 | H120: 611415
B121: Gran Superficie | C121: 1735296 | D121: 694137 | E121: 518892 | F121: 1637990 | G121: 804640 | H121: 844101
B122: Hosteleria | C122: 456696 | D122: 181855 | E122: 117993 | F122: 350440 | G122: 187396 | H122: 156495
A123: Centro Europa | B123: Tienda Tradicional | C123: 282910 | D123: 74018 | E123: 23050 | F123: 161778 | G123: 47615 | H123: 11794
B124: Gran Superficie | C124: 449573 | D124: 120545 | E124: 42421 | F124: 263643 | G124: 77888 | H124: 19751
B125: Hosteleria | C125: 130083 | D125: 33696 | E125: 11467 | F125: 78137 | G125: 22580 | H125: 5726
A126: Polonia | B126: Tienda Tradicional | C126: 389642 | D126: 290613 | E126: 207118 | F126: 325221 | G126: 213138 | H126: 105734
B127: Gran Superficie | C127: 723802 | D127: 660093 | E127: 457418 | F127: 601610 | G127: 469778 | H127: 271067
B128: Hosteleria | C128: 132227 | D128: 121486 | E128: 83558 | F128: 93164 | G128: 83043 | H128: 45422
A129: Mexico | B129: Tienda Tradicional | C129: 1068442 | D129: 354143 | E129: 277282 | F129: 826753 | G129: 389762 | H129: 221778
B130: Gran Superficie | C130: 1412412 | D130: 443095 | E130: 282822 | F130: 1296721 | G130: 603935 | H130: 298406
B131: Hosteleria | C131: 482790 | D131: 165738 | E131: 126289 | F131: 370387 | G131: 180388 | H131: 99936

Sheet 67 - 73
A1: 67
A2: Cuenta de Resultados de la Compania Drink2Go
B3: =+'TablasInformes (1)'!B927 -> 2023 | C3: =+'TablasInformes (1)'!C927 -> 2024 | D3: =+'TablasInformes (1)'!D927 -> 2025 | E3: =+'TablasInformes (1)'!E927 -> 2026 | F3: =+'TablasInformes (1)'!F927 -> 2027 | G3: =+'TablasInformes (1)'!G927 -> 2028
A4: Ingresos Totales | B4: =+'TablasInformes (1)'!B929 -> 7976033 | C4: =+'TablasInformes (1)'!C929 -> 10787901 | D4: =+'TablasInformes (1)'!D929 -> 16607629 | E4: =+'TablasInformes (1)'!E929 -> 19958018 | F4: =+'TablasInformes (1)'!F929 -> 19829118 | G4: =+'TablasInformes (1)'!G929 -> 21517990
A5: Costes de Produccion | B5: =+'TablasInformes (1)'!B930 -> 2178934 | C5: =+'TablasInformes (1)'!C930 -> 1946781 | D5: =+'TablasInformes (1)'!D930 -> 2273503 | E5: =+'TablasInformes (1)'!E930 -> 2110921 | F5: =+'TablasInformes (1)'!F930 -> 2342845 | G5: =+'TablasInformes (1)'!G930 -> 2330088
A6: Costes Logisticos | B6: =+'TablasInformes (1)'!B931 -> 530811 | C6: =+'TablasInformes (1)'!C931 -> 612307 | D6: =+'TablasInformes (1)'!D931 -> 889558 | E6: =+'TablasInformes (1)'!E931 -> 1094731 | F6: =+'TablasInformes (1)'!F931 -> 1442761 | G6: =+'TablasInformes (1)'!G931 -> 1509609
A7: Margen Bruto | B7: =+'TablasInformes (1)'!B932 -> 5266288 | C7: =+'TablasInformes (1)'!C932 -> 8228813 | D7: =+'TablasInformes (1)'!D932 -> 13444568 | E7: =+'TablasInformes (1)'!E932 -> 16752366 | F7: =+'TablasInformes (1)'!F932 -> 16043512 | G7: =+'TablasInformes (1)'!G932 -> 17678294
A8: Margen sobre Ingresos | B8: =+'TablasInformes (1)'!B933 -> 0.66 | C8: =+'TablasInformes (1)'!C933 -> 0.76 | D8: =+'TablasInformes (1)'!D933 -> 0.81 | E8: =+'TablasInformes (1)'!E933 -> 0.84 | F8: =+'TablasInformes (1)'!F933 -> 0.81 | G8: =+'TablasInformes (1)'!G933 -> 0.82
A9: Gastos de Marketing | B9: =+'TablasInformes (1)'!B934 -> 1223530 | C9: =+'TablasInformes (1)'!C934 -> 1827967 | D9: =+'TablasInformes (1)'!D934 -> 4112474 | E9: =+'TablasInformes (1)'!E934 -> 4603239 | F9: =+'TablasInformes (1)'!F934 -> 5568433 | G9: =+'TablasInformes (1)'!G934 -> 8201000
A10: Gastos de Personal | B10: =+'TablasInformes (1)'!B935 -> 1042270 | C10: =+'TablasInformes (1)'!C935 -> 1337912 | D10: =+'TablasInformes (1)'!D935 -> 2035508 | E10: =+'TablasInformes (1)'!E935 -> 2696273 | F10: =+'TablasInformes (1)'!F935 -> 2826239 | G10: =+'TablasInformes (1)'!G935 -> 3519586
A11: Gastos Innovacion | B11: =+'TablasInformes (1)'!B936 -> 1392445 | C11: =+'TablasInformes (1)'!C936 -> 971720 | D11: =+'TablasInformes (1)'!D936 -> 2039144 | E11: =+'TablasInformes (1)'!E936 -> 2713324 | F11: =+'TablasInformes (1)'!F936 -> 3460937 | G11: =+'TablasInformes (1)'!G936 -> 4209891
A12: Gastos Generales | B12: =+'TablasInformes (1)'!B937 -> 760343 | C12: =+'TablasInformes (1)'!C937 -> 990911 | D12: =+'TablasInformes (1)'!D937 -> 1834687 | E12: =+'TablasInformes (1)'!E937 -> 1836222 | F12: =+'TablasInformes (1)'!F937 -> 1784621 | G12: =+'TablasInformes (1)'!G937 -> 1936619
A13: Total Gastos Explotacion | B13: =+'TablasInformes (1)'!B938 -> 4418589 | C13: =+'TablasInformes (1)'!C938 -> 5128510 | D13: =+'TablasInformes (1)'!D938 -> 10021813 | E13: =+'TablasInformes (1)'!E938 -> 11849057 | F13: =+'TablasInformes (1)'!F938 -> 13640230 | G13: =+'TablasInformes (1)'!G938 -> 17867096
A14: Resultado Bruto | B14: =+'TablasInformes (1)'!B939 -> 847700 | C14: =+'TablasInformes (1)'!C939 -> 3100303 | D14: =+'TablasInformes (1)'!D939 -> 3422755 | E14: =+'TablasInformes (1)'!E939 -> 4903309 | F14: =+'TablasInformes (1)'!F939 -> 2403283 | G14: =+'TablasInformes (1)'!G939 -> -188802
A15: Gastos de Depreciacion | B15: =+'TablasInformes (1)'!B940 -> 427500 | C15: =+'TablasInformes (1)'!C940 -> 462000 | D15: =+'TablasInformes (1)'!D940 -> 626000 | E15: =+'TablasInformes (1)'!E940 -> 695000 | F15: =+'TablasInformes (1)'!F940 -> 764000 | G15: =+'TablasInformes (1)'!G940 -> 833000
... A17: Resultado Neto | B17: =+'TablasInformes (1)'!B942 -> 184751 | C17: =+'TablasInformes (1)'!C942 -> 2217466 | D17: =+'TablasInformes (1)'!D942 -> 2182566 | E17: =+'TablasInformes (1)'!E942 -> 3699908 | F17: =+'TablasInformes (1)'!F942 -> 1244268 | G17: =+'TablasInformes (1)'!G942 -> -1479023
A29: 68
A30: Cuenta de Resultados de la Compania. Comparativa.
B31: GlobalBiz | C31: FreshMarket | D31: SparklingCo | E31: QualityMax | F31: Drink2Go
A32: Ingresos Totales | B32: =+'TablasInformes (1)'!B947 -> 27027948 | C32: =+'TablasInformes (1)'!C947 -> 23052926 | D32: =+'TablasInformes (1)'!D947 -> 20193200 | E32: =+'TablasInformes (1)'!E947 -> 20913542 | F32: =+'TablasInformes (1)'!F947 -> 21517990
A33: Costes de Produccion | B33: =+'TablasInformes (1)'!B948 -> 3169076 | C33: =+'TablasInformes (1)'!C948 -> 3829937 | D33: =+'TablasInformes (1)'!D948 -> 2991682 | E33: =+'TablasInformes (1)'!E948 -> 2355328 | F33: =+'TablasInformes (1)'!F948 -> 2330088
A34: Costes Logisticos | B34: =+'TablasInformes (1)'!B949 -> 1712430 | C34: =+'TablasInformes (1)'!C949 -> 2358333 | D34: =+'TablasInformes (1)'!D949 -> 1396118 | E34: =+'TablasInformes (1)'!E949 -> 1630791 | F34: =+'TablasInformes (1)'!F949 -> 1509609
A35: Margen Bruto | B35: =+'TablasInformes (1)'!B950 -> 22146442 | C35: =+'TablasInformes (1)'!C950 -> 16864656 | D35: =+'TablasInformes (1)'!D950 -> 15805399 | E35: =+'TablasInformes (1)'!E950 -> 16927424 | F35: =+'TablasInformes (1)'!F950 -> 17678294
A36: Margen sobre Ingresos | B36: =+'TablasInformes (1)'!B951 -> 0.82 | C36: =+'TablasInformes (1)'!C951 -> 0.73 | D36: =+'TablasInformes (1)'!D951 -> 0.78 | E36: =+'TablasInformes (1)'!E951 -> 0.81 | F36: =+'TablasInformes (1)'!F951 -> 0.82
A37: Gastos de Marketing | B37: =+'TablasInformes (1)'!B952 -> 5055572 | C37: =+'TablasInformes (1)'!C952 -> 4945517 | D37: =+'TablasInformes (1)'!D952 -> 4011000 | E37: =+'TablasInformes (1)'!E952 -> 2958773 | F37: =+'TablasInformes (1)'!F952 -> 8201000
A38: Gastos de Personal | B38: =+'TablasInformes (1)'!B953 -> 1557847 | C38: =+'TablasInformes (1)'!C953 -> 2028873 | D38: =+'TablasInformes (1)'!D953 -> 1440011 | E38: =+'TablasInformes (1)'!E953 -> 1361140 | F38: =+'TablasInformes (1)'!F953 -> 3519586
A39: Gastos Innovacion | B39: =+'TablasInformes (1)'!B954 -> 4401980 | C39: =+'TablasInformes (1)'!C954 -> 1254455 | D39: =+'TablasInformes (1)'!D954 -> 3326400 | E39: =+'TablasInformes (1)'!E954 -> 3553320 | F39: =+'TablasInformes (1)'!F954 -> 4209891
A40: Gastos Generales | B40: =+'TablasInformes (1)'!B955 -> 2482515 | C40: =+'TablasInformes (1)'!C955 -> 2074763 | D40: =+'TablasInformes (1)'!D955 -> 1887388 | E40: =+'TablasInformes (1)'!E955 -> 1882219 | F40: =+'TablasInformes (1)'!F955 -> 1936619
A41: Total Gastos Explotacion | B41: =+'TablasInformes (1)'!B956 -> 13497914 | C41: =+'TablasInformes (1)'!C956 -> 10303609 | D41: =+'TablasInformes (1)'!D956 -> 10664799 | E41: =+'TablasInformes (1)'!E956 -> 9755452 | F41: =+'TablasInformes (1)'!F956 -> 17867096
A42: Resultado Bruto | B42: =+'TablasInformes (1)'!B957 -> 8648527 | C42: =+'TablasInformes (1)'!C957 -> 6561048 | D42: =+'TablasInformes (1)'!D957 -> 5140601 | E42: =+'TablasInformes (1)'!E957 -> 7171972 | F42: =+'TablasInformes (1)'!F957 -> -188802
A43: Gastos de Depreciacion | B43: =+'TablasInformes (1)'!B958 -> 907000 | C43: =+'TablasInformes (1)'!C958 -> 950500 | D43: =+'TablasInformes (1)'!D958 -> 879000 | E43: =+'TablasInformes (1)'!E958 -> 740000 | F43: =+'TablasInformes (1)'!F958 -> 833000
... A45: Resultado Neto | B45: =+'TablasInformes (1)'!B960 -> 6991802 | C45: =+'TablasInformes (1)'!C960 -> 4827083 | D45: =+'TablasInformes (1)'!D960 -> 3309868 | E45: =+'TablasInformes (1)'!E960 -> 6033841 | F45: =+'TablasInformes (1)'!F960 -> -1479023
A69: 69
A70: Balance de Situacion de la Compania Drink2Go
B71: =+'TablasInformes (1)'!B964 -> 2023 | C71: =+'TablasInformes (1)'!C964 -> 2024 | D71: =+'TablasInformes (1)'!D964 -> 2025 | E71: =+'TablasInformes (1)'!E964 -> 2026 | F71: =+'TablasInformes (1)'!F964 -> 2027 | G71: =+'TablasInformes (1)'!G964 -> 2028
A72: Inventario | B72: =+'TablasInformes (1)'!B966 -> 70664 | C72: =+'TablasInformes (1)'!C966 -> 116992 | D72: =+'TablasInformes (1)'!D966 -> 209589 | E72: =+'TablasInformes (1)'!E966 -> 244176 | F72: =+'TablasInformes (1)'!F966 -> 221669 | G72: =+'TablasInformes (1)'!G966 -> 234046
A73: Clientes | B73: =+'TablasInformes (1)'!B967 -> 1323863 | C73: =+'TablasInformes (1)'!C967 -> 1779806 | D73: =+'TablasInformes (1)'!D967 -> 2770284 | E73: =+'TablasInformes (1)'!E967 -> 3290117 | F73: =+'TablasInformes (1)'!F967 -> 3288231 | G73: =+'TablasInformes (1)'!G967 -> 3554629
A74: Efectivo y equivalentes | B74: =+'TablasInformes (1)'!B968 -> 0 | C74: =+'TablasInformes (1)'!C968 -> 5474396 | D74: =+'TablasInformes (1)'!D968 -> 892073 | E74: =+'TablasInformes (1)'!E968 -> 1678058 | F74: =+'TablasInformes (1)'!F968 -> 474024 | G74: =+'TablasInformes (1)'!G968 -> 0
A75: Total Corriente | B75: =+'TablasInformes (1)'!B969 -> 1394527 | C75: =+'TablasInformes (1)'!C969 -> 7371194 | D75: =+'TablasInformes (1)'!D969 -> 3871945 | E75: =+'TablasInformes (1)'!E969 -> 5212352 | F75: =+'TablasInformes (1)'!F969 -> 3983924 | G75: =+'TablasInformes (1)'!G969 -> 3788675
A76: Activo Fijo Bruto | B76: =+'TablasInformes (1)'!B970 -> 25999000 | C76: =+'TablasInformes (1)'!C970 -> 26344000 | D76: =+'TablasInformes (1)'!D970 -> 34673000 | E76: =+'TablasInformes (1)'!E970 -> 35363000 | F76: =+'TablasInformes (1)'!F970 -> 36053000 | G76: =+'TablasInformes (1)'!G970 -> 36743000
A77: Amortizacion Acumulada | B77: =+'TablasInformes (1)'!B971 -> 8734700 | C77: =+'TablasInformes (1)'!C971 -> 9196700 | D77: =+'TablasInformes (1)'!D971 -> 9788200 | E77: =+'TablasInformes (1)'!E971 -> 10379700 | F77: =+'TablasInformes (1)'!F971 -> 10971200 | G77: =+'TablasInformes (1)'!G971 -> 11562700
A78: Activo Fijo Neto | B78: =+'TablasInformes (1)'!B972 -> 17264300 | C78: =+'TablasInformes (1)'!C972 -> 17147300 | D78: =+'TablasInformes (1)'!D972 -> 24884800 | E78: =+'TablasInformes (1)'!E972 -> 24983300 | F78: =+'TablasInformes (1)'!F972 -> 25081800 | G78: =+'TablasInformes (1)'!G972 -> 25180300
A79: Activo Total | B79: =+'TablasInformes (1)'!B973 -> 18658826 | C79: =+'TablasInformes (1)'!C973 -> 24518494 | D79: =+'TablasInformes (1)'!D973 -> 28756744 | E79: =+'TablasInformes (1)'!E973 -> 30195652 | F79: =+'TablasInformes (1)'!F973 -> 29065724 | G79: =+'TablasInformes (1)'!G973 -> 28968974
A80: Capital | B80: =+'TablasInformes (1)'!B974 -> 14373803 | C80: =+'TablasInformes (1)'!C974 -> 14443085 | D80: =+'TablasInformes (1)'!D974 -> 15108325 | E80: =+'TablasInformes (1)'!E974 -> 16745249 | F80: =+'TablasInformes (1)'!F974 -> 19520180 | G80: =+'TablasInformes (1)'!G974 -> 20453380
A81: Beneficio Neto | B81: =+'TablasInformes (1)'!B975 -> 184751 | C81: =+'TablasInformes (1)'!C975 -> 2217466 | D81: =+'TablasInformes (1)'!D975 -> 2182566 | E81: =+'TablasInformes (1)'!E975 -> 3699908 | F81: =+'TablasInformes (1)'!F975 -> 1244268 | G81: =+'TablasInformes (1)'!G975 -> -1479023
A82: Prestamo a corto plazo | B82: =+'TablasInformes (1)'!B976 -> 0 | C82: =+'TablasInformes (1)'!C976 -> 50000 | D82: =+'TablasInformes (1)'!D976 -> 500000 | E82: =+'TablasInformes (1)'!E976 -> 500000 | F82: =+'TablasInformes (1)'!F976 -> 0 | G82: =+'TablasInformes (1)'!G976 -> 500000
A83: Credito Extraordinario | B83: =+'TablasInformes (1)'!B977 -> 291157 | C83: =+'TablasInformes (1)'!C977 -> 0 | D83: =+'TablasInformes (1)'!D977 -> 0 | E83: =+'TablasInformes (1)'!E977 -> 0 | F83: =+'TablasInformes (1)'!F977 -> 0 | G83: =+'TablasInformes (1)'!G977 -> 1002075
... A86: Patrimonio Neto + Pasivo | B86: =+'TablasInformes (1)'!B980 -> 18658826 | C86: =+'TablasInformes (1)'!C980 -> 24518494 | D86: =+'TablasInformes (1)'!D980 -> 28756744 | E86: =+'TablasInformes (1)'!E980 -> 30195652 | F86: =+'TablasInformes (1)'!F980 -> 29065724 | G86: =+'TablasInformes (1)'!G980 -> 28968974
A105: 70
A106: Ratio de Financieros. Resumen. Compania Drink2Go
B107: =+'TablasInformes (1)'!B984 -> 2027 | C107: =+'TablasInformes (1)'!C984 -> 2028
A108: Rentabilidad sobre Patrimonio | B108: =+'TablasInformes (1)'!B986 -> 0.045 | C108: =+'TablasInformes (1)'!C986 -> -0.078
A109: Rendimiento del Activo | B109: =+'TablasInformes (1)'!B987 -> 0.083 | C109: =+'TablasInformes (1)'!C987 -> -0.007
A110: Cobertura Fondo de Maniobra | B110: =+'TablasInformes (1)'!B988 -> 0.554 | C110: =+'TablasInformes (1)'!C988 -> 0.025
A111: Endeudamiento: Total Pasivo sobre Patrimonio | B111: =+'TablasInformes (1)'!B989 -> 4 | C111: =+'TablasInformes (1)'!C989 -> 5
A112: Pasivo Corriente sobre Pasivo Total | B112: =+'TablasInformes (1)'!B990 -> 0.214 | C112: =+'TablasInformes (1)'!C990 -> 0.37
A125: 71
A126: Condiciones financieras previstas.
C127: Valores
A128: Prestamo Largo Plazo | B128: Tipo de Interes | C128: =+'TablasInformes (1)'!C995 -> 0.6
A129: Prestamo Largo Plazo | B129: Plazo de Vencimiento - Anos | C129: =+'TablasInformes (1)'!C996 -> 8
A130: Credito Corto Plazo | B130: Tipo de Interes | C130: =+'TablasInformes (1)'!C997 -> 0.71
A131: Credito Corto Plazo | B131: Plazo de Vencimiento - Anos | C131: =+'TablasInformes (1)'!C998 -> 1
A132: Credito Extraordinario | B132: Tipo de Interes de Referencia | C132: =+'TablasInformes (1)'!C999 -> 0.96
A133: Credito Extraordinario | B133: Plazo de Vencimiento - Anos | C133: =+'TablasInformes (1)'!C1000 -> 1
A150: 72
A151: Analisis del inmovilizado por compania Drink2Go
B152: =+'TablasInformes (1)'!B1004 -> 2027 | C152: =+'TablasInformes (1)'!C1004 -> 2028
A153: Activo Fijo Inmaterial - Bruto | B153: =+'TablasInformes (1)'!B1006 -> 350000 | C153: =+'TablasInformes (1)'!C1006 -> 350000
A154: Activo Fijo Inmaterial - Amort Acum | B154: =+'TablasInformes (1)'!B1007 -> 241500 | C154: =+'TablasInformes (1)'!C1007 -> 255500
A155: Activo Fijo Inmaterial - Neto | B155: =+'TablasInformes (1)'!B1008 -> 108500 | C155: =+'TablasInformes (1)'!C1008 -> 94500
A156: Activo Fijo Central - Bruto | B156: =+'TablasInformes (1)'!B1009 -> 550000 | C156: =+'TablasInformes (1)'!C1009 -> 550000
A157: Activo Fijo Central - Amort Acum | B157: =+'TablasInformes (1)'!B1010 -> 423500 | C157: =+'TablasInformes (1)'!C1010 -> 462000
A158: Activo Fijo Central - Neto | B158: =+'TablasInformes (1)'!B1011 -> 126500 | C158: =+'TablasInformes (1)'!C1011 -> 88000
A159: Activo Fijo Fabricas- Bruto | B159: =+'TablasInformes (1)'!B1012 -> 35153000 | C159: =+'TablasInformes (1)'!C1012 -> 35843000
A160: Activo Fijo Fabrica - Amort Acum | B160: =+'TablasInformes (1)'!B1013 -> 10306200 | C160: =+'TablasInformes (1)'!C1013 -> 10845200
A161: Activo Fijo Fabricas- Neto | B161: =+'TablasInformes (1)'!B1014 -> 24846800 | C161: =+'TablasInformes (1)'!C1014 -> 24997800
A162: Activo Fijo Material - Bruto | B162: =+'TablasInformes (1)'!B1015 -> 35703000 | C162: =+'TablasInformes (1)'!C1015 -> 36393000
A163: Activo Fijo Material - Amort Acum | B163: =+'TablasInformes (1)'!B1016 -> 10729700 | C163: =+'TablasInformes (1)'!C1016 -> 11307200
A164: Activo Fijo Material - Neto | B164: =+'TablasInformes (1)'!B1017 -> 24973300 | C164: =+'TablasInformes (1)'!C1017 -> 25085800
... A167: Activo Fijo Total - Neto | B167: =+'TablasInformes (1)'!B1020 -> 25081800 | C167: =+'TablasInformes (1)'!C1020 -> 25180300
A188: 73
A189: Capacidades de la organización Drink2Go
B190: =+'TablasInformes (1)'!B1024 -> 2023 | C190: =+'TablasInformes (1)'!C1024 -> 2024 | D190: =+'TablasInformes (1)'!D1024 -> 2025 | E190: =+'TablasInformes (1)'!E1024 -> 2026 | F190: =+'TablasInformes (1)'!F1024 -> 2027 | G190: =+'TablasInformes (1)'!G1024 -> 2028
A191: Direccion | B191: =+'TablasInformes (1)'!B1026 -> 382 | C191: =+'TablasInformes (1)'!C1026 -> 486 | D191: =+'TablasInformes (1)'!D1026 -> 624 | E191: =+'TablasInformes (1)'!E1026 -> 787 | F191: =+'TablasInformes (1)'!F1026 -> 905 | G191: =+'TablasInformes (1)'!G1026 -> 891
A192: Markt-Cial | B192: =+'TablasInformes (1)'!B1027 -> 391 | C192: =+'TablasInformes (1)'!C1027 -> 492 | D192: =+'TablasInformes (1)'!D1027 -> 620 | E192: =+'TablasInformes (1)'!E1027 -> 781 | F192: =+'TablasInformes (1)'!F1027 -> 905 | G192: =+'TablasInformes (1)'!G1027 -> 896
A193: Innovacion | B193: =+'TablasInformes (1)'!B1028 -> 299 | C193: =+'TablasInformes (1)'!C1028 -> 377 | D193: =+'TablasInformes (1)'!D1028 -> 475 | E193: =+'TablasInformes (1)'!E1028 -> 599 | F193: =+'TablasInformes (1)'!F1028 -> 754 | G193: =+'TablasInformes (1)'!G1028 -> 896
A194: Produc-Logis | B194: =+'TablasInformes (1)'!B1029 -> 370 | C194: =+'TablasInformes (1)'!C1029 -> 466 | D194: =+'TablasInformes (1)'!D1029 -> 588 | E194: =+'TablasInformes (1)'!E1029 -> 740 | F194: =+'TablasInformes (1)'!F1029 -> 908 | G194: =+'TablasInformes (1)'!G1029 -> 896
